Workbook
Name BoxPlot: "BoxPlot"
Name Bubble: "Bubble"
Name Candlestick: "Candlestick"
Name Chart: "Chart"
Name ChartImage: "ChartImage"
Name ColumnRange: "ColumnRange"
Name Dumbbell: "Dumbbell"
Name Heatmap: "Heatmap"
Name Histogram: "Histogram"
Name Map: "Map"
Name OHLC: "OHLC"
Name PieChart: "PieChart"
Name Scatter: "Scatter"
Name Series: "Series"
Name Stripe: "Stripe"
Name Table: "Table"
Name TreeMap: "TreeMap"
Name Waterfall: "Waterfall"

Sheet before_after
A1: name | B1: public_rating | C1: model_rating_oct | D1: model_rating_dec | E1: model delta (rating notches, -ve = worse, +ve = better) | F1: Adjustment | G1: LS_rating | H1: LS_letter | I1: Analyst | J1: Gov_Factor 2023_old | K1: Gov_Factor_2023_new | L1: Gov_Factor_2024 | M1: Method Change | N1: Time Change | O1: Total Change | P1: Rating impact (x2.8) | Q1: Comments
A2: United States | B2: 21 | C2: 18.856549 | D2: 18.705977 | E2: =D2-C2 -> -0.15057239 | F2: 0 | G2: 18.705977 | H2: AA- | I2: BRIAN HORRIGAN | J2: 0.90987171 | K2: 0.83764433 | L2: 0.82855756 | M2: =K2-J2 -> -0.072227379 | N2: =L2-K2 -> -0.009086772 | O2: =M2+N2 -> -0.081314151 | P2: =O2*2.804471 -> -0.22804318
A3: United Kingdom | B3: 19.333333 | C3: 19.33286 | D3: 19.153396 | E3: =D3-C3 -> -0.1794638 | F3: 0 | G3: 19.153396 | H3: AA- | I3: JON LEVY | J3: 1.1678865 | K3: 1.1126805 | L3: 1.0991731 | M3: =K3-J3 -> -0.055206058 | N3: =L3-K3 -> -0.013507412 | O3: =M3+N3 -> -0.06871347 | P3: =O3*2.804471 -> -0.19270493
A4: Austria | B4: 20.666667 | C4: 18.750964 | D4: 18.723972 | E4: =D4-C4 -> -0.026991694 | F4: 0 | G4: 18.723972 | H4: AA- | I4: Not covered | J4: 1.2393602 | K4: 1.3053375 | L4: 1.2334629 | M4: =K4-J4 -> 0.065977335 | N4: =L4-K4 -> -0.071874579 | O4: =M4+N4 -> -0.0058972436 | P4: =O4*2.804471 -> -0.016538649
A5: Belgium | B5: 19 | C5: 17.424721 | D5: 17.541837 | E5: =D5-C5 -> 0.11711549 | F5: 0 | G5: 17.541837 | H5: A+ | I5: Not covered | J5: 1.0218825 | K5: 1.0734132 | L5: 1.0532288 | M5: =K5-J5 -> 0.051530707 | N5: =L5-K5 -> -0.020184446 | O5: =M5+N5 -> 0.031346261 | P5: =O5*2.804471 -> 0.087909679
A6: Denmark | B6: 22 | C6: 23.325837 | D6: 23.251883 | E6: =D6-C6 -> -0.07395359 | F6: 0 | G6: 22 | H6: AAA | I6: Not covered | J6: 1.7698904 | K6: 1.8503604 | L6: 1.7928139 | M6: =K6-J6 -> 0.080469966 | N6: =L6-K6 -> -0.057546497 | O6: =M6+N6 -> 0.022923469 | P6: =O6*2.804471 -> 0.064288203
A7: France | B7: 18.666667 | C7: 18.393059 | D7: 17.913243 | E7: =D7-C7 -> -0.47981588 | F7: 0.2 | G7: 18.113243 | H7: A+ | I7: JON LEVY | J7: 0.94904984 | K7: 0.90804671 | L7: 0.80220623 | M7: =K7-J7 -> -0.041003129 | N7: =L7-K7 -> -0.10584047 | O7: =M7+N7 -> -0.1468436 | P7: =O7*2.804471 -> -0.41181863
A8: Germany | B8: 22 | C8: 21.285506 | D8: 21.331576 | E8: =D8-C8 -> 0.046069524 | F8: 0.4 | G8: 21.731576 | H8: AAA | I8: JON LEVY | J8: 1.2672908 | K8: 1.3550906 | L8: 1.3012734 | M8: =K8-J8 -> 0.087799731 | N8: =L8-K8 -> -0.053817119 | O8: =M8+N8 -> 0.033982612 | P8: =O8*2.804471 -> 0.09530325
A9: Italy | B9: 14.333333 | C9: 16.48874 | D9: 16.575605 | E9: =D9-C9 -> 0.086865333 | F9: 0 | G9: 16.575605 | H9: A | I9: JON LEVY | J9: 0.54432528 | K9: 0.6127735 | L9: 0.54514429 | M9: =K9-J9 -> 0.068448226 | N9: =L9-K9 -> -0.067629215 | O9: =M9+N9 -> 0.00081901122 | P9: =O9*2.804471 -> 0.0022968932
A10: Luxembourg | B10: 22 | C10: 21.03868 | D10: 21.06722 | E10: =D10-C10 -> 0.028539926 | F10: 0 | G10: 21.06722 | H10: AA+ | I10: Not covered | J10: 1.6981916 | K10: 1.7308632 | L10: 1.7286095 | M10: =K10-J10 -> 0.032671661 | N10: =L10-K10 -> -0.0022537421 | O10: =M10+N10 -> 0.030417919 | P10: =O10*2.804471 -> 0.085306171
A11: Netherlands | B11: 22 | C11: 21.516545 | D11: 21.4562 | E11: =D11-C11 -> -0.060344247 | F11: 0 | G11: 21.4562 | H11: AA+ | I11: Not covered | J11: 1.4952929 | K11: 1.5334098 | L11: 1.4922354 | M11: =K11-J11 -> 0.038116857 | N11: =L11-K11 -> -0.041174408 | O11: =M11+N11 -> -0.0030575512 | P11: =O11*2.804471 -> -0.0085748136
A12: Norway | B12: 22 | C12: 23.834111 | D12: 23.741085 | E12: =D12-C12 -> -0.093025612 | F12: 0 | G12: 22 | H12: AAA | I12: JINGZHOU MENG | J12: 1.6551482 | K12: 1.7129826 | L12: 1.6972911 | M12: =K12-J12 -> 0.057834394 | N12: =L12-K12 -> -0.015691464 | O12: =M12+N12 -> 0.042142931 | P12: =O12*2.804471 -> 0.11818863
A13: Sweden | B13: 22 | C13: 21.825526 | D13: 21.812877 | E13: =D13-C13 -> -0.012648835 | F13: 0 | G13: 21.812877 | H13: AAA | I13: JINGZHOU MENG | J13: 1.5208156 | K13: 1.5655746 | L13: 1.5488989 | M13: =K13-J13 -> 0.044759028 | N13: =L13-K13 -> -0.016675688 | O13: =M13+N13 -> 0.02808334 | P13: =O13*2.804471 -> 0.078758913
... A23: Spain | B23: 17 | C23: 17.592002 | D23: 17.65874 | E23: =D23-C23 -> 0.066738639 | F23: 0 | G23: 17.65874 | H23: A+ | I23: JINGZHOU MENG | J23: 0.62668272 | K23: 0.68075657 | L23: 0.6376626 | M23: =K23-J23 -> 0.05407385 | N23: =L23-K23 -> -0.04309397 | O23: =M23+N23 -> 0.01097988 | P23: =O23*2.804471 -> 0.030792755
A24: Turkey | B24: 10 | C24: 12.005381 | D24: 11.604822 | E24: =D24-C24 -> -0.40055898 | F24: -0.5 | G24: 11.104822 | H24: BB | I24: HASSAN MALIK | J24: -0.80655186 | K24: -0.84427835 | L24: -0.88491213 | M24: =K24-J24 -> -0.037726488 | N24: =L24-K24 -> -0.040633775 | O24: =M24+N24 -> -0.078360263 | P24: =O24*2.804471 -> -0.21975909 | Q24: Due to higher weight to inflation coefficient
A25: Australia | B25: 22 | C25: 21.398345 | D25: 21.263648 | E25: =D25-C25 -> -0.1346965 | F25: 0.3 | G25: 21.563648 | H25: AAA | I25: KAIMIN KHAW | J25: 1.523677 | K25: 1.5355528 | L25: 1.4983284 | M25: =K25-J25 -> 0.011875844 | N25: =L25-K25 -> -0.037224448 | O25: =M25+N25 -> -0.025348605 | P25: =O25*2.804471 -> -0.071089427
A26: New Zealand | B26: 21.333333 | C26: 20.146832 | D26: 20.017221 | E26: =D26-C26 -> -0.12961173 | F26: 0.5 | G26: 20.517221 | H26: AA+ | I26: KAIMIN KHAW | J26: 1.7121728 | K26: 1.718652 | L26: 1.6817429 | M26: =K26-J26 -> 0.0064791924 | N26: =L26-K26 -> -0.03690917 | O26: =M26+N26 -> -0.030429978 | P26: =O26*2.804471 -> -0.08533999
A27: South Africa | B27: 10.333333 | C27: 11.835041 | D27: 11.937094 | E27: =D27-C27 -> 0.10205268 | F27: 0.5 | G27: 12.437094 | H27: BB+ | I27: HASSAN MALIK | J27: -0.29585497 | K27: -0.29134367 | L27: -0.28694899 | M27: =K27-J27 -> 0.0045113023 | N27: =L27-K27 -> 0.0043946763 | O27: =M27+N27 -> 0.0089059786 | P27: =O27*2.804471 -> 0.024976559
A28: Argentina | B28: 5.6666667 | C28: 8.5183684 | D28: 8.5219663 | E28: =D28-C28 -> 0.0035979133 | F28: -2.5 | G28: 6.0219663 | H28: CCC+ | I28: GREGORY HADJIAN | J28: -0.40125153 | K28: -0.29255747 | L28: -0.26466684 | M28: =K28-J28 -> 0.10869405 | N28: =L28-K28 -> 0.027890635 | O28: =M28+N28 -> 0.13658469 | P28: =O28*2.804471 -> 0.3830478
A29: Bolivia | B29: 3.6666667 | C29: 5.8755299 | D29: 6.3757781 | E29: =D29-C29 -> 0.50024824 | F29: -2.75 | G29: 3.6257781 | H29: CCC- | I29: GREGORY HADJIAN | J29: -0.99291646 | K29: -1.0056255 | L29: -1.1340894 | M29: =K29-J29 -> -0.012709062 | N29: =L29-K29 -> -0.12846386 | O29: =M29+N29 -> -0.14117292 | P29: =O29*2.804471 -> -0.39591536 | Q29: Sharp improvement in reserve buffers post data update
A30: Brazil | B30: 11.333333 | C30: 12.724257 | D30: 12.783663 | E30: =D30-C30 -> 0.059406075 | F30: -1 | G30: 11.783663 | H30: BB+ | I30: GREGORY HADJIAN | J30: -0.48766703 | K30: -0.50865034 | L30: -0.4855316 | M30: =K30-J30 -> -0.020983309 | N30: =L30-K30 -> 0.02311874 | O30: =M30+N30 -> 0.0021354309 | P30: =O30*2.804471 -> 0.0059887539
A31: Chile | B31: 16.666667 | C31: 15.923479 | D31: 15.965811 | E31: =D31-C31 -> 0.042331927 | F31: 0 | G31: 15.965811 | H31: A- | I31: GREGORY HADJIAN | J31: 0.62328809 | K31: 0.66202218 | L31: 0.66084981 | M31: =K31-J31 -> 0.038734094 | N31: =L31-K31 -> -0.0011723717 | O31: =M31+N31 -> 0.037561723 | P31: =O31*2.804471 -> 0.10534076
A32: Colombia | B32: 12 | C32: 12.133574 | D32: 11.801764 | E32: =D32-C32 -> -0.33181047 | F32: -1.5 | G32: 10.301764 | H32: BB- | I32: GREGORY HADJIAN | J32: -0.41284555 | K32: -0.48023923 | L32: -0.54717886 | M32: =K32-J32 -> -0.067393682 | N32: =L32-K32 -> -0.06693963 | O32: =M32+N32 -> -0.13433331 | P32: =O32*2.804471 -> -0.37673388
A33: Costa Rica | B33: 10.666667 | C33: 13.759663 | D33: 14.062246 | E33: =D33-C33 -> 0.30258223 | F33: -1.25 | G33: 12.812246 | H33: BBB- | I33: GREGORY HADJIAN | J33: 0.54861199 | K33: 0.65229291 | L33: 0.62275776 | M33: =K33-J33 -> 0.10368092 | N33: =L33-K33 -> -0.029535152 | O33: =M33+N33 -> 0.074145765 | P33: =O33*2.804471 -> 0.20793965
A34: Dominican Republic | B34: 10.666667 | C34: 11.84615 | D34: 12.091648 | E34: =D34-C34 -> 0.24549807 | F34: -0.25 | G34: 11.841648 | H34: BB+ | I34: GREGORY HADJIAN | J34: -0.11320813 | K34: -0.16774065 | L34: -0.058754814 | M34: =K34-J34 -> -0.054532519 | N34: =L34-K34 -> 0.10898583 | O34: =M34+N34 -> 0.054453315 | P34: =O34*2.804471 -> 0.15271274
A35: Ecuador | B35: 5.6666667 | C35: 8.702736 | D35: 8.3999594 | E35: =D35-C35 -> -0.30277662 | F35: -2.75 | G35: 5.6499594 | H35: CCC+ | I35: GREGORY HADJIAN | J35: -0.76690152 | K35: -0.70641765 | L35: -0.82496177 | M35: =K35-J35 -> 0.060483865 | N35: =L35-K35 -> -0.11854412 | O35: =M35+N35 -> -0.058060251 | P35: =O35*2.804471 -> -0.16282829 | Q35: Reweighting of defaut coefficient
A36: El Salvador | B36: 7 | C36: 6.297293 | D36: 5.7739379 | E36: =D36-C36 -> -0.52335506 | F36: 0.75 | G36: 6.5239379 | H36: B- | I36: GREGORY HADJIAN | J36: -0.47637359 | K36: -0.59835748 | L36: -0.62679652 | M36: =K36-J36 -> -0.12198388 | N36: =L36-K36 -> -0.028439043 | O36: =M36+N36 -> -0.15042292 | P36: =O36*2.804471 -> -0.42185673
A37: Guatemala | B37: 12 | C37: 10.689704 | D37: 10.969666 | E37: =D37-C37 -> 0.27996174 | F37: 1 | G37: 11.969666 | H37: BB+ | I37: GREGORY HADJIAN | J37: -0.93160879 | K37: -0.92804608 | L37: -0.88361184 | M37: =K37-J37 -> 0.0035627118 | N37: =L37-K37 -> 0.044434234 | O37: =M37+N37 -> 0.047996945 | P37: =O37*2.804471 -> 0.13460604
A38: Honduras | B38: 9.5 | C38: 8.9685337 | D38: 8.8087696 | E38: =D38-C38 -> -0.15976411 | F38: 0 | G38: 8.8087696 | H38: B+ | I38: GREGORY HADJIAN | J38: -0.99174471 | K38: -1.0216101 | L38: -1.0839169 | M38: =K38-J38 -> -0.029865428 | N38: =L38-K38 -> -0.062306751 | O38: =M38+N38 -> -0.092172179 | P38: =O38*2.804471 -> -0.2584942
A39: Mexico | B39: 13.666667 | C39: 12.534224 | D39: 12.265758 | E39: =D39-C39 -> -0.26846526 | F39: 0.5 | G39: 12.765758 | H39: BBB- | I39: GREGORY HADJIAN | J39: -0.71266744 | K39: -0.75577651 | L39: -0.84145677 | M39: =K39-J39 -> -0.043109064 | N39: =L39-K39 -> -0.08568026 | O39: =M39+N39 -> -0.12878932 | P39: =O39*2.804471 -> -0.36118593
A40: Nicaragua | B40: 8.3333333 | C40: 6.7228111 | D40: 6.245288 | E40: =D40-C40 -> -0.47752312 | F40: 0 | G40: 6.245288 | H40: CCC+ | I40: Not covered | J40: -1.2944628 | K40: -1.3557762 | L40: -1.4409284 | M40: =K40-J40 -> -0.061313449 | N40: =L40-K40 -> -0.085152167 | O40: =M40+N40 -> -0.14646562 | P40: =O40*2.804471 -> -0.41075857
A41: Panama | B41: 12.666667 | C41: 11.675954 | D41: 11.875909 | E41: =D41-C41 -> 0.1999549 | F41: -0.1 | G41: 11.775909 | H41: BB+ | I41: GREGORY HADJIAN | J41: -0.21938553 | K41: -0.16141605 | L41: -0.16571271 | M41: =K41-J41 -> 0.05796948 | N41: =L41-K41 -> -0.0042966633 | O41: =M41+N41 -> 0.053672817 | P41: =O41*2.804471 -> 0.15052386
A42: Paraguay | B42: 12.333333 | C42: 10.489497 | D42: 10.379036 | E42: =D42-C42 -> -0.11046089 | F42: 2.25 | G42: 12.629036 | H42: BBB- | I42: GREGORY HADJIAN | J42: -0.53916181 | K42: -0.59654359 | L42: -0.60531442 | M42: =K42-J42 -> -0.057381783 | N42: =L42-K42 -> -0.008770825 | O42: =M42+N42 -> -0.066152608 | P42: =O42*2.804471 -> -0.18552307
A43: Peru | B43: 14 | C43: 12.809185 | D43: 12.786463 | E43: =D43-C43 -> -0.022722585 | F43: 0.75 | G43: 13.536463 | H43: BBB | I43: GREGORY HADJIAN | J43: -0.52640665 | K43: -0.51966761 | L43: -0.5480991 | M43: =K43-J43 -> 0.0067390347 | N43: =L43-K43 -> -0.028431484 | O43: =M43+N43 -> -0.021692449 | P43: =O43*2.804471 -> -0.060835846
A44: Uruguay | B44: 14.666667 | C44: 13.890368 | D44: 13.867454 | E44: =D44-C44 -> -0.02291416 | F44: 0 | G44: 13.867454 | H44: BBB | I44: GREGORY HADJIAN | J44: 0.93445807 | K44: 1.0081235 | L44: 0.97591837 | M44: =K44-J44 -> 0.073665472 | N44: =L44-K44 -> -0.032205171 | O44: =M44+N44 -> 0.041460301 | P44: =O44*2.804471 -> 0.11627421
A45: Venezuela | B45: 1 | C45: -0.80261715 | D45: -1.1667272 | E45: =D45-C45 -> -0.36411008 | F45: 0 | G45: 1 | H45: D | I45: GREGORY HADJIAN | J45: -2.0540953 | K45: -2.0267007 | L45: -2.1799606 | M45: =K45-J45 -> 0.027394544 | N45: =L45-K45 -> -0.15325985 | O45: =M45+N45 -> -0.12586531 | P45: =O45*2.804471 -> -0.3529856
A46: Barbados | B46: 8.3333333 | C46: 9.4886257 | D46: 9.5286985 | E46: =D46-C46 -> 0.040072775 | F46: -0.75 | G46: 8.7786985 | H46: B+ | I46: GREGORY HADJIAN | J46: 0.74263616 | K46: 0.78029593 | L46: 0.78480038 | M46: =K46-J46 -> 0.037659775 | N46: =L46-K46 -> 0.0045044447 | O46: =M46+N46 -> 0.042164219 | P46: =O46*2.804471 -> 0.11824833
A47: Belize | B47: 6.5 | C47: 6.0014046 | D47: 6.0312688 | E47: =D47-C47 -> 0.029864204 | F47: 0 | G47: 6.0312688 | H47: CCC+ | I47: Not covered | J47: -0.26556218 | K47: -0.20827073 | L47: -0.22331691 | M47: =K47-J47 -> 0.057291449 | N47: =L47-K47 -> -0.015046177 | O47: =M47+N47 -> 0.042245272 | P47: =O47*2.804471 -> 0.11847564
... A55: Jordan | B55: 10 | C55: 9.935072 | D55: 9.9644323 | E55: =D55-C55 -> 0.029360322 | F55: -0.4 | G55: 9.5644323 | H55: BB- | I55: RAMSEY ANDRAWIS | J55: -0.18831597 | K55: -0.21216038 | L55: -0.21905894 | M55: =K55-J55 -> -0.023844402 | N55: =L55-K55 -> -0.006898563 | O55: =M55+N55 -> -0.030742965 | P55: =O55*2.804471 -> -0.086217753
A56: Kuwait | B56: 18.333333 | C56: 19.524028 | D56: 19.203784 | E56: =D56-C56 -> -0.32024386 | F56: -2.5 | G56: 16.703784 | H56: A | I56: RAMSEY ANDRAWIS | J56: -0.049126405 | K56: -0.04553989 | L56: -0.042925366 | M56: =K56-J56 -> 0.0035865154 | N56: =L56-K56 -> 0.0026145236 | O56: =M56+N56 -> 0.006201039 | P56: =O56*2.804471 -> 0.017390634 | Q56: Driven by smaller fiscal perf coefficient in re-weighting
A57: Lebanon | B57: 1.3333333 | C57: -1.8741458 | D57: -1.7799974 | E57: =D57-C57 -> 0.094148366 | F57: 0 | G57: 1 | H57: D | I57: RAMSEY ANDRAWIS | J57: -1.5066692 | K57: -1.3854518 | L57: -1.4248859 | M57: =K57-J57 -> 0.12121746 | N57: =L57-K57 -> -0.039434114 | O57: =M57+N57 -> 0.08178335 | P57: =O57*2.804471 -> 0.22935903
A58: Oman | B58: 12.666667 | C58: 14.136254 | D58: 14.533416 | E58: =D58-C58 -> 0.39716191 | F58: -0.7 | G58: 13.833416 | H58: BBB | I58: RAMSEY ANDRAWIS | J58: 0.031578472 | K58: 0.061802917 | L58: 0.18166453 | M58: =K58-J58 -> 0.030224445 | N58: =L58-K58 -> 0.11986162 | O58: =M58+N58 -> 0.15008606 | P58: =O58*2.804471 -> 0.420912
A59: Qatar | B59: 20 | C59: 17.460298 | D59: 17.230358 | E59: =D59-C59 -> -0.22994016 | F59: 3.5 | G59: 20.730358 | H59: AA+ | I59: RAMSEY ANDRAWIS | J59: 0.53384237 | K59: 0.47838402 | L59: 0.46299916 | M59: =K59-J59 -> -0.055458344 | N59: =L59-K59 -> -0.015384862 | O59: =M59+N59 -> -0.070843206 | P59: =O59*2.804471 -> -0.19867772
A60: Saudi Arabia | B60: 18.333333 | C60: 16.262 | D60: 16.361501 | E60: =D60-C60 -> 0.0995008 | F60: 0.2 | G60: 16.561501 | H60: A | I60: RAMSEY ANDRAWIS | J60: -0.072493144 | K60: -0.16582077 | L60: -0.029632788 | M60: =K60-J60 -> -0.093327629 | N60: =L60-K60 -> 0.13618799 | O60: =M60+N60 -> 0.042860356 | P60: =O60*2.804471 -> 0.12020063
A61: United Arab Emirates | B61: 19.666667 | C61: 18.614348 | D61: 18.471338 | E61: =D61-C61 -> -0.14300936 | F61: 2.4 | G61: 20.871338 | H61: AA+ | I61: RAMSEY ANDRAWIS | J61: 0.58998505 | K61: 0.51296366 | L61: 0.55720414 | M61: =K61-J61 -> -0.077021387 | N61: =L61-K61 -> 0.044240484 | O61: =M61+N61 -> -0.032780903 | P61: =O61*2.804471 -> -0.091933093
A62: Egypt | B62: 7.3333333 | C62: 6.9080553 | D62: 6.7979198 | E62: =D62-C62 -> -0.11013551 | F62: 0.5 | G62: 7.2979198 | H62: B- | I62: RAMSEY ANDRAWIS | J62: -0.93805546 | K62: -1.0581597 | L62: -1.0672434 | M62: =K62-J62 -> -0.12010424 | N62: =L62-K62 -> -0.0090837353 | O62: =M62+N62 -> -0.12918797 | P62: =O62*2.804471 -> -0.36230393
A63: Bangladesh | B63: 8.6666667 | C63: 9.7222357 | D63: 9.0610353 | E63: =D63-C63 -> -0.66120036 | F63: 0 | G63: 9.0610353 | H63: B+ | I63: Not covered | J63: -1.0830267 | K63: -1.2491752 | L63: -1.3545825 | M63: =K63-J63 -> -0.16614849 | N63: =L63-K63 -> -0.10540727 | O63: =M63+N63 -> -0.27155575 | P63: =O63*2.804471 -> -0.76157023
A64: Cambodia | B64: 8 | C64: 9.3636397 | D64: 9.2010307 | E64: =D64-C64 -> -0.16260901 | F64: 0 | G64: 9.2010307 | H64: B+ | I64: Not covered | J64: -0.96351665 | K64: -1.0382505 | L64: -1.0445023 | M64: =K64-J64 -> -0.074733864 | N64: =L64-K64 -> -0.0062517856 | O64: =M64+N64 -> -0.08098565 | P64: =O64*2.804471 -> -0.22712191
A65: Sri Lanka | B65: 6 | C65: 4.2059002 | D65: 4.3422831 | E65: =D65-C65 -> 0.13638289 | F65: 1.6 | G65: 5.9422831 | H65: CCC+ | I65: KAIMIN KHAW | J65: -0.54734988 | K65: -0.6421916 | L65: -0.50437757 | M65: =K65-J65 -> -0.094841721 | N65: =L65-K65 -> 0.13781403 | O65: =M65+N65 -> 0.042972307 | P65: =O65*2.804471 -> 0.12051459
A66: Taiwan | B66: 20 | C66: 20.62355 | D66: 20.48487 | E66: =D66-C66 -> -0.1386801 | F66: 0 | G66: 20.48487 | H66: AA | I66: Not covered | J66: 1.1580946 | K66: 1.1739869 | L66: 1.1458079 | M66: =K66-J66 -> 0.015892296 | N66: =L66-K66 -> -0.028178956 | O66: =M66+N66 -> -0.012286661 | P66: =O66*2.804471 -> -0.034457584
A67: Hong Kong | B67: 19.666667 | C67: 19.837179 | D67: 19.647103 | E67: =D67-C67 -> -0.19007626 | F67: 0 | G67: 19.647103 | H67: AA | I67: BO ZHUANG | J67: 0.99749119 | K67: 0.88260573 | L67: 0.95702897 | M67: =K67-J67 -> -0.11488546 | N67: =L67-K67 -> 0.074423246 | O67: =M67+N67 -> -0.040462213 | P67: =O67*2.804471 -> -0.1134751
A68: India | B68: 13.333333 | C68: 13.343984 | D68: 13.070945 | E68: =D68-C68 -> -0.27303928 | F68: 0.5 | G68: 13.570945 | H68: BBB | I68: KAIMIN KHAW | J68: -0.25306154 | K68: -0.40097809 | L68: -0.36074267 | M68: =K68-J68 -> -0.14791655 | N68: =L68-K68 -> 0.040235422 | O68: =M68+N68 -> -0.10768112 | P68: =O68*2.804471 -> -0.30198859
... A138: Romania | B138: 13 | C138: 13.731877 | D138: 13.805774 | E138: =D138-C138 -> 0.07389675 | F138: -1.4 | G138: 12.405774 | H138: BB+ | I138: RAMSEY ANDRAWIS | J138: 0.11779894 | K138: 0.17150644 | L138: 0.13682122 | M138: =K138-J138 -> 0.053707492 | N138: =L138-K138 -> -0.034685219 | O138: =M138+N138 -> 0.019022273 | P138: =O138*2.804471 -> 0.053347414
A141: *NOTE ALGERIA REMOVED :)

Sheet select_country
B1: Select Country | C1: Bolivia
B2: Year | C2: 2025
B4: Factor View
D5: Oct (before) | G5: Dec (after WGI changes)
B6: Short Name | C6: Long Name | D6: Coeff | E6: Z-Score | F6: Rating Impact | G6: Coeff | H6: Z-Score | I6: Rating Impact | J6: Delta
B7: const | C7: Constant | D7: 12.695933 | E7: - | F7: =D7 -> 12.695933 | G7: 12.691923 | H7: - | I7: =G7 -> 12.691923 | J7: =I7-F7 -> -0.0040107437
B8: wealth_factor | C8: Wealth (5%) | D8: 0.50759205 | E8: =INDEX('2025_oct_transform'!$C$1:$AQ$139,MATCH($C$1,'2025_oct_transform'!$C$1:$C$139,0),MATCH($B8,'2025_oct_transform'!$C$1:$AQ$1,0)) -> -0.54654873 | F8: =D8*E8 -> -0.27742379 | G8: 0.53027255 | H8: =INDEX('2025_dec_transform'!$C$1:$AQ$139,MATCH($C$1,'2025_dec_transform'!$C$1:$C$139,0),MATCH($B8,'2025_dec_transform'!$C$1:$AQ$1,0)) -> -0.54654873 | I8: =G8*H8 -> -0.28981979 | J8: =I8-F8 -> -0.012395996
B9: size_factor | C9: Size (18%) | D9: 1.6047043 | E9: =INDEX('2025_oct_transform'!$C$1:$AQ$139,MATCH($C$1,'2025_oct_transform'!$C$1:$C$139,0),MATCH($B9,'2025_oct_transform'!$C$1:$AQ$1,0)) -> -0.40458579 | F9: =D9*E9 -> -0.64924056 | G9: 1.5749904 | H9: =INDEX('2025_dec_transform'!$C$1:$AQ$139,MATCH($C$1,'2025_dec_transform'!$C$1:$C$139,0),MATCH($B9,'2025_dec_transform'!$C$1:$AQ$1,0)) -> -0.40458579 | I9: =G9*H9 -> -0.63721875 | J9: =I9-F9 -> 0.012021817
B10: growth_factor | C10: Growth (2%) | D10: 0.14465344 | E10: =INDEX('2025_oct_transform'!$C$1:$AQ$139,MATCH($C$1,'2025_oct_transform'!$C$1:$C$139,0),MATCH($B10,'2025_oct_transform'!$C$1:$AQ$1,0)) -> -1.0103516 | F10: =D10*E10 -> -0.14615084 | G10: 0.13008491 | H10: =INDEX('2025_dec_transform'!$C$1:$AQ$139,MATCH($C$1,'2025_dec_transform'!$C$1:$C$139,0),MATCH($B10,'2025_dec_transform'!$C$1:$AQ$1,0)) -> -1.0103516 | I10: =G10*H10 -> -0.1314315 | J10: =I10-F10 -> 0.014719338
B11: inflation_factor | C11: Inflation (3%) | D11: 0.27236765 | E11: =INDEX('2025_oct_transform'!$C$1:$AQ$139,MATCH($C$1,'2025_oct_transform'!$C$1:$C$139,0),MATCH($B11,'2025_oct_transform'!$C$1:$AQ$1,0)) -> -0.74028236 | F11: =D11*E11 -> -0.20162897 | G11: 0.30518536 | H11: =INDEX('2025_dec_transform'!$C$1:$AQ$139,MATCH($C$1,'2025_dec_transform'!$C$1:$C$139,0),MATCH($B11,'2025_dec_transform'!$C$1:$AQ$1,0)) -> -0.74028236 | I11: =G11*H11 -> -0.22592334 | J11: =I11-F11 -> -0.024294369
B12: default_factor | C12: Default History (9%) | D12: 0.81804555 | E12: =INDEX('2025_oct_transform'!$C$1:$AQ$139,MATCH($C$1,'2025_oct_transform'!$C$1:$C$139,0),MATCH($B12,'2025_oct_transform'!$C$1:$AQ$1,0)) -> 0.30213082 | F12: =D12*E12 -> 0.24715677 | G12: 0.87885606 | H12: =INDEX('2025_dec_transform'!$C$1:$AQ$139,MATCH($C$1,'2025_dec_transform'!$C$1:$C$139,0),MATCH($B12,'2025_dec_transform'!$C$1:$AQ$1,0)) -> 0.30213082 | I12: =G12*H12 -> 0.2655295 | J12: =I12-F12 -> 0.01837273
B13: governance_factor | C13: Governance (32%) | D13: 2.8789941 | E13: =INDEX('2025_oct_transform'!$C$1:$AQ$139,MATCH($C$1,'2025_oct_transform'!$C$1:$C$139,0),MATCH($B13,'2025_oct_transform'!$C$1:$AQ$1,0)) -> -0.99291646 | F13: =D13*E13 -> -2.8586006 | G13: 2.8044707 | H13: =INDEX('2025_dec_transform'!$C$1:$AQ$139,MATCH($C$1,'2025_dec_transform'!$C$1:$C$139,0),MATCH($B13,'2025_dec_transform'!$C$1:$AQ$1,0)) -> -1.1340894 | I13: =G13*H13 -> -3.1805204 | J13: =I13-F13 -> -0.32191986
B14: fiscalperf_factor | C14: Fiscal Performance (7%) | D14: 0.65335151 | E14: =INDEX('2025_oct_transform'!$C$1:$AQ$139,MATCH($C$1,'2025_oct_transform'!$C$1:$C$139,0),MATCH($B14,'2025_oct_transform'!$C$1:$AQ$1,0)) -> -0.99802823 | F14: =D14*E14 -> -0.65206325 | G14: 0.5796163 | H14: =INDEX('2025_dec_transform'!$C$1:$AQ$139,MATCH($C$1,'2025_dec_transform'!$C$1:$C$139,0),MATCH($B14,'2025_dec_transform'!$C$1:$AQ$1,0)) -> -0.99802879 | I14: =G14*H14 -> -0.57847375 | J14: =I14-F14 -> 0.073589494
B15: govdebt_factor | C15: Government Debt (10%) | D15: 0.91025734 | E15: =INDEX('2025_oct_transform'!$C$1:$AQ$139,MATCH($C$1,'2025_oct_transform'!$C$1:$C$139,0),MATCH($B15,'2025_oct_transform'!$C$1:$AQ$1,0)) -> -0.99062149 | F15: =D15*E15 -> -0.90172048 | G15: 0.88139076 | H15: =INDEX('2025_dec_transform'!$C$1:$AQ$139,MATCH($C$1,'2025_dec_transform'!$C$1:$C$139,0),MATCH($B15,'2025_dec_transform'!$C$1:$AQ$1,0)) -> -0.99062149 | I15: =G15*H15 -> -0.87312462 | J15: =I15-F15 -> 0.028595851
B16: extperf_factor | C16: External Performance (5%) | D16: 0.46481235 | E16: =INDEX('2025_oct_transform'!$C$1:$AQ$139,MATCH($C$1,'2025_oct_transform'!$C$1:$C$139,0),MATCH($B16,'2025_oct_transform'!$C$1:$AQ$1,0)) -> 0.098618921 | F16: =D16*E16 -> 0.045839293 | G16: 0.47302681 | H16: =INDEX('2025_dec_transform'!$C$1:$AQ$139,MATCH($C$1,'2025_dec_transform'!$C$1:$C$139,0),MATCH($B16,'2025_dec_transform'!$C$1:$AQ$1,0)) -> 0.098618921 | I16: =G16*H16 -> 0.046649393 | J16: =I16-F16 -> 0.00081010045
B17: reservebuffer_factor | C17: FX Reserves (4%) | D17: 0.35395378 | E17: =INDEX('2025_oct_transform'!$C$1:$AQ$139,MATCH($C$1,'2025_oct_transform'!$C$1:$C$139,0),MATCH($B17,'2025_oct_transform'!$C$1:$AQ$1,0)) -> -3.3590278 | F17: =D17*E17 -> -1.1889406 | G17: 0.3484954 | H17: =INDEX('2025_dec_transform'!$C$1:$AQ$139,MATCH($C$1,'2025_dec_transform'!$C$1:$C$139,0),MATCH($B17,'2025_dec_transform'!$C$1:$AQ$1,0)) -> -1.3162626 | I17: =G17*H17 -> -0.45871148 | J17: =I17-F17 -> 0.73022909
B18: reservestatus_factor | C18: Reserve Currency Status (5%) | D18: 0.45274543 | E18: =INDEX('2025_oct_transform'!$C$1:$AQ$139,MATCH($C$1,'2025_oct_transform'!$C$1:$C$139,0),MATCH($B18,'2025_oct_transform'!$C$1:$AQ$1,0)) -> -0.52486557 | F18: =D18*E18 -> -0.23763049 | G18: 0.48221815 | H18: =INDEX('2025_dec_transform'!$C$1:$AQ$139,MATCH($C$1,'2025_dec_transform'!$C$1:$C$139,0),MATCH($B18,'2025_dec_transform'!$C$1:$AQ$1,0)) -> -0.52486557 | I18: =G18*H18 -> -0.25309971 | J18: =I18-F18 -> -0.015469217
B19: Model Rating | F19: =SUM(F7:F18) -> 5.8755299 | I19: =SUM(I7:I18) -> 6.3757781 | J19: =I19-F19 -> 0.50024824
E20: check | F20: =INDEX('2025_oct_transform'!$C$1:$AQ$139,MATCH($C$1,'2025_oct_transform'!$C$1:$C$139,0),MATCH("predicted_rating",'2025_oct_transform'!$C$1:$AQ$1,0)) -> 5.8755299 | H20: check | I20: =INDEX('2025_dec_transform'!$C$1:$AQ$139,MATCH($C$1,'2025_dec_transform'!$C$1:$C$139,0),MATCH("predicted_rating",'2025_dec_transform'!$C$1:$AQ$1,0)) -> 6.3757781 | J20: =SUM(J7:J18) -> 0.50024824
B23: Raw Variable View
D24: Oct (before) | F24: Dec (after WGI changes)
A25: Short Name | B25: Factor | C25: Constituent Variables | D25: Raw | E25: Z-Score | F25: Raw | G25: Z-score | H25: Raw Delta | I25: Z-Score Delta
B26: Intercept | C26: Baseline Rating | D26: - | E26: - | F26: - | G26: - | H26: - | I26: -
A27: ngdp_pc | B27: Wealth (%) | C27: Nominal GDP per capita (US$) | D27: =INDEX('2025_oct_raw'!$C$1:$AK$139,MATCH($C$1,'2025_oct_raw'!$C$1:$C$139,0),MATCH($A27,'2025_oct_raw'!$C$1:$AK$1,0)) -> 4585.184 | E27: =INDEX('2025_oct_transform'!$C$1:$AQ$139,MATCH($C$1,'2025_oct_transform'!$C$1:$C$139,0),MATCH($A27,'2025_oct_transform'!$C$1:$AQ$1,0)) -> -0.54654873 | F27: =INDEX('2025_dec_raw'!$C$1:$AK$139,MATCH($C$1,'2025_dec_raw'!$C$1:$C$139,0),MATCH($A27,'2025_dec_raw'!$C$1:$AK$1,0)) -> 4585.184 | G27: =INDEX('2025_dec_transform'!$C$1:$AQ$139,MATCH($C$1,'2025_dec_transform'!$C$1:$C$139,0),MATCH($A27,'2025_dec_transform'!$C$1:$AQ$1,0)) -> -0.54654873 | H27: =F27-D27 -> 0 | I27: =G27-E27 -> 0
A28: ngdp | B28: Size (18%) | C28: Nominal GDP (US$ bil) | D28: =INDEX('2025_oct_raw'!$C$1:$AK$139,MATCH($C$1,'2025_oct_raw'!$C$1:$C$139,0),MATCH($A28,'2025_oct_raw'!$C$1:$AK$1,0)) -> 57.086 | E28: =INDEX('2025_oct_transform'!$C$1:$AQ$139,MATCH($C$1,'2025_oct_transform'!$C$1:$C$139,0),MATCH($A28,'2025_oct_transform'!$C$1:$AQ$1,0)) -> -0.40458579 | F28: =INDEX('2025_dec_raw'!$C$1:$AK$139,MATCH($C$1,'2025_dec_raw'!$C$1:$C$139,0),MATCH($A28,'2025_dec_raw'!$C$1:$AK$1,0)) -> 57.086 | G28: =INDEX('2025_dec_transform'!$C$1:$AQ$139,MATCH($C$1,'2025_dec_transform'!$C$1:$C$139,0),MATCH($A28,'2025_dec_transform'!$C$1:$AQ$1,0)) -> -0.40458579 | H28: =F28-D28 -> 0 | I28: =G28-E28 -> 0
A29: growth_avg | B29: Growth (2%) | C29: Average Growth t-5 to t+4 (%) | D29: =INDEX('2025_oct_raw'!$C$1:$AK$139,MATCH($C$1,'2025_oct_raw'!$C$1:$C$139,0),MATCH($A29,'2025_oct_raw'!$C$1:$AK$1,0)) -> 0.89857143 | E29: =INDEX('2025_oct_transform'!$C$1:$AQ$139,MATCH($C$1,'2025_oct_transform'!$C$1:$C$139,0),MATCH($A29,'2025_oct_transform'!$C$1:$AQ$1,0)) -> -1.0103516 | F29: =INDEX('2025_dec_raw'!$C$1:$AK$139,MATCH($C$1,'2025_dec_raw'!$C$1:$C$139,0),MATCH($A29,'2025_dec_raw'!$C$1:$AK$1,0)) -> 0.89857143 | G29: =INDEX('2025_dec_transform'!$C$1:$AQ$139,MATCH($C$1,'2025_dec_transform'!$C$1:$C$139,0),MATCH($A29,'2025_dec_transform'!$C$1:$AQ$1,0)) -> -1.0103516 | H29: =F29-D29 -> 0 | I29: =G29-E29 -> 0
A30: inf_avg | B30: Inflation (3%) | C30: Average Inflation t-5 to t+4 (%) | D30: =INDEX('2025_oct_raw'!$C$1:$AK$139,MATCH($C$1,'2025_oct_raw'!$C$1:$C$139,0),MATCH($A30,'2025_oct_raw'!$C$1:$AK$1,0)) -> 8.5318571 | E30: =INDEX('2025_oct_transform'!$C$1:$AQ$139,MATCH($C$1,'2025_oct_transform'!$C$1:$C$139,0),MATCH($A30,'2025_oct_transform'!$C$1:$AQ$1,0)) -> 0.74028236 | F30: =INDEX('2025_dec_raw'!$C$1:$AK$139,MATCH($C$1,'2025_dec_raw'!$C$1:$C$139,0),MATCH($A30,'2025_dec_raw'!$C$1:$AK$1,0)) -> 8.5318571 | G30: =INDEX('2025_dec_transform'!$C$1:$AQ$139,MATCH($C$1,'2025_dec_transform'!$C$1:$C$139,0),MATCH($A30,'2025_dec_transform'!$C$1:$AQ$1,0)) -> 0.74028236 | H30: =F30-D30 -> 0 | I30: =G30-E30 -> 0
A31: default_factor | B31: Default History (9%) | C31: Average of Default History and Default Decay | D31: - | E31: =INDEX('2025_oct_transform'!$C$1:$AQ$139,MATCH($C$1,'2025_oct_transform'!$C$1:$C$139,0),MATCH($A31,'2025_oct_transform'!$C$1:$AQ$1,0)) -> 0.30213082 | F31: - | G31: =INDEX('2025_dec_transform'!$C$1:$AQ$139,MATCH($C$1,'2025_dec_transform'!$C$1:$C$139,0),MATCH($A31,'2025_dec_transform'!$C$1:$AQ$1,0)) -> 0.30213082 | H31: - | I31: =G31-E31 -> 0
A32: default_hist | C32: Default history dummy. 1 if ever defaulted before 0 otherwise. | D32: =INDEX('2025_oct_raw'!$C$1:$AK$139,MATCH($C$1,'2025_oct_raw'!$C$1:$C$139,0),MATCH($A32,'2025_oct_raw'!$C$1:$AK$1,0)) -> 0 | E32: =INDEX('2025_oct_transform'!$C$1:$AQ$139,MATCH($C$1,'2025_oct_transform'!$C$1:$C$139,0),MATCH($A32,'2025_oct_transform'!$C$1:$AQ$1,0)) -> -0.3610543 | F32: =INDEX('2025_dec_raw'!$C$1:$AK$139,MATCH($C$1,'2025_dec_raw'!$C$1:$C$139,0),MATCH($A32,'2025_dec_raw'!$C$1:$AK$1,0)) -> 0 | G32: =INDEX('2025_dec_transform'!$C$1:$AQ$139,MATCH($C$1,'2025_dec_transform'!$C$1:$C$139,0),MATCH($A32,'2025_dec_transform'!$C$1:$AQ$1,0)) -> -0.3610543 | H32: =F32-D32 -> 0 | I32: =G32-E32 -> 0
A33: default_decay | C33: Default Decay. 1 at point of default. Decays to 0.5 in 4.3 years. | D33: =INDEX('2025_oct_raw'!$C$1:$AK$139,MATCH($C$1,'2025_oct_raw'!$C$1:$C$139,0),MATCH($A33,'2025_oct_raw'!$C$1:$AK$1,0)) -> 0 | E33: =INDEX('2025_oct_transform'!$C$1:$AQ$139,MATCH($C$1,'2025_oct_transform'!$C$1:$C$139,0),MATCH($A33,'2025_oct_transform'!$C$1:$AQ$1,0)) -> -0.24320733 | F33: =INDEX('2025_dec_raw'!$C$1:$AK$139,MATCH($C$1,'2025_dec_raw'!$C$1:$C$139,0),MATCH($A33,'2025_dec_raw'!$C$1:$AK$1,0)) -> 0 | G33: =INDEX('2025_dec_transform'!$C$1:$AQ$139,MATCH($C$1,'2025_dec_transform'!$C$1:$C$139,0),MATCH($A33,'2025_dec_transform'!$C$1:$AQ$1,0)) -> -0.24320733 | H33: =F33-D33 -> 0 | I33: =G33-E33 -> 0
A34: governance_factor | B34: Governance (32%) | C34: Average of 6 WGI Indicators | D34: - | E34: =INDEX('2025_oct_transform'!$C$1:$AQ$139,MATCH($C$1,'2025_oct_transform'!$C$1:$C$139,0),MATCH($A34,'2025_oct_transform'!$C$1:$AQ$1,0)) -> -0.99291646 | F34: - | G34: =INDEX('2025_dec_transform'!$C$1:$AQ$139,MATCH($C$1,'2025_dec_transform'!$C$1:$C$139,0),MATCH($A34,'2025_dec_transform'!$C$1:$AQ$1,0)) -> -1.1340894 | H34: - | I34: =G34-E34 -> -0.14117292
A35: voice_acct | C35: Voice and Accountability (cross section z-score) | D35: =INDEX('2025_oct_raw'!$C$1:$AK$139,MATCH($C$1,'2025_oct_raw'!$C$1:$C$139,0),MATCH($A35,'2025_oct_raw'!$C$1:$AK$1,0)) -> -0.265191 | E35: =INDEX('2025_oct_transform'!$C$1:$AQ$139,MATCH($C$1,'2025_oct_transform'!$C$1:$C$139,0),MATCH($A35,'2025_oct_transform'!$C$1:$AQ$1,0)) -> -0.44968671 | F35: =INDEX('2025_dec_raw'!$C$1:$AK$139,MATCH($C$1,'2025_dec_raw'!$C$1:$C$139,0),MATCH($A35,'2025_dec_raw'!$C$1:$AK$1,0)) -> -0.439764 | G35: =INDEX('2025_dec_transform'!$C$1:$AQ$139,MATCH($C$1,'2025_dec_transform'!$C$1:$C$139,0),MATCH($A35,'2025_dec_transform'!$C$1:$AQ$1,0)) -> -0.63148476 | H35: =F35-D35 -> -0.174573 | I35: =G35-E35 -> -0.18179804
A36: pol_stab | C36: Political Stability (cross section z-score) | D36: =INDEX('2025_oct_raw'!$C$1:$AK$139,MATCH($C$1,'2025_oct_raw'!$C$1:$C$139,0),MATCH($A36,'2025_oct_raw'!$C$1:$AK$1,0)) -> -0.313184 | E36: =INDEX('2025_oct_transform'!$C$1:$AQ$139,MATCH($C$1,'2025_oct_transform'!$C$1:$C$139,0),MATCH($A36,'2025_oct_transform'!$C$1:$AQ$1,0)) -> -0.40383874 | F36: =INDEX('2025_dec_raw'!$C$1:$AK$139,MATCH($C$1,'2025_dec_raw'!$C$1:$C$139,0),MATCH($A36,'2025_dec_raw'!$C$1:$AK$1,0)) -> -0.546036 | G36: =INDEX('2025_dec_transform'!$C$1:$AQ$139,MATCH($C$1,'2025_dec_transform'!$C$1:$C$139,0),MATCH($A36,'2025_dec_transform'!$C$1:$AQ$1,0)) -> -0.69802322 | H36: =F36-D36 -> -0.232852 | I36: =G36-E36 -> -0.29418448
A37: gov_eff | C37: Government Effectiveness (cross section z-score) | D37: =INDEX('2025_oct_raw'!$C$1:$AK$139,MATCH($C$1,'2025_oct_raw'!$C$1:$C$139,0),MATCH($A37,'2025_oct_raw'!$C$1:$AK$1,0)) -> -0.639481 | E37: =INDEX('2025_oct_transform'!$C$1:$AQ$139,MATCH($C$1,'2025_oct_transform'!$C$1:$C$139,0),MATCH($A37,'2025_oct_transform'!$C$1:$AQ$1,0)) -> -0.98282211 | F37: =INDEX('2025_dec_raw'!$C$1:$AK$139,MATCH($C$1,'2025_dec_raw'!$C$1:$C$139,0),MATCH($A37,'2025_dec_raw'!$C$1:$AK$1,0)) -> -0.610417 | G37: =INDEX('2025_dec_transform'!$C$1:$AQ$139,MATCH($C$1,'2025_dec_transform'!$C$1:$C$139,0),MATCH($A37,'2025_dec_transform'!$C$1:$AQ$1,0)) -> -1.0457222 | H37: =F37-D37 -> 0.029064 | I37: =G37-E37 -> -0.062900053
A38: reg_qual | C38: Regulatory Quality (cross section z-score) | D38: =INDEX('2025_oct_raw'!$C$1:$AK$139,MATCH($C$1,'2025_oct_raw'!$C$1:$C$139,0),MATCH($A38,'2025_oct_raw'!$C$1:$AK$1,0)) -> -1.177119 | E38: =INDEX('2025_oct_transform'!$C$1:$AQ$139,MATCH($C$1,'2025_oct_transform'!$C$1:$C$139,0),MATCH($A38,'2025_oct_transform'!$C$1:$AQ$1,0)) -> -1.6557626 | F38: =INDEX('2025_dec_raw'!$C$1:$AK$139,MATCH($C$1,'2025_dec_raw'!$C$1:$C$139,0),MATCH($A38,'2025_dec_raw'!$C$1:$AK$1,0)) -> -1.25443 | G38: =INDEX('2025_dec_transform'!$C$1:$AQ$139,MATCH($C$1,'2025_dec_transform'!$C$1:$C$139,0),MATCH($A38,'2025_dec_transform'!$C$1:$AQ$1,0)) -> -1.7760799 | H38: =F38-D38 -> -0.077311 | I38: =G38-E38 -> -0.12031728
A39: rule_law | C39: Rule of Law (cross section z-score) | D39: =INDEX('2025_oct_raw'!$C$1:$AK$139,MATCH($C$1,'2025_oct_raw'!$C$1:$C$139,0),MATCH($A39,'2025_oct_raw'!$C$1:$AK$1,0)) -> -1.219338 | E39: =INDEX('2025_oct_transform'!$C$1:$AQ$139,MATCH($C$1,'2025_oct_transform'!$C$1:$C$139,0),MATCH($A39,'2025_oct_transform'!$C$1:$AQ$1,0)) -> -1.4791424 | F39: =INDEX('2025_dec_raw'!$C$1:$AK$139,MATCH($C$1,'2025_dec_raw'!$C$1:$C$139,0),MATCH($A39,'2025_dec_raw'!$C$1:$AK$1,0)) -> -1.267722 | G39: =INDEX('2025_dec_transform'!$C$1:$AQ$139,MATCH($C$1,'2025_dec_transform'!$C$1:$C$139,0),MATCH($A39,'2025_dec_transform'!$C$1:$AQ$1,0)) -> -1.4925143 | H39: =F39-D39 -> -0.048384 | I39: =G39-E39 -> -0.013371943
A40: cont_corrupt | C40: Control of Corruption (cross section z-score) | D40: =INDEX('2025_oct_raw'!$C$1:$AK$139,MATCH($C$1,'2025_oct_raw'!$C$1:$C$139,0),MATCH($A40,'2025_oct_raw'!$C$1:$AK$1,0)) -> -0.838301 | E40: =INDEX('2025_oct_transform'!$C$1:$AQ$139,MATCH($C$1,'2025_oct_transform'!$C$1:$C$139,0),MATCH($A40,'2025_oct_transform'!$C$1:$AQ$1,0)) -> -0.98624622 | F40: =INDEX('2025_dec_raw'!$C$1:$AK$139,MATCH($C$1,'2025_dec_raw'!$C$1:$C$139,0),MATCH($A40,'2025_dec_raw'!$C$1:$AK$1,0)) -> -0.997583 | G40: =INDEX('2025_dec_transform'!$C$1:$AQ$139,MATCH($C$1,'2025_dec_transform'!$C$1:$C$139,0),MATCH($A40,'2025_dec_transform'!$C$1:$AQ$1,0)) -> -1.1607119 | H40: =F40-D40 -> -0.159282 | I40: =G40-E40 -> -0.17446571
A41: fiscalperf_factor | B41: Fiscal Performance (7%) | C41: Average of Fiscal Balance, Govt Rev GDP, Interest to Rev | D41: - | E41: =INDEX('2025_oct_transform'!$C$1:$AQ$139,MATCH($C$1,'2025_oct_transform'!$C$1:$C$139,0),MATCH($A41,'2025_oct_transform'!$C$1:$AQ$1,0)) -> -0.99802823 | F41: - | G41: =INDEX('2025_dec_transform'!$C$1:$AQ$139,MATCH($C$1,'2025_dec_transform'!$C$1:$C$139,0),MATCH($A41,'2025_dec_transform'!$C$1:$AQ$1,0)) -> -0.99802879 | I41: =G41-E41 -> -5.6430916e-07
A42: fb_avg | C42: Average of Fiscal Balance 10Y Avg t-5 to t+4 (% of GDP) | D42: =INDEX('2025_oct_raw'!$C$1:$AK$139,MATCH($C$1,'2025_oct_raw'!$C$1:$C$139,0),MATCH($A42,'2025_oct_raw'!$C$1:$AK$1,0)) -> -11.042 | E42: =INDEX('2025_oct_transform'!$C$1:$AQ$139,MATCH($C$1,'2025_oct_transform'!$C$1:$C$139,0),MATCH($A42,'2025_oct_transform'!$C$1:$AQ$1,0)) -> -2.1377782 | F42: =INDEX('2025_dec_raw'!$C$1:$AK$139,MATCH($C$1,'2025_dec_raw'!$C$1:$C$139,0),MATCH($A42,'2025_dec_raw'!$C$1:$AK$1,0)) -> -11.042 | G42: =INDEX('2025_dec_transform'!$C$1:$AQ$139,MATCH($C$1,'2025_dec_transform'!$C$1:$C$139,0),MATCH($A42,'2025_dec_transform'!$C$1:$AQ$1,0)) -> -2.1377782 | H42: =F42-D42 -> 0 | I42: =G42-E42 -> 0
A43: gov_rev_gdp | C43: Government Revenue (% of GDP) | D43: =INDEX('2025_oct_raw'!$C$1:$AK$139,MATCH($C$1,'2025_oct_raw'!$C$1:$C$139,0),MATCH($A43,'2025_oct_raw'!$C$1:$AK$1,0)) -> 25.073 | E43: =INDEX('2025_oct_transform'!$C$1:$AQ$139,MATCH($C$1,'2025_oct_transform'!$C$1:$C$139,0),MATCH($A43,'2025_oct_transform'!$C$1:$AQ$1,0)) -> -0.3573749 | F43: =INDEX('2025_dec_raw'!$C$1:$AK$139,MATCH($C$1,'2025_dec_raw'!$C$1:$C$139,0),MATCH($A43,'2025_dec_raw'!$C$1:$AK$1,0)) -> 25.073 | G43: =INDEX('2025_dec_transform'!$C$1:$AQ$139,MATCH($C$1,'2025_dec_transform'!$C$1:$C$139,0),MATCH($A43,'2025_dec_transform'!$C$1:$AQ$1,0)) -> -0.3573749 | H43: =F43-D43 -> 0 | I43: =G43-E43 -> 0
A44: ir_rev | C44: Interest Payment (% of Revenue) | D44: =INDEX('2025_oct_raw'!$C$1:$AK$139,MATCH($C$1,'2025_oct_raw'!$C$1:$C$139,0),MATCH($A44,'2025_oct_raw'!$C$1:$AK$1,0)) -> 12.694931 | E44: =INDEX('2025_oct_transform'!$C$1:$AQ$139,MATCH($C$1,'2025_oct_transform'!$C$1:$C$139,0),MATCH($A44,'2025_oct_transform'!$C$1:$AQ$1,0)) -> -0.49893154 | F44: =INDEX('2025_dec_raw'!$C$1:$AK$139,MATCH($C$1,'2025_dec_raw'!$C$1:$C$139,0),MATCH($A44,'2025_dec_raw'!$C$1:$AK$1,0)) -> 12.694931 | G44: =INDEX('2025_dec_transform'!$C$1:$AQ$139,MATCH($C$1,'2025_dec_transform'!$C$1:$C$139,0),MATCH($A44,'2025_dec_transform'!$C$1:$AQ$1,0)) -> -0.49893324 | H44: =F44-D44 -> 0 | I44: =G44-E44 -> -1.6929275e-06
A45: gov_debt_gdp | B45: Government Debt (10%) | C45: Government Debt (% of GDP) | D45: =INDEX('2025_oct_raw'!$C$1:$AK$139,MATCH($C$1,'2025_oct_raw'!$C$1:$C$139,0),MATCH($A45,'2025_oct_raw'!$C$1:$AK$1,0)) -> 93.706 | E45: =INDEX('2025_oct_transform'!$C$1:$AQ$139,MATCH($C$1,'2025_oct_transform'!$C$1:$C$139,0),MATCH($A45,'2025_oct_transform'!$C$1:$AQ$1,0)) -> 0.99062149 | F45: =INDEX('2025_dec_raw'!$C$1:$AK$139,MATCH($C$1,'2025_dec_raw'!$C$1:$C$139,0),MATCH($A45,'2025_dec_raw'!$C$1:$AK$1,0)) -> 93.706 | G45: =INDEX('2025_dec_transform'!$C$1:$AQ$139,MATCH($C$1,'2025_dec_transform'!$C$1:$C$139,0),MATCH($A45,'2025_dec_transform'!$C$1:$AQ$1,0)) -> 0.99062149 | H45: =F45-D45 -> 0 | I45: =G45-E45 -> 0
A46: cab_avg | B46: External Performance (5%) | C46: Average Current Account Balance t-5 to t+4 (% of GDP) | D46: =INDEX('2025_oct_raw'!$C$1:$AK$139,MATCH($C$1,'2025_oct_raw'!$C$1:$C$139,0),MATCH($A46,'2025_oct_raw'!$C$1:$AK$1,0)) -> -0.77514286 | E46: =INDEX('2025_oct_transform'!$C$1:$AQ$139,MATCH($C$1,'2025_oct_transform'!$C$1:$C$139,0),MATCH($A46,'2025_oct_transform'!$C$1:$AQ$1,0)) -> 0.098618921 | F46: =INDEX('2025_dec_raw'!$C$1:$AK$139,MATCH($C$1,'2025_dec_raw'!$C$1:$C$139,0),MATCH($A46,'2025_dec_raw'!$C$1:$AK$1,0)) -> -0.77514286 | G46: =INDEX('2025_dec_transform'!$C$1:$AQ$139,MATCH($C$1,'2025_dec_transform'!$C$1:$C$139,0),MATCH($A46,'2025_dec_transform'!$C$1:$AQ$1,0)) -> 0.098618921 | H46: =F46-D46 -> 0 | I46: =G46-E46 -> 0
A47: reservebuffer_factor | B47: FX Reserves (4%) | C47: Average of FX reserves (% GDP) and Import Cover | D47: - | E47: =INDEX('2025_oct_transform'!$C$1:$AQ$139,MATCH($C$1,'2025_oct_transform'!$C$1:$C$139,0),MATCH($A47,'2025_oct_transform'!$C$1:$AQ$1,0)) -> -3.3590278 | F47: - | G47: =INDEX('2025_dec_transform'!$C$1:$AQ$139,MATCH($C$1,'2025_dec_transform'!$C$1:$C$139,0),MATCH($A47,'2025_dec_transform'!$C$1:$AQ$1,0)) -> -1.3162626 | H47: - | I47: =G47-E47 -> 2.0427651
A48: reserve_gdp | C48: FX Reserves (% of GDP) | D48: =INDEX('2025_oct_raw'!$C$1:$AK$139,MATCH($C$1,'2025_oct_raw'!$C$1:$C$139,0),MATCH($A48,'2025_oct_raw'!$C$1:$AK$1,0)) -> 0.034654838 | E48: =INDEX('2025_oct_transform'!$C$1:$AQ$139,MATCH($C$1,'2025_oct_transform'!$C$1:$C$139,0),MATCH($A48,'2025_oct_transform'!$C$1:$AQ$1,0)) -> -3.57261 | F48: =INDEX('2025_dec_raw'!$C$1:$AK$139,MATCH($C$1,'2025_dec_raw'!$C$1:$C$139,0),MATCH($A48,'2025_dec_raw'!$C$1:$AK$1,0)) -> 0.76786469 | G48: =INDEX('2025_dec_transform'!$C$1:$AQ$139,MATCH($C$1,'2025_dec_transform'!$C$1:$C$139,0),MATCH($A48,'2025_dec_transform'!$C$1:$AQ$1,0)) -> -1.6031107 | H48: =F48-D48 -> 0.73320986 | I48: =G48-E48 -> 1.9694993
A49: import_cover | C49: FX Reserves (months of imports) | D49: =INDEX('2025_oct_raw'!$C$1:$AK$139,MATCH($C$1,'2025_oct_raw'!$C$1:$C$139,0),MATCH($A49,'2025_oct_raw'!$C$1:$AK$1,0)) -> 0.027037 | E49: =INDEX('2025_oct_transform'!$C$1:$AQ$139,MATCH($C$1,'2025_oct_transform'!$C$1:$C$139,0),MATCH($A49,'2025_oct_transform'!$C$1:$AQ$1,0)) -> -3.1454456 | F49: =INDEX('2025_dec_raw'!$C$1:$AK$139,MATCH($C$1,'2025_dec_raw'!$C$1:$C$139,0),MATCH($A49,'2025_dec_raw'!$C$1:$AK$1,0)) -> 0.737872 | G49: =INDEX('2025_dec_transform'!$C$1:$AQ$139,MATCH($C$1,'2025_dec_transform'!$C$1:$C$139,0),MATCH($A49,'2025_dec_transform'!$C$1:$AQ$1,0)) -> -1.0294146 | H49: =F49-D49 -> 0.710835 | I49: =G49-E49 -> 2.116031
A50: reserve_fx | B50: Reserve Currency Status (5%) | C50: Reserve Currency Status (1 = Yes, 0 = No) | D50: =INDEX('2025_oct_raw'!$C$1:$AK$139,MATCH($C$1,'2025_oct_raw'!$C$1:$C$139,0),MATCH($A50,'2025_oct_raw'!$C$1:$AK$1,0)) -> 0 | E50: =INDEX('2025_oct_transform'!$C$1:$AQ$139,MATCH($C$1,'2025_oct_transform'!$C$1:$C$139,0),MATCH($A50,'2025_oct_transform'!$C$1:$AQ$1,0)) -> -0.52486557 | F50: =INDEX('2025_dec_raw'!$C$1:$AK$139,MATCH($C$1,'2025_dec_raw'!$C$1:$C$139,0),MATCH($A50,'2025_dec_raw'!$C$1:$AK$1,0)) -> 0 | G50: =INDEX('2025_dec_transform'!$C$1:$AQ$139,MATCH($C$1,'2025_dec_transform'!$C$1:$C$139,0),MATCH($A50,'2025_dec_transform'!$C$1:$AQ$1,0)) -> -0.52486557 | H50: =F50-D50 -> 0 | I50: =G50-E50 -> 0

Sheet Ratings
A1: name | B1: public_rating | C1: model_rating | D1: Adjustment | E1: LS_rating | F1: LS_letter | G1: distance_lower_bound | H1: ERV_Dot | I1: in ERV | J1: Analyst
A2: United States | B2: 21 | C2: 18.705977 | D2: 0 | E2: 18.705977 | F2: AA- | G2: 0.205977 | H2: ⚫ | I2: No | J2: BRIAN HORRIGAN
A3: United Kingdom | B3: 19.333333 | C3: 19.153396 | D3: 0 | E3: 19.153396 | F3: AA- | G3: 0.65339647 | H3: ⚫ | I3: No | J3: JON LEVY
A4: Austria | B4: 20.666667 | C4: 18.723972 | D4: 0 | E4: 18.723972 | F4: AA- | G4: 0.22397205 | H4: ⚫ | I4: No | J4: Not covered
A5: Belgium | B5: 19 | C5: 17.541837 | D5: 0 | E5: 17.541837 | F5: A+ | G5: 0.041836822 | H5: ⚫ | I5: No | J5: Not covered
A6: Denmark | B6: 22 | C6: 23.251883 | D6: 0 | E6: 22 | F6: AAA | G6: 1 | H6: ⚫ | I6: No | J6: Not covered
A7: France | B7: 18.666667 | C7: 17.913243 | D7: 0.2 | E7: 18.113243 | F7: A+ | G7: 0.61324323 | H7: ⚫ | I7: No | J7: JON LEVY
A8: Germany | B8: 22 | C8: 21.331576 | D8: 0.4 | E8: 21.731576 | F8: AAA | G8: 0.2315757 | H8: ⚫ | I8: No | J8: JON LEVY
A9: Italy | B9: 14.333333 | C9: 16.575605 | D9: 0 | E9: 16.575605 | F9: A | G9: 0.075605408 | H9: ⚫ | I9: No | J9: JON LEVY
A10: Luxembourg | B10: 22 | C10: 21.06722 | D10: 0 | E10: 21.06722 | F10: AA+ | G10: 0.56722023 | H10: ⚫ | I10: No | J10: Not covered
A11: Netherlands | B11: 22 | C11: 21.4562 | D11: 0 | E11: 21.4562 | F11: AA+ | G11: 0.95620032 | H11: ⚫ | I11: No | J11: Not covered
A12: Norway | B12: 22 | C12: 23.741085 | D12: 0 | E12: 22 | F12: AAA | G12: 1 | H12: ⚫ | I12: No | J12: JINGZHOU MENG
A13: Sweden | B13: 22 | C13: 21.812877 | D13: 0 | E13: 21.812877 | F13: AAA | G13: 0.31287702 | H13: ⚫ | I13: No | J13: JINGZHOU MENG
... A79: Vietnam | B79: 11.666667 | C79: 13.07901 | D79: 0 | E79: 13.07901 | F79: BBB- | G79: 0.57901001 | H79: ⚫ | I79: Yes | J79: HUANI ZHU
A80: Algeria | C80: 10.4754 | D80: 0 | E80: 10.4754 | F80: BB- | G80: 0.97539982 | H80: ⚫
A81: Angola | B81: 7 | C81: 7.9745947 | D81: -1 | E81: 6.9745947 | F81: B- | G81: 0.47459467 | H81: ⚫ | I81: Yes | J81: SAURABH LELE
A82: Botswana | B82: 15 | C82: 12.282028 | D82: 0 | E82: 12.282028 | F82: BB+ | G82: 0.78202798 | H82: ⚫ | I82: No | J82: Not covered
A83: Cameroon | B83: 7 | C83: 7.7166527 | D83: 0 | E83: 7.7166527 | F83: B | G83: 0.21665266 | H83: ⚫ | I83: Yes | J83: SAURABH LELE
A84: Cabo Verde | B84: 8 | C84: 9.5974388 | D84: 0 | E84: 9.5974388 | F84: BB- | G84: 0.097438838 | H84: ⚫ | I84: No | J84: Not covered
A85: Republic of Congo | B85: 5.6666667 | C85: 3.7726127 | D85: 0 | E85: 3.7726127 | F85: CCC- | G85: 0.27261269 | H85: ⚫ | I85: No | J85: Not covered
A86: Democratic Republic of the Congo | B86: 7 | C86: 6.3491191 | D86: 0 | E86: 6.3491191 | F86: CCC+ | G86: 0.84911914 | H86: ⚫ | I86: No | J86: Not covered
A87: Benin | B87: 9.3333333 | C87: 7.9366786 | D87: 0 | E87: 7.9366786 | F87: B | G87: 0.43667856 | H87: ⚫ | I87: No | J87: Not covered
A88: Ethiopia | B88: 2 | C88: 7.2218771 | D88: 0 | E88: 7.2218771 | F88: B- | G88: 0.72187713 | H88: ⚫ | I88: Yes | J88: SAURABH LELE
A89: Gabon | B89: 5 | C89: 7.6194959 | D89: -1.5 | E89: 6.1194959 | F89: CCC+ | G89: 0.61949592 | H89: ⚫ | I89: Yes | J89: SAURABH LELE
A90: Ghana | B90: 6.3333333 | C90: 7.3490591 | D90: -1 | E90: 6.3490591 | F90: CCC+ | G90: 0.84905914 | H90: ⚫ | I90: Yes | J90: SAURABH LELE
A91: Côte d'Ivoire | B91: 10.666667 | C91: 9.8343364 | D91: 1.5 | E91: 11.334336 | F91: BB | G91: 0.83433635 | H91: ⚫ | I91: Yes | J91: SAURABH LELE
A92: Kenya | B92: 7 | C92: 8.6955272 | D92: -0.5 | E92: 8.1955272 | F92: B | G92: 0.6955272 | H92: ⚫ | I92: Yes | J92: SAURABH LELE
... A139: Romania | B139: 13 | C139: 13.805774 | D139: -1.4 | E139: 12.405774 | F139: BB+ | G139: 0.90577398 | H139: ⚫ | I139: Yes | J139: RAMSEY ANDRAWIS

Sheet 2023_old
A1: cc | B1: year | C1: name | D1: rating | E1: predicted_rating | F1: resid | G1: wealth_factor | H1: size_factor | I1: growth_factor | J1: inflation_factor | K1: default_factor | L1: governance_factor | M1: fiscalperf_factor | N1: govdebt_factor | O1: extperf_factor | P1: reservebuffer_factor | Q1: reservestatus_factor | R1: ngdp_pc | S1: median_ngdp_pc | T1: detrend_median_ngdp_pc | U1: trend_median_ngdp_pc | V1: ngdp | W1: median_ngdp | X1: detrend_median_ngdp | Y1: trend_median_ngdp | Z1: growth_avg | AA1: inf_avg | AB1: default_hist | AC1: default_decay | AD1: voice_acct | AE1: pol_stab | AF1: gov_eff | AG1: reg_qual | AH1: rule_law | AI1: cont_corrupt | AJ1: fb_avg | AK1: gov_rev_gdp | AL1: ir_rev | AM1: gov_debt_gdp | AN1: cab_avg | AO1: reserve_gdp | AP1: import_cover | AQ1: reserve_fx
A2: 111 | B2: 2023 | C2: United States | D2: 21.333333 | E2: 19.029275 | F2: 2.3040584 | G2: 1.6614344 | H2: 2.8554324 | I2: -0.52759164 | J2: 0.28282165 | K2: 0.30213082 | L2: 0.90987171 | M2: -0.51474064 | N2: -1.7165755 | O2: -0.16133751 | P2: -2.3965533 | Q2: 1.9052497 | R2: 1.6614344 | S2: 9.1137513 | T2: 0.022102599 | U2: 9.0916487 | V2: 2.8554324 | W2: 4.6286621 | X2: 0.094936804 | Y2: 4.5337253 | Z2: -0.52759164 | AA2: -0.28282165 | AB2: -0.3610543 | AC2: -0.24320733 | AD2: 0.82446263 | AE2: 0.0058924098 | AF2: 1.0970561 | AG2: 1.2640173 | AH2: 1.2576697 | AI2: 1.0101322 | AJ2: -1.3046814 | AK2: 0.036896935 | AL2: -0.27643747 | AM2: 1.7165755 | AN2: -0.16133751 | AO2: -2.712037 | AP2: -2.0810697 | AQ2: 1.9052497
A3: 112 | B3: 2023 | C3: United Kingdom | D3: 19.333333 | E3: 19.233674 | F3: 0.099659818 | G3: 1.2704945 | H3: 1.7540306 | I3: -0.92463478 | J3: 0.24867021 | K3: 0.30213082 | L3: 1.1678865 | M3: 0.097672458 | N3: -1.1753189 | O3: -0.23399601 | P3: -0.60213319 | Q3: 1.9052497 | R3: 1.2704945 | S3: 9.1137513 | T3: 0.022102599 | U3: 9.0916487 | V3: 1.7540306 | W3: 4.6286621 | X3: 0.094936804 | Y3: 4.5337253 | Z3: -0.92463478 | AA3: -0.24867021 | AB3: -0.3610543 | AC3: -0.24320733 | AD3: 1.252749 | AE3: 0.58652216 | AF3: 1.0342592 | AG3: 1.4262373 | AH3: 1.3336252 | AI3: 1.3739263 | AJ3: -0.63404892 | AK3: 0.77305254 | AL3: 0.15401376 | AM3: 1.1753189 | AN3: -0.23399601 | AO3: -0.7002033 | AP3: -0.50406308 | AQ3: 1.9052497
A4: 122 | B4: 2023 | C4: Austria | D4: 21 | E4: 18.795248 | F4: 2.204752 | G4: 1.369164 | H4: 0.77017188 | I4: -0.83111527 | J4: 0.24309914 | K4: 0.30213082 | L4: 1.2393602 | M4: 0.77258859 | N4: -0.56838463 | O4: 0.30582854 | P4: -1.6526393 | Q4: 1.9052497 | R4: 1.369164 | S4: 9.1137513 | T4: 0.022102599 | U4: 9.0916487 | V4: 0.77017188 | W4: 4.6286621 | X4: 0.094936804 | Y4: 4.5337253 | Z4: -0.83111527 | AA4: -0.24309914 | AB4: -0.3610543 | AC4: -0.24320733 | AD4: 1.4195834 | AE4: 0.84131539 | AF4: 1.2196969 | AG4: 1.2272618 | AH4: 1.7077709 | AI4: 1.0205327 | AJ4: -0.0084995308 | AK4: 1.7049828 | AL4: 0.62128251 | AM4: 0.56838463 | AN4: 0.30582854 | AO4: -1.6868478 | AP4: -1.6184307 | AQ4: 1.9052497
A5: 124 | B5: 2023 | C5: Belgium | D5: 19.333333 | E5: 17.554461 | F5: 1.7788721 | G5: 1.3513205 | H5: 0.89074216 | I5: -0.80286731 | J5: 0.31567571 | K5: 0.30213082 | L5: 1.0218825 | M5: 0.52358695 | N5: -1.2557489 | O5: 0.07115932 | P5: -1.4421738 | Q5: 1.9052497 | R5: 1.3513205 | S5: 9.1137513 | T5: 0.022102599 | U5: 9.0916487 | V5: 0.89074216 | W5: 4.6286621 | X5: 0.094936804 | Y5: 4.5337253 | Z5: -0.80286731 | AA5: -0.31567571 | AB5: -0.3610543 | AC5: -0.24320733 | AD5: 1.3242276 | AE5: 0.45367637 | AF5: 0.89521734 | AG5: 1.0079023 | AH5: 1.2229596 | AI5: 1.227312 | AJ5: -0.53263083 | AK5: 1.633207 | AL5: 0.47018467 | AM5: 1.2557489 | AN5: 0.07115932 | AO5: -1.2784922 | AP5: -1.6058553 | AQ5: 1.9052497
A6: 128 | B6: 2023 | C6: Denmark | D6: 22 | E6: 23.012028 | F6: -1.0120279 | G6: 1.5163769 | H6: 0.64753099 | I6: -0.63700335 | J6: 0.3777779 | K6: 0.30213082 | L6: 1.7698904 | M6: 1.251327 | N6: 0.67396079 | O6: 1.4332184 | P6: 0.54832728 | Q6: 1.9052497 | R6: 1.5163769 | S6: 9.1137513 | T6: 0.022102599 | U6: 9.0916487 | V6: 0.64753099 | W6: 4.6286621 | X6: 0.094936804 | Y6: 4.5337253 | Z6: -0.63700335 | AA6: -0.3777779 | AB6: -0.3610543 | AC6: -0.24320733 | AD6: 1.7021874 | AE6: 0.98824427 | AF6: 1.9914874 | AG6: 1.7703085 | AH6: 1.8822413 | AI6: 2.2848736 | AJ6: 1.0395626 | AK6: 1.767436 | AL6: 0.94698235 | AM6: -0.67396079 | AN6: 1.4332184 | AO6: 0.58422422 | AP6: 0.51243033 | AQ6: 1.9052497
A7: 132 | B7: 2023 | C7: France | D7: 19.666667 | E7: 18.468881 | F7: 1.1977855 | G7: 1.1972556 | H7: 1.7036778 | I7: -0.8691867 | J7: 0.39506349 | K7: 0.30213082 | L7: 0.94904984 | M7: 0.57768211 | N7: -1.4328339 | O7: 0.088848734 | P7: -1.4326136 | Q7: 1.9052497 | R7: 1.1972556 | S7: 9.1137513 | T7: 0.022102599 | U7: 9.0916487 | V7: 1.7036778 | W7: 4.6286621 | X7: 0.094936804 | Y7: 4.5337253 | Z7: -0.8691867 | AA7: -0.39506349 | AB7: -0.3610543 | AC7: -0.24320733 | AD7: 1.1334158 | AE7: 0.38173612 | AF7: 1.0157567 | AG7: 0.99118441 | AH7: 1.0996007 | AI7: 1.0726053 | AJ7: -0.52583955 | AK7: 1.8141315 | AL7: 0.4447544 | AM7: 1.4328339 | AN7: 0.088848734 | AO7: -1.4555591 | AP7: -1.4096681 | AQ7: 1.9052497
A8: 134 | B8: 2023 | C8: Germany | D8: 22 | E8: 21.466101 | F8: 0.53389884 | G8: 1.349646 | H8: 1.9121006 | I8: -1.0209922 | J8: 0.27776571 | K8: 0.30213082 | L8: 1.2672908 | M8: 0.7547226 | N8: -0.1203657 | O8: 1.0582493 | P8: -1.5395165 | Q8: 1.9052497 | R8: 1.349646 | S8: 9.1137513 | T8: 0.022102599 | U8: 9.0916487 | V8: 1.9121006 | W8: 4.6286621 | X8: 0.094936804 | Y8: 4.5337253 | Z8: -1.0209922 | AA8: -0.27776571 | AB8: -0.3610543 | AC8: -0.24320733 | AD8: 1.4754885 | AE8: 0.67269141 | AF8: 1.0614513 | AG8: 1.3358428 | AH8: 1.4978565 | AI8: 1.5604146 | AJ8: 0.28828684 | AK8: 1.3404113 | AL8: 0.63546968 | AM8: 0.1203657 | AN8: 1.0582493 | AO8: -1.5706085 | AP8: -1.5084245 | AQ8: 1.9052497
A9: 136 | B9: 2023 | C9: Italy | D9: 13.666667 | E9: 16.496386 | F9: -2.8297189 | G9: 1.0922305 | H9: 1.5556689 | I9: -1.06928 | J9: 0.35066662 | K9: 0.30213082 | L9: 0.54432528 | M9: 0.29317024 | N9: -2.1277828 | O9: 0.42801222 | P9: -0.90886719 | Q9: 1.9052497 | R9: 1.0922305 | S9: 9.1137513 | T9: 0.022102599 | U9: 9.0916487 | V9: 1.5556689 | W9: 4.6286621 | X9: 0.094936804 | Y9: 4.5337253 | Z9: -1.06928 | AA9: -0.35066662 | AB9: -0.3610543 | AC9: -0.24320733 | AD9: 1.0898518 | AE9: 0.66830479 | AF9: 0.41802366 | AG9: 0.4125634 | AH9: 0.25050446 | AI9: 0.42670358 | AJ9: -0.57247634 | AK9: 1.4281097 | AL9: 0.0238773 | AM9: 2.1277828 | AN9: 0.42801222 | AO9: -0.96013718 | AP9: -0.85759721 | AQ9: 1.9052497
A10: 137 | B10: 2023 | C10: Luxembourg | D10: 22 | E10: 20.748664 | F10: 1.2513356 | G10: 2.0327943 | H10: -0.14397729 | I10: -0.53073516 | J10: 0.35246005 | K10: 0.30213082 | L10: 1.6981916 | M10: 0.91029767 | N10: 0.92703064 | O10: 0.70045247 | P10: -1.4981541 | Q10: 1.9052497 | R10: 2.0327943 | S10: 9.1137513 | T10: 0.022102599 | U10: 9.0916487 | V10: -0.14397729 | W10: 4.6286621 | X10: 0.094936804 | Y10: 4.5337253 | Z10: -0.53073516 | AA10: -0.35246005 | AB10: -0.3610543 | AC10: -0.24320733 | AD10: 1.6664665 | AE10: 1.2311991 | AF10: 1.8778576 | AG10: 1.8720047 | AH10: 1.7140783 | AI10: 1.8275432 | AJ10: 0.50984289 | AK10: 1.3350487 | AL10: 0.8860014 | AM10: -0.92703064 | AN10: 0.70045247 | AO10: -2.3386797 | AP10: -0.65762862 | AQ10: 1.9052497
A11: 138 | B11: 2023 | C11: Netherlands | D11: 22 | E11: 21.3671 | F11: 0.63290026 | G11: 1.4651433 | H11: 1.1862091 | I11: -0.64198058 | J11: 0.26219723 | K11: 0.30213082 | L11: 1.4952929 | M11: 0.7143679 | N11: 0.33696032 | O11: 1.2336564 | P11: -2.0233008 | Q11: 1.9052497 | R11: 1.4651433 | S11: 9.1137513 | T11: 0.022102599 | U11: 9.0916487 | V11: 1.1862091 | W11: 4.6286621 | X11: 0.094936804 | Y11: 4.5337253 | Z11: -0.64198058 | AA11: -0.26219723 | AB11: -0.3610543 | AC11: -0.24320733 | AD11: 1.5812798 | AE11: 0.75795176 | AF11: 1.5544735 | AG11: 1.7151645 | AH11: 1.5959556 | AI11: 1.7669324 | AJ11: 0.2893143 | AK11: 1.1735119 | AL11: 0.68027746 | AM11: -0.33696032 | AN11: 1.2336564 | AO11: -1.8277385 | AP11: -2.218863 | AQ11: 1.9052497
A12: 142 | B12: 2023 | C12: Norway | D12: 22 | E12: 23.808847 | F12: -1.8088475 | G12: 1.7040681 | H12: 0.73985482 | I12: -0.71733757 | J12: 0.2752282 | K12: 0.30213082 | L12: 1.6551482 | M12: 2.4488778 | N12: 0.3867186 | O12: 2.4058129 | P12: 0.40779863 | Q12: 1.9052497 | R12: 1.7040681 | S12: 9.1137513 | T12: 0.022102599 | U12: 9.0916487 | V12: 0.73985482 | W12: 4.6286621 | X12: 0.094936804 | Y12: 4.5337253 | Z12: -0.71733757 | AA12: -0.2752282 | AB12: -0.3610543 | AC12: -0.24320733 | AD12: 1.827689 | AE12: 1.0384835 | AF12: 1.7498419 | AG12: 1.4954666 | AH12: 1.801702 | AI12: 2.0177062 | AJ12: 3.452847 | AK12: 2.7287366 | AL12: 1.1650498 | AM12: -0.3867186 | AN12: 2.4058129 | AO12: 0.2799165 | AP12: 0.53568076 | AQ12: 1.9052497
A13: 144 | B13: 2023 | C13: Sweden | D13: 22 | E13: 21.795118 | F13: 0.20488235 | G13: 1.3507389 | H13: 0.83452117 | I13: -0.64918447 | J13: 0.23674582 | K13: 0.30213082 | L13: 1.5208156 | M13: 0.96748506 | N13: 0.72888659 | O13: 0.84562722 | P13: -0.20619644 | Q13: 1.9052497 | R13: 1.3507389 | S13: 9.1137513 | T13: 0.022102599 | U13: 9.0916487 | V13: 0.83452117 | W13: 4.6286621 | X13: 0.094936804 | Y13: 4.5337253 | Z13: -0.64918447 | AA13: -0.23674582 | AB13: -0.3610543 | AC13: -0.24320733 | AD13: 1.6019835 | AE13: 0.87764249 | AF13: 1.5274215 | AG13: 1.6323146 | AH13: 1.5546071 | AI13: 1.9309243 | AJ13: 0.61025858 | AK13: 1.5569762 | AL13: 0.73522044 | AM13: -0.72888659 | AN13: 0.84562722 | AO13: -0.1805197 | AP13: -0.23187319 | AQ13: 1.9052497
... A138: 968 | B138: 2023 | C138: Romania | D138: 13 | E138: 14.046677 | F138: -1.0466774 | G138: 0.51937183 | H138: 0.57306196 | I138: 0.095435133 | J138: -0.15817071 | K138: 0.30213082 | L138: 0.11779894 | M138: -0.17922926 | N138: 0.16412604 | O138: -0.64509386 | P138: 0.32681456 | Q138: -0.52486557 | R138: 0.51937183 | S138: 9.1137513 | T138: 0.022102599 | U138: 9.0916487 | V138: 0.57306196 | W138: 4.6286621 | X138: 0.094936804 | Y138: 4.5337253 | Z138: 0.095435133 | AA138: 0.15817071 | AB138: -0.3610543 | AC138: -0.24320733 | AD138: 0.40706558 | AE138: 0.41754898 | AF138: -0.37027317 | AG138: 0.043304124 | AH138: 0.30107876 | AI138: -0.091930606 | AJ138: -0.84650817 | AK138: 0.13490801 | AL138: 0.17391238 | AM138: -0.16412604 | AN138: -0.64509386 | AO138: 0.39544703 | AP138: 0.25818208 | AQ138: -0.52486557

Sheet 2023_new
A1: cc | B1: year | C1: name | D1: rating | E1: predicted_rating | F1: resid | G1: wealth_factor | H1: size_factor | I1: growth_factor | J1: inflation_factor | K1: default_factor | L1: governance_factor | M1: fiscalperf_factor | N1: govdebt_factor | O1: extperf_factor | P1: reservebuffer_factor | Q1: reservestatus_factor | R1: ngdp_pc | S1: median_ngdp_pc | T1: detrend_median_ngdp_pc | U1: trend_median_ngdp_pc | V1: ngdp | W1: median_ngdp | X1: detrend_median_ngdp | Y1: trend_median_ngdp | Z1: growth_avg | AA1: inf_avg | AB1: default_hist | AC1: default_decay | AD1: voice_acct | AE1: pol_stab | AF1: gov_eff | AG1: reg_qual | AH1: rule_law | AI1: cont_corrupt | AJ1: fb_avg | AK1: gov_rev_gdp | AL1: ir_rev | AM1: gov_debt_gdp | AN1: cab_avg | AO1: reserve_gdp | AP1: import_cover | AQ1: reserve_fx
A2: 111 | B2: 2023 | C2: United States | D2: 21.333333 | E2: 18.898517 | F2: 2.4348163 | G2: 1.6614344 | H2: 2.8554324 | I2: -0.52759164 | J2: 0.28282165 | K2: 0.30213082 | L2: 0.83764433 | M2: -0.51474114 | N2: -1.7165755 | O2: -0.16133751 | P2: -2.3964739 | Q2: 1.9052497 | R2: 1.6614344 | S2: 9.1137513 | T2: 0.022102599 | U2: 9.0916487 | V2: 2.8554324 | W2: 4.6286621 | X2: 0.094936804 | Y2: 4.5337253 | Z2: -0.52759164 | AA2: -0.28282165 | AB2: -0.3610543 | AC2: -0.24320733 | AD2: 0.79071613 | AE2: -0.27336381 | AF2: 1.1947255 | AG2: 1.3285642 | AH2: 0.90966121 | AI2: 1.0755628 | AJ2: -1.3046814 | AK2: 0.036896935 | AL2: -0.27643899 | AM2: 1.7165755 | AN2: -0.16133751 | AO2: -2.7125494 | AP2: -2.0803984 | AQ2: 1.9052497
A3: 112 | B3: 2023 | C3: United Kingdom | D3: 19.333333 | E3: 19.088919 | F3: 0.2444139 | G3: 1.2704945 | H3: 1.7540306 | I3: -0.92463478 | J3: 0.24867021 | K3: 0.30213082 | L3: 1.1126805 | M3: 0.097672065 | N3: -1.1753189 | O3: -0.23399601 | P3: -0.60163945 | Q3: 1.9052497 | R3: 1.2704945 | S3: 9.1137513 | T3: 0.022102599 | U3: 9.0916487 | V3: 1.7540306 | W3: 4.6286621 | X3: 0.094936804 | Y3: 4.5337253 | Z3: -0.92463478 | AA3: -0.24867021 | AB3: -0.3610543 | AC3: -0.24320733 | AD3: 1.2144678 | AE3: 0.40228747 | AF3: 0.94367181 | AG3: 1.5115984 | AH3: 1.2434715 | AI3: 1.3605859 | AJ3: -0.63404892 | AK3: 0.77305254 | AL3: 0.15401258 | AM3: 1.1753189 | AN3: -0.23399601 | AO3: -0.69989992 | AP3: -0.50337898 | AQ3: 1.9052497
A4: 122 | B4: 2023 | C4: Austria | D4: 21 | E4: 18.957766 | F4: 2.0422337 | G4: 1.369164 | H4: 0.77017188 | I4: -0.83111527 | J4: 0.24309914 | K4: 0.30213082 | L4: 1.3053375 | M4: 0.77258832 | N4: -0.56838463 | O4: 0.30582854 | P4: -1.6523367 | Q4: 1.9052497 | R4: 1.369164 | S4: 9.1137513 | T4: 0.022102599 | U4: 9.0916487 | V4: 0.77017188 | W4: 4.6286621 | X4: 0.094936804 | Y4: 4.5337253 | Z4: -0.83111527 | AA4: -0.24309914 | AB4: -0.3610543 | AC4: -0.24320733 | AD4: 1.4118524 | AE4: 0.80335897 | AF4: 1.4456689 | AG4: 1.3070708 | AH4: 1.661046 | AI4: 1.2030281 | AJ4: -0.0084995308 | AK4: 1.7049828 | AL4: 0.6212817 | AM4: 0.56838463 | AN4: 0.30582854 | AO4: -1.6869308 | AP4: -1.6177427 | AQ4: 1.9052497
A5: 124 | B5: 2023 | C5: Belgium | D5: 19.333333 | E5: 17.735677 | F5: 1.5976563 | G5: 1.3513205 | H5: 0.89074216 | I5: -0.80286731 | J5: 0.31567571 | K5: 0.30213082 | L5: 1.0734132 | M5: 0.52358664 | N5: -1.2557489 | O5: 0.07115932 | P5: -1.4134719 | Q5: 1.9052497 | R5: 1.3513205 | S5: 9.1137513 | T5: 0.022102599 | U5: 9.0916487 | V5: 0.89074216 | W5: 4.6286621 | X5: 0.094936804 | Y5: 4.5337253 | Z5: -0.80286731 | AA5: -0.31567571 | AB5: -0.3610543 | AC5: -0.24320733 | AD5: 1.5017598 | AE5: 0.1990069 | AF5: 0.97406611 | AG5: 1.1675274 | AH5: 1.2452427 | AI5: 1.3528766 | AJ5: -0.53263083 | AK5: 1.633207 | AL5: 0.47018374 | AM5: 1.2557489 | AN5: 0.07115932 | AO5: -1.2217635 | AP5: -1.6051802 | AQ5: 1.9052497
A6: 128 | B6: 2023 | C6: Denmark | D6: 22 | E6: 23.110471 | F6: -1.1104711 | G6: 1.5163769 | H6: 0.64753099 | I6: -0.63700335 | J6: 0.3777779 | K6: 0.30213082 | L6: 1.8503604 | M6: 1.2513268 | N6: 0.67396079 | O6: 1.4332184 | P6: 0.54908219 | Q6: 1.9052497 | R6: 1.5163769 | S6: 9.1137513 | T6: 0.022102599 | U6: 9.0916487 | V6: 0.64753099 | W6: 4.6286621 | X6: 0.094936804 | Y6: 4.5337253 | Z6: -0.63700335 | AA6: -0.3777779 | AB6: -0.3610543 | AC6: -0.24320733 | AD6: 1.944824 | AE6: 1.0427675 | AF6: 1.8745483 | AG6: 1.9746202 | AH6: 2.0454802 | AI6: 2.2199222 | AJ6: 1.0395626 | AK6: 1.767436 | AL6: 0.94698179 | AM6: -0.67396079 | AN6: 1.4332184 | AO6: 0.58504166 | AP6: 0.51312271 | AQ6: 1.9052497
A7: 132 | B7: 2023 | C7: France | D7: 19.666667 | E7: 18.36325 | F7: 1.3034169 | G7: 1.1972556 | H7: 1.7036778 | I7: -0.8691867 | J7: 0.39506349 | K7: 0.30213082 | L7: 0.90804671 | M7: 0.5776818 | N7: -1.4328339 | O7: 0.088848734 | P7: -1.4323325 | Q7: 1.9052497 | R7: 1.1972556 | S7: 9.1137513 | T7: 0.022102599 | U7: 9.0916487 | V7: 1.7036778 | W7: 4.6286621 | X7: 0.094936804 | Y7: 4.5337253 | Z7: -0.8691867 | AA7: -0.39506349 | AB7: -0.3610543 | AC7: -0.24320733 | AD7: 1.1297172 | AE7: -0.06354428 | AF7: 1.1870391 | AG7: 1.0996733 | AH7: 0.9462337 | AI7: 1.1491612 | AJ7: -0.52583955 | AK7: 1.8141315 | AL7: 0.44475345 | AM7: 1.4328339 | AN7: 0.088848734 | AO7: -1.4555682 | AP7: -1.4090969 | AQ7: 1.9052497
A8: 134 | B8: 2023 | C8: Germany | D8: 22 | E8: 21.65122 | F8: 0.34878016 | G8: 1.349646 | H8: 1.9121006 | I8: -1.0209922 | J8: 0.27776571 | K8: 0.30213082 | L8: 1.3550906 | M8: 0.75472234 | N8: -0.1203657 | O8: 1.0582493 | P8: -1.5392033 | Q8: 1.9052497 | R8: 1.349646 | S8: 9.1137513 | T8: 0.022102599 | U8: 9.0916487 | V8: 1.9121006 | W8: 4.6286621 | X8: 0.094936804 | Y8: 4.5337253 | Z8: -1.0209922 | AA8: -0.27776571 | AB8: -0.3610543 | AC8: -0.24320733 | AD8: 1.5850057 | AE8: 0.56796 | AF8: 1.4255611 | AG8: 1.3788734 | AH8: 1.5832603 | AI8: 1.5898828 | AJ8: 0.28828684 | AK8: 1.3404113 | AL8: 0.63546888 | AM8: 0.1203657 | AN8: 1.0582493 | AO8: -1.5706581 | AP8: -1.5077486 | AQ8: 1.9052497
A9: 136 | B9: 2023 | C9: Italy | D9: 13.666667 | E9: 16.772362 | F9: -3.105695 | G9: 1.0922305 | H9: 1.5556689 | I9: -1.06928 | J9: 0.35066662 | K9: 0.30213082 | L9: 0.6127735 | M9: 0.29316981 | N9: -2.1277828 | O9: 0.42801222 | P9: -0.90843542 | Q9: 1.9052497 | R9: 1.0922305 | S9: 9.1137513 | T9: 0.022102599 | U9: 9.0916487 | V9: 1.5556689 | W9: 4.6286621 | X9: 0.094936804 | Y9: 4.5337253 | Z9: -1.06928 | AA9: -0.35066662 | AB9: -0.3610543 | AC9: -0.24320733 | AD9: 1.0339907 | AE9: 0.52911491 | AF9: 0.61988726 | AG9: 0.47879794 | AH9: 0.57534207 | AI9: 0.43950816 | AJ9: -0.57247634 | AK9: 1.4281097 | AL9: 0.023876019 | AM9: 2.1277828 | AN9: 0.42801222 | AO9: -0.95993979 | AP9: -0.85693106 | AQ9: 1.9052497
A10: 137 | B10: 2023 | C10: Luxembourg | D10: 22 | E10: 20.774039 | F10: 1.2259609 | G10: 2.0327943 | H10: -0.14397729 | I10: -0.53073516 | J10: 0.35246005 | K10: 0.30213082 | L10: 1.7308632 | M10: 0.91029747 | N10: 0.92703064 | O10: 0.70045247 | P10: -1.4979933 | Q10: 1.9052497 | R10: 2.0327943 | S10: 9.1137513 | T10: 0.022102599 | U10: 9.0916487 | V10: -0.14397729 | W10: 4.6286621 | X10: 0.094936804 | Y10: 4.5337253 | Z10: -0.53073516 | AA10: -0.35246005 | AB10: -0.3610543 | AC10: -0.24320733 | AD10: 1.6681751 | AE10: 1.1812252 | AF10: 2.0903329 | AG10: 1.7988298 | AH10: 1.7375079 | AI10: 1.9091085 | AJ10: 0.50984289 | AK10: 1.3350487 | AL10: 0.8860008 | AM10: -0.92703064 | AN10: 0.70045247 | AO10: -2.3390407 | AP10: -0.65694577 | AQ10: 1.9052497
A11: 138 | B11: 2023 | C11: Netherlands | D11: 22 | E11: 21.407861 | F11: 0.59213909 | G11: 1.4651433 | H11: 1.1862091 | I11: -0.64198058 | J11: 0.26219723 | K11: 0.30213082 | L11: 1.5334098 | M11: 0.71436765 | N11: 0.33696032 | O11: 1.2336564 | P11: -2.0231127 | Q11: 1.9052497 | R11: 1.4651433 | S11: 9.1137513 | T11: 0.022102599 | U11: 9.0916487 | V11: 1.1862091 | W11: 4.6286621 | X11: 0.094936804 | Y11: 4.5337253 | Z11: -0.64198058 | AA11: -0.26219723 | AB11: -0.3610543 | AC11: -0.24320733 | AD11: 1.7035877 | AE11: 0.69120629 | AF11: 1.6414676 | AG11: 1.6608843 | AH11: 1.7254626 | AI11: 1.7778503 | AJ11: 0.2893143 | AK11: 1.1735119 | AL11: 0.68027669 | AM11: -0.33696032 | AN11: 1.2336564 | AO11: -1.8279032 | AP11: -2.2183221 | AQ11: 1.9052497
A12: 142 | B12: 2023 | C12: Norway | D12: 22 | E12: 23.775678 | F12: -1.7756778 | G12: 1.7040681 | H12: 0.73985482 | I12: -0.71733757 | J12: 0.2752282 | K12: 0.30213082 | L12: 1.7129826 | M12: 2.4488777 | N12: 0.3867186 | O12: 2.4058129 | P12: 0.39492916 | Q12: 1.9052497 | R12: 1.7040681 | S12: 9.1137513 | T12: 0.022102599 | U12: 9.0916487 | V12: 0.73985482 | W12: 4.6286621 | X12: 0.094936804 | Y12: 4.5337253 | Z12: -0.71733757 | AA12: -0.2752282 | AB12: -0.3610543 | AC12: -0.24320733 | AD12: 1.9577335 | AE12: 1.0856028 | AF12: 1.6823055 | AG12: 1.5649116 | AH12: 2.0148819 | AI12: 1.9724602 | AJ12: 3.452847 | AK12: 2.7287366 | AL12: 1.1650494 | AM12: -0.3867186 | AN12: 2.4058129 | AO12: 0.25557259 | AP12: 0.53428572 | AQ12: 1.9052497
A13: 144 | B13: 2023 | C13: Sweden | D13: 22 | E13: 21.816798 | F13: 0.18320229 | G13: 1.3507389 | H13: 0.83452117 | I13: -0.64918447 | J13: 0.23674582 | K13: 0.30213082 | L13: 1.5655746 | M13: 0.96748482 | N13: 0.72888659 | O13: 0.84562722 | P13: -0.20557425 | Q13: 1.9052497 | R13: 1.3507389 | S13: 9.1137513 | T13: 0.022102599 | U13: 9.0916487 | V13: 0.83452117 | W13: 4.6286621 | X13: 0.094936804 | Y13: 4.5337253 | Z13: -0.64918447 | AA13: -0.23674582 | AB13: -0.3610543 | AC13: -0.24320733 | AD13: 1.7365364 | AE13: 0.89621125 | AF13: 1.5753491 | AG13: 1.6079226 | AH13: 1.7009365 | AI13: 1.8764918 | AJ13: 0.61025858 | AK13: 1.5569762 | AL13: 0.73521972 | AM13: -0.72888659 | AN13: 0.84562722 | AO13: -0.17996417 | AP13: -0.23118432 | AQ13: 1.9052497
... A138: 968 | B138: 2023 | C138: Romania | D138: 13 | E138: 14.178187 | F138: -1.1781868 | G138: 0.51937183 | H138: 0.57306196 | I138: 0.095435133 | J138: -0.15817071 | K138: 0.30213082 | L138: 0.17150644 | M138: -0.17922965 | N138: 0.16412604 | O138: -0.64509386 | P138: 0.33028412 | Q138: -0.52486557 | R138: 0.51937183 | S138: 9.1137513 | T138: 0.022102599 | U138: 9.0916487 | V138: 0.57306196 | W138: 4.6286621 | X138: 0.094936804 | Y138: 4.5337253 | Z138: 0.095435133 | AA138: 0.15817071 | AB138: -0.3610543 | AC138: -0.24320733 | AD138: 0.39138139 | AE138: 0.55874119 | AF138: -0.20100825 | AG138: 0.073086481 | AH138: 0.31801952 | AI138: -0.11118172 | AJ138: -0.84650817 | AK138: 0.13490801 | AL138: 0.17391122 | AM138: -0.16412604 | AN138: -0.64509386 | AO138: 0.40169585 | AP138: 0.25887239 | AQ138: -0.52486557

Sheet 2024_new
A1: cc | B1: year | C1: name | D1: rating | E1: predicted_rating | F1: resid | G1: wealth_factor | H1: size_factor | I1: growth_factor | J1: inflation_factor | K1: default_factor | L1: governance_factor | M1: fiscalperf_factor | N1: govdebt_factor | O1: extperf_factor | P1: reservebuffer_factor | Q1: reservestatus_factor | R1: ngdp_pc | S1: median_ngdp_pc | T1: detrend_median_ngdp_pc | U1: trend_median_ngdp_pc | V1: ngdp | W1: median_ngdp | X1: detrend_median_ngdp | Y1: trend_median_ngdp | Z1: growth_avg | AA1: inf_avg | AB1: default_hist | AC1: default_decay | AD1: voice_acct | AE1: pol_stab | AF1: gov_eff | AG1: reg_qual | AH1: rule_law | AI1: cont_corrupt | AJ1: fb_avg | AK1: gov_rev_gdp | AL1: ir_rev | AM1: gov_debt_gdp | AN1: cab_avg | AO1: reserve_gdp | AP1: import_cover | AQ1: reserve_fx
A2: 111 | B2: 2024 | C2: United States | D2: 21.333333 | E2: 18.820344 | F2: 2.5129891 | G2: 1.690399 | H2: 2.867654 | I2: -0.39573874 | J2: 0.28553087 | K2: 0.30213082 | L2: 0.82855756 | M2: -0.53474057 | N2: -1.7856425 | O2: -0.18443203 | P2: -2.4592715 | Q2: 1.9052497 | R2: 1.690399 | S2: 9.2051622 | T2: 0.10860756 | U2: 9.0965546 | V2: 2.867654 | W2: 4.672296 | X2: 0.10991564 | Y2: 4.5623803 | Z2: -0.39573874 | AA2: -0.28553087 | AB2: -0.3610543 | AC2: -0.24320733 | AD2: 0.81618166 | AE2: -0.15540861 | AF2: 1.1963812 | AG2: 1.2381495 | AH2: 0.9108459 | AI2: 0.96519575 | AJ2: -1.2719279 | AK2: 0.039784467 | AL2: -0.37207832 | AM2: 1.7856425 | AN2: -0.18443203 | AO2: -2.7888722 | AP2: -2.1296708 | AQ2: 1.9052497
A3: 112 | B3: 2024 | C3: United Kingdom | D3: 19.333333 | E3: 19.152893 | F3: 0.18044066 | G3: 1.3155084 | H3: 1.7797921 | I3: -0.87804966 | J3: 0.27187029 | K3: 0.30213082 | L3: 1.0991731 | M3: 0.1027623 | N3: -1.1995729 | O3: -0.10773911 | P3: -0.6504941 | Q3: 1.9052497 | R3: 1.3155084 | S3: 9.2051622 | T3: 0.10860756 | U3: 9.0965546 | V3: 1.7797921 | W3: 4.672296 | X3: 0.10991564 | Y3: 4.5623803 | Z3: -0.87804966 | AA3: -0.27187029 | AB3: -0.3610543 | AC3: -0.24320733 | AD3: 1.2675474 | AE3: 0.26915693 | AF3: 0.99717107 | AG3: 1.4217018 | AH3: 1.2429962 | AI3: 1.3964651 | AJ3: -0.68675024 | AK3: 0.7331221 | AL3: 0.26191503 | AM3: 1.1995729 | AN3: -0.10773911 | AO3: -0.78352578 | AP3: -0.51746241 | AQ3: 1.9052497
A4: 122 | B4: 2024 | C4: Austria | D4: 21 | E4: 18.672103 | F4: 2.3278965 | G4: 1.3787467 | H4: 0.7674339 | I4: -1.056313 | J4: 0.24752547 | K4: 0.30213082 | L4: 1.2334629 | M4: 0.71966684 | N4: -0.63175627 | O4: 0.4777443 | P4: -1.8007155 | Q4: 1.9052497 | R4: 1.3787467 | S4: 9.2051622 | T4: 0.10860756 | U4: 9.0965546 | V4: 0.7674339 | W4: 4.672296 | X4: 0.10991564 | Y4: 4.5623803 | Z4: -1.056313 | AA4: -0.24752547 | AB4: -0.3610543 | AC4: -0.24320733 | AD4: 1.3819502 | AE4: 0.5506054 | AF4: 1.3722223 | AG4: 1.2364995 | AH4: 1.6826228 | AI4: 1.1768774 | AJ4: -0.22692307 | AK4: 1.8134715 | AL4: 0.57245211 | AM4: 0.63175627 | AN4: 0.4777443 | AO4: -1.7596579 | AP4: -1.841773 | AQ4: 1.9052497
A5: 124 | B5: 2024 | C5: Belgium | D5: 19.333333 | E5: 17.644544 | F5: 1.6887896 | G5: 1.3654938 | H5: 0.89135513 | I5: -0.77684601 | J5: 0.3317784 | K5: 0.30213082 | L5: 1.0532288 | M5: 0.49367798 | N5: -1.2962001 | O5: 0.2234719 | P5: -1.615386 | Q5: 1.9052497 | R5: 1.3654938 | S5: 9.2051622 | T5: 0.10860756 | U5: 9.0965546 | V5: 0.89135513 | W5: 4.672296 | X5: 0.10991564 | Y5: 4.5623803 | Z5: -0.77684601 | AA5: -0.3317784 | AB5: -0.3610543 | AC5: -0.24320733 | AD5: 1.482072 | AE5: 0.10519436 | AF5: 1.0083566 | AG5: 1.1121873 | AH5: 1.2568859 | AI5: 1.3546767 | AJ5: -0.65755526 | AK5: 1.6964852 | AL5: 0.44210402 | AM5: 1.2962001 | AN5: 0.2234719 | AO5: -1.5089518 | AP5: -1.7218201 | AQ5: 1.9052497
A6: 128 | B6: 2024 | C6: Denmark | D6: 22 | E6: 23.040293 | F6: -1.0402928 | G6: 1.5454828 | H6: 0.65759838 | I6: -0.56164637 | J6: 0.40355365 | K6: 0.30213082 | L6: 1.7928139 | M6: 1.2916575 | N6: 0.73891604 | O6: 1.3560211 | P6: 0.54374185 | Q6: 1.9052497 | R6: 1.5454828 | S6: 9.2051622 | T6: 0.10860756 | U6: 9.0965546 | V6: 0.65759838 | W6: 4.672296 | X6: 0.10991564 | Y6: 4.5623803 | Z6: -0.56164637 | AA6: -0.40355365 | AB6: -0.3610543 | AC6: -0.24320733 | AD6: 1.9160566 | AE6: 0.88426567 | AF6: 1.825546 | AG6: 1.9067083 | AH6: 2.0346627 | AI6: 2.1896441 | AJ6: 1.1052701 | AK6: 1.8466369 | AL6: 0.92306549 | AM6: -0.73891604 | AN6: 1.3560211 | AO6: 0.54212983 | AP6: 0.54535388 | AQ6: 1.9052497
A7: 132 | B7: 2024 | C7: France | D7: 19.333333 | E7: 17.962134 | F7: 1.3711994 | G7: 1.2158262 | H7: 1.7054682 | I7: -0.90442024 | J7: 0.41152868 | K7: 0.30213082 | L7: 0.80220623 | M7: 0.46899732 | N7: -1.5307668 | O7: 0.14174888 | P7: -1.4125591 | Q7: 1.9052497 | R7: 1.2158262 | S7: 9.2051622 | T7: 0.10860756 | U7: 9.0965546 | V7: 1.7054682 | W7: 4.672296 | X7: 0.10991564 | Y7: 4.5623803 | Z7: -0.90442024 | AA7: -0.41152868 | AB7: -0.3610543 | AC7: -0.24320733 | AD7: 1.1017518 | AE7: -0.33139979 | AF7: 1.0151396 | AG7: 0.99957514 | AH7: 0.92903136 | AI7: 1.0991393 | AJ7: -0.81425586 | AK7: 1.8149565 | AL7: 0.40629131 | AM7: 1.5307668 | AN7: 0.14174888 | AO7: -1.4770769 | AP7: -1.3480413 | AQ7: 1.9052497
A8: 134 | B8: 2024 | C8: Germany | D8: 22 | E8: 21.437265 | F8: 0.56273478 | G8: 1.3636798 | H8: 1.9107651 | I8: -1.1472566 | J8: 0.31544676 | K8: 0.30213082 | L8: 1.3012734 | M8: 0.74100089 | N8: -0.15045404 | O8: 1.0035518 | P8: -1.5480784 | Q8: 1.9052497 | R8: 1.3636798 | S8: 9.2051622 | T8: 0.10860756 | U8: 9.0965546 | V8: 1.9107651 | W8: 4.672296 | X8: 0.10991564 | Y8: 4.5623803 | Z8: -1.1472566 | AA8: -0.31544676 | AB8: -0.3610543 | AC8: -0.24320733 | AD8: 1.5922117 | AE8: 0.10858056 | AF8: 1.4083937 | AG8: 1.4064671 | AH8: 1.6266154 | AI8: 1.6653721 | AJ8: 0.1985718 | AK8: 1.4322348 | AL8: 0.59219607 | AM8: 0.15045404 | AN8: 1.0035518 | AO8: -1.6156501 | AP8: -1.4805066 | AQ8: 1.9052497
A9: 136 | B9: 2024 | C9: Italy | D9: 13.666667 | E9: 16.562748 | F9: -2.8960817 | G9: 1.1105756 | H9: 1.5556195 | I9: -0.99833269 | J9: 0.37033709 | K9: 0.30213082 | L9: 0.54514429 | M9: 0.25016371 | N9: -2.1469248 | O9: 0.39983588 | P9: -0.87889348 | Q9: 1.9052497 | R9: 1.1105756 | S9: 9.2051622 | T9: 0.10860756 | U9: 9.0965546 | V9: 1.5556195 | W9: 4.672296 | X9: 0.10991564 | Y9: 4.5623803 | Z9: -0.99833269 | AA9: -0.37033709 | AB9: -0.3610543 | AC9: -0.24320733 | AD9: 1.0130186 | AE9: 0.33052136 | AF9: 0.55040968 | AG9: 0.41451204 | AH9: 0.54154645 | AI9: 0.42085766 | AJ9: -0.69020853 | AK9: 1.4611926 | AL9: -0.020492952 | AM9: 2.1469248 | AN9: 0.39983588 | AO9: -0.96366768 | AP9: -0.79411928 | AQ9: 1.9052497
A10: 137 | B10: 2024 | C10: Luxembourg | D10: 22 | E10: 20.990733 | F10: 1.0092669 | G10: 2.0533351 | H10: -0.13348895 | I10: -0.50558705 | J10: 0.35738244 | K10: 0.30213082 | L10: 1.7286095 | M10: 0.94338415 | N10: 0.88241211 | O10: 1.1649548 | P10: -1.5230828 | Q10: 1.9052497 | R10: 2.0533351 | S10: 9.2051622 | T10: 0.10860756 | U10: 9.0965546 | V10: -0.13348895 | W10: 4.672296 | X10: 0.10991564 | Y10: 4.5623803 | Z10: -0.50558705 | AA10: -0.35738244 | AB10: -0.3610543 | AC10: -0.24320733 | AD10: 1.6655116 | AE10: 1.2502946 | AF10: 1.9698481 | AG10: 1.8002716 | AH10: 1.7732029 | AI10: 1.9125281 | AJ10: 0.39396514 | AK10: 1.5256258 | AL10: 0.91056148 | AM10: -0.88241211 | AN10: 1.1649548 | AO10: -2.3929401 | AP10: -0.65322547 | AQ10: 1.9052497
A11: 138 | B11: 2024 | C11: Netherlands | D11: 22 | E11: 21.42857 | F11: 0.57142992 | G11: 1.5068451 | H11: 1.2062456 | I11: -0.65756717 | J11: 0.25490905 | K11: 0.30213082 | L11: 1.4922354 | M11: 0.68207644 | N11: 0.3960257 | O11: 1.3544565 | P11: -2.0337932 | Q11: 1.9052497 | R11: 1.5068451 | S11: 9.2051622 | T11: 0.10860756 | U11: 9.0965546 | V11: 1.2062456 | W11: 4.672296 | X11: 0.10991564 | Y11: 4.5623803 | Z11: -0.65756717 | AA11: -0.25490905 | AB11: -0.3610543 | AC11: -0.24320733 | AD11: 1.6527832 | AE11: 0.47421965 | AF11: 1.6424564 | AG11: 1.6651936 | AH11: 1.7140803 | AI11: 1.8046792 | AJ11: 0.20839535 | AK11: 1.1602293 | AL11: 0.67760467 | AM11: -0.3960257 | AN11: 1.3544565 | AO11: -1.8820075 | AP11: -2.1855789 | AQ11: 1.9052497
A12: 142 | B12: 2024 | C12: Norway | D12: 22 | E12: 23.42385 | F12: -1.4238504 | G12: 1.6942979 | H12: 0.72559302 | I12: -0.73506349 | J12: 0.32141849 | K12: 0.30213082 | L12: 1.6972911 | M12: 2.3874043 | N12: 0.42591956 | O12: 1.7740629 | P12: 0.41772847 | Q12: 1.9052497 | R12: 1.6942979 | S12: 9.2051622 | T12: 0.10860756 | U12: 9.0965546 | V12: 0.72559302 | W12: 4.672296 | X12: 0.10991564 | Y12: 4.5623803 | Z12: -0.73506349 | AA12: -0.32141849 | AB12: -0.3610543 | AC12: -0.24320733 | AD12: 1.9536842 | AE12: 1.0459816 | AF12: 1.7460731 | AG12: 1.605794 | AH12: 1.975525 | AI12: 1.8566888 | AJ12: 3.2693572 | AK12: 2.6662009 | AL12: 1.2266549 | AM12: -0.42591956 | AN12: 1.7740629 | AO12: 0.26801496 | AP12: 0.56744198 | AQ12: 1.9052497
A13: 144 | B13: 2024 | C13: Sweden | D13: 22 | E13: 21.829396 | F13: 0.1706044 | G13: 1.3762471 | H13: 0.84139003 | I13: -0.63538794 | J13: 0.33673894 | K13: 0.30213082 | L13: 1.5488989 | M13: 0.93910846 | N13: 0.69624227 | O13: 0.95035424 | P13: -0.21019516 | Q13: 1.9052497 | R13: 1.3762471 | S13: 9.2051622 | T13: 0.10860756 | U13: 9.0965546 | V13: 0.84139003 | W13: 4.672296 | X13: 0.10991564 | Y13: 4.5623803 | Z13: -0.63538794 | AA13: -0.33673894 | AB13: -0.3610543 | AC13: -0.24320733 | AD13: 1.7336721 | AE13: 0.68527622 | AF13: 1.6682843 | AG13: 1.6073434 | AH13: 1.7354015 | AI13: 1.8634159 | AJ13: 0.56494998 | AK13: 1.4993905 | AL13: 0.75298486 | AM13: -0.69624227 | AN13: 0.95035424 | AO13: -0.20848548 | AP13: -0.21190484 | AQ13: 1.9052497
... A138: 968 | B138: 2024 | C138: Romania | D138: 13 | E138: 13.943446 | F138: -0.94344633 | G138: 0.58653951 | H138: 0.60367295 | I138: -0.17263665 | J138: -0.14229697 | K138: 0.30213082 | L138: 0.13682122 | M138: -0.26689196 | N138: 0.017018248 | O138: -0.66406343 | P138: 0.32504669 | Q138: -0.52486557 | R138: 0.58653951 | S138: 9.2051622 | T138: 0.10860756 | U138: 9.0965546 | V138: 0.60367295 | W138: 4.672296 | X138: 0.10991564 | Y138: 4.5623803 | Z138: -0.17263665 | AA138: 0.14229697 | AB138: -0.3610543 | AC138: -0.24320733 | AD138: 0.2710415 | AE138: 0.15023786 | AF138: 0.12465041 | AG138: 0.11771164 | AH138: 0.27409631 | AI138: -0.11681042 | AJ138: -1.081747 | AK138: 0.15256321 | AL138: 0.12850793 | AM138: -0.017018248 | AN138: -0.66406343 | AO138: 0.3272716 | AP138: 0.32282179 | AQ138: -0.52486557

Sheet 2025_oct_transform
A1: cc | B1: year | C1: name | D1: rating | E1: predicted_rating | F1: resid | G1: wealth_factor | H1: size_factor | I1: growth_factor | J1: inflation_factor | K1: default_factor | L1: governance_factor | M1: fiscalperf_factor | N1: govdebt_factor | O1: extperf_factor | P1: reservebuffer_factor | Q1: reservestatus_factor | R1: ngdp_pc | S1: median_ngdp_pc | T1: detrend_median_ngdp_pc | U1: trend_median_ngdp_pc | V1: ngdp | W1: median_ngdp | X1: detrend_median_ngdp | Y1: trend_median_ngdp | Z1: growth_avg | AA1: inf_avg | AB1: default_hist | AC1: default_decay | AD1: voice_acct | AE1: pol_stab | AF1: gov_eff | AG1: reg_qual | AH1: rule_law | AI1: cont_corrupt | AJ1: fb_avg | AK1: gov_rev_gdp | AL1: ir_rev | AM1: gov_debt_gdp | AN1: cab_avg | AO1: reserve_gdp | AP1: import_cover | AQ1: reserve_fx
A2: 111 | B2: 2025 | C2: United States | D2: 21 | E2: 18.856549 | F2: 2.1434506 | G2: 1.7165951 | H2: 2.87566 | I2: -0.42158541 | J2: 0.256588 | K2: 0.30213082 | L2: 0.90987171 | M2: -0.59856299 | N2: -1.8614329 | O2: -0.26667229 | P2: -2.4129085 | Q2: 1.9052497 | R2: 1.7165951 | S2: 9.2569805 | T2: 0.15551987 | U2: 9.1014606 | V2: 2.87566 | W2: 4.6758099 | X2: 0.084774447 | Y2: 4.5910354 | Z2: -0.42158541 | AA2: -0.256588 | AB2: -0.3610543 | AC2: -0.24320733 | AD2: 0.82446263 | AE2: 0.0058924098 | AF2: 1.0970561 | AG2: 1.2640173 | AH2: 1.2576697 | AI2: 1.0101322 | AJ2: -1.4785982 | AK2: 0.083757451 | AL2: -0.40084818 | AM2: 1.8614329 | AN2: -0.26667229 | AO2: -2.7322519 | AP2: -2.0935651 | AQ2: 1.9052497
A3: 112 | B3: 2025 | C3: United Kingdom | D3: 19.333333 | E3: 19.33286 | F3: 0.0004730625 | G3: 1.3676964 | H3: 1.8079895 | I3: -0.89625584 | J3: 0.23216686 | K3: 0.30213082 | L3: 1.1678865 | M3: 0.081403644 | N3: -1.2588605 | O3: -0.12581645 | P3: -0.60202004 | Q3: 1.9052497 | R3: 1.3676964 | S3: 9.2569805 | T3: 0.15551987 | U3: 9.1014606 | V3: 1.8079895 | W3: 4.6758099 | X3: 0.084774447 | Y3: 4.5910354 | Z3: -0.89625584 | AA3: -0.23216686 | AB3: -0.3610543 | AC3: -0.24320733 | AD3: 1.252749 | AE3: 0.58652216 | AF3: 1.0342592 | AG3: 1.4262373 | AH3: 1.3336252 | AI3: 1.3739263 | AJ3: -0.70990574 | AK3: 0.82082056 | AL3: 0.13329612 | AM3: 1.2588605 | AN3: -0.12581645 | AO3: -0.713884 | AP3: -0.49015608 | AQ3: 1.9052497
A4: 122 | B4: 2025 | C4: Austria | D4: 20.666667 | E4: 18.750964 | F4: 1.9157029 | G4: 1.4324905 | H4: 0.79318469 | I4: -1.110102 | J4: 0.2170372 | K4: 0.30213082 | L4: 1.2393602 | M4: 0.64367348 | N4: -0.66609531 | O4: 0.44703351 | P4: -1.5350175 | Q4: 1.9052497 | R4: 1.4324905 | S4: 9.2569805 | T4: 0.15551987 | U4: 9.1014606 | V4: 0.79318469 | W4: 4.6758099 | X4: 0.084774447 | Y4: 4.5910354 | Z4: -1.110102 | AA4: -0.2170372 | AB4: -0.3610543 | AC4: -0.24320733 | AD4: 1.4195834 | AE4: 0.84131539 | AF4: 1.2196969 | AG4: 1.2272618 | AH4: 1.7077709 | AI4: 1.0205327 | AJ4: -0.46005688 | AK4: 1.8538969 | AL4: 0.53718039 | AM4: 0.66609531 | AN4: 0.44703351 | AO4: -1.4373217 | AP4: -1.6327133 | AQ4: 1.9052497
A5: 124 | B5: 2025 | C5: Belgium | D5: 19 | E5: 17.424721 | F5: 1.5752787 | G5: 1.4165765 | H5: 0.91617924 | I5: -0.80622913 | J5: 0.31042898 | K5: 0.30213082 | L5: 1.0218825 | M5: 0.44382669 | N5: -1.3739074 | O5: 0.14883499 | P5: -1.663122 | Q5: 1.9052497 | R5: 1.4165765 | S5: 9.2569805 | T5: 0.15551987 | U5: 9.1014606 | V5: 0.91617924 | W5: 4.6758099 | X5: 0.084774447 | Y5: 4.5910354 | Z5: -0.80622913 | AA5: -0.31042898 | AB5: -0.3610543 | AC5: -0.24320733 | AD5: 1.3242276 | AE5: 0.45367637 | AF5: 0.89521734 | AG5: 1.0079023 | AH5: 1.2229596 | AI5: 1.227312 | AJ5: -0.75626687 | AK5: 1.676025 | AL5: 0.41172195 | AM5: 1.3739074 | AN5: 0.14883499 | AO5: -1.4609952 | AP5: -1.8652488 | AQ5: 1.9052497
A6: 128 | B6: 2025 | C6: Denmark | D6: 22 | E6: 23.325837 | F6: -1.3258369 | G6: 1.5970641 | H6: 0.68409036 | I6: -0.61622124 | J6: 0.39882206 | K6: 0.30213082 | L6: 1.7698904 | M6: 1.2528404 | N6: 0.78959113 | O6: 1.5943498 | P6: 0.61700818 | Q6: 1.9052497 | R6: 1.5970641 | S6: 9.2569805 | T6: 0.15551987 | U6: 9.1014606 | V6: 0.68409036 | W6: 4.6758099 | X6: 0.084774447 | Y6: 4.5910354 | Z6: -0.61622124 | AA6: -0.39882206 | AB6: -0.3610543 | AC6: -0.24320733 | AD6: 1.7021874 | AE6: 0.98824427 | AF6: 1.9914874 | AG6: 1.7703085 | AH6: 1.8822413 | AI6: 2.2848736 | AJ6: 1.0603374 | AK6: 1.7624859 | AL6: 0.93569789 | AM6: -0.78959113 | AN6: 1.5943498 | AO6: 0.6569105 | AP6: 0.57710586 | AQ6: 1.9052497
A7: 132 | B7: 2025 | C7: France | D7: 18.666667 | E7: 18.393059 | F7: 0.27360755 | G7: 1.2568188 | H7: 1.7226357 | I7: -0.96632998 | J7: 0.40021483 | K7: 0.30213082 | L7: 0.94904984 | M7: 0.44103246 | N7: -1.6240323 | O7: 0.13602051 | P7: -1.100465 | Q7: 1.9052497 | R7: 1.2568188 | S7: 9.2569805 | T7: 0.15551987 | U7: 9.1014606 | V7: 1.7226357 | W7: 4.6758099 | X7: 0.084774447 | Y7: 4.5910354 | Z7: -0.96632998 | AA7: -0.40021483 | AB7: -0.3610543 | AC7: -0.24320733 | AD7: 1.1334158 | AE7: 0.38173612 | AF7: 1.0157567 | AG7: 0.99118441 | AH7: 1.0996007 | AI7: 1.0726053 | AJ7: -0.91194 | AK7: 1.8543919 | AL7: 0.38064545 | AM7: 1.6240323 | AN7: 0.13602051 | AO7: -1.0812834 | AP7: -1.1196466 | AQ7: 1.9052497
A8: 134 | B8: 2025 | C8: Germany | D8: 22 | E8: 21.285506 | F8: 0.71449383 | G8: 1.4103441 | H8: 1.9312788 | I8: -1.183669 | J8: 0.29436445 | K8: 0.30213082 | L8: 1.2672908 | M8: 0.64163881 | N8: -0.17701401 | O8: 0.87610525 | P8: -1.5764098 | Q8: 1.9052497 | R8: 1.4103441 | S8: 9.2569805 | T8: 0.15551987 | U8: 9.1014606 | V8: 1.9312788 | W8: 4.6758099 | X8: 0.084774447 | Y8: 4.5910354 | Z8: -1.183669 | AA8: -0.29436445 | AB8: -0.3610543 | AC8: -0.24320733 | AD8: 1.4754885 | AE8: 0.67269141 | AF8: 1.0614513 | AG8: 1.3358428 | AH8: 1.4978565 | AI8: 1.5604146 | AJ8: -0.18840575 | AK8: 1.5277708 | AL8: 0.58555133 | AM8: 0.17701401 | AN8: 0.87610525 | AO8: -1.6269339 | AP8: -1.5258857 | AQ8: 1.9052497
A9: 136 | B9: 2025 | C9: Italy | D9: 14.333333 | E9: 16.48874 | F9: -2.1554067 | G9: 1.1604992 | H9: 1.577122 | I9: -0.98348832 | J9: 0.34765214 | K9: 0.30213082 | L9: 0.54432528 | M9: 0.27018495 | N9: -2.188904 | O9: 0.35605199 | P9: -0.86426135 | Q9: 1.9052497 | R9: 1.1604992 | S9: 9.2569805 | T9: 0.15551987 | U9: 9.1014606 | V9: 1.577122 | W9: 4.6758099 | X9: 0.084774447 | Y9: 4.5910354 | Z9: -0.98348832 | AA9: -0.34765214 | AB9: -0.3610543 | AC9: -0.24320733 | AD9: 1.0898518 | AE9: 0.66830479 | AF9: 0.41802366 | AG9: 0.4125634 | AH9: 0.25050446 | AI9: 0.42670358 | AJ9: -0.63886045 | AK9: 1.4830553 | AL9: -0.033640041 | AM9: 2.188904 | AN9: 0.35605199 | AO9: -0.94007686 | AP9: -0.78844584 | AQ9: 1.9052497
A10: 137 | B10: 2025 | C10: Luxembourg | D10: 22 | E10: 21.03868 | F10: 0.96131969 | G10: 2.0925923 | H10: -0.10863984 | I10: -0.72043742 | J10: 0.37642329 | K10: 0.30213082 | L10: 1.6981916 | M10: 0.8932282 | N10: 0.85926938 | O10: 1.370452 | P10: -1.539743 | Q10: 1.9052497 | R10: 2.0925923 | S10: 9.2569805 | T10: 0.15551987 | U10: 9.1014606 | V10: -0.10863984 | W10: 4.6758099 | X10: 0.084774447 | Y10: 4.5910354 | Z10: -0.72043742 | AA10: -0.37642329 | AB10: -0.3610543 | AC10: -0.24320733 | AD10: 1.6664665 | AE10: 1.2311991 | AF10: 1.8778576 | AG10: 1.8720047 | AH10: 1.7140783 | AI10: 1.8275432 | AJ10: 0.37624768 | AK10: 1.496338 | AL10: 0.80709891 | AM10: -0.85926938 | AN10: 1.370452 | AO10: -2.4445641 | AP10: -0.63492191 | AQ10: 1.9052497
A11: 138 | B11: 2025 | C11: Netherlands | D11: 22 | E11: 21.516545 | F11: 0.48345544 | G11: 1.5624155 | H11: 1.234991 | I11: -0.7655381 | J11: 0.22810303 | K11: 0.30213082 | L11: 1.4952929 | M11: 0.64221539 | N11: 0.38930236 | O11: 1.3362111 | P11: -2.0211073 | Q11: 1.9052497 | R11: 1.5624155 | S11: 9.2569805 | T11: 0.15551987 | U11: 9.1014606 | V11: 1.234991 | W11: 4.6758099 | X11: 0.084774447 | Y11: 4.5910354 | Z11: -0.7655381 | AA11: -0.22810303 | AB11: -0.3610543 | AC11: -0.24320733 | AD11: 1.5812798 | AE11: 0.75795176 | AF11: 1.5544735 | AG11: 1.7151645 | AH11: 1.5959556 | AI11: 1.7669324 | AJ11: 0.14860203 | AK11: 1.1398516 | AL11: 0.63819256 | AM11: -0.38930236 | AN11: 1.3362111 | AO11: -1.860044 | AP11: -2.1821705 | AQ11: 1.9052497
A12: 142 | B12: 2025 | C12: Norway | D12: 22 | E12: 23.834111 | F12: -1.8341108 | G12: 1.7357668 | H12: 0.74560497 | I12: -0.74440671 | J12: 0.31888098 | K12: 0.30213082 | L12: 1.6551482 | M12: 2.4858293 | N12: 0.42589178 | O12: 2.1992683 | P12: 0.48740378 | Q12: 1.9052497 | R12: 1.7357668 | S12: 9.2569805 | T12: 0.15551987 | U12: 9.1014606 | V12: 0.74560497 | W12: 4.6758099 | X12: 0.084774447 | Y12: 4.5910354 | Z12: -0.74440671 | AA12: -0.31888098 | AB12: -0.3610543 | AC12: -0.24320733 | AD12: 1.827689 | AE12: 1.0384835 | AF12: 1.7498419 | AG12: 1.4954666 | AH12: 1.801702 | AI12: 2.0177062 | AJ12: 3.5203338 | AK12: 2.6624058 | AL12: 1.2747482 | AM12: -0.42589178 | AN12: 2.1992683 | AO12: 0.37985595 | AP12: 0.5949516 | AQ12: 1.9052497
A13: 144 | B13: 2025 | C13: Sweden | D13: 22 | E13: 21.825526 | F13: 0.17447415 | G13: 1.4366998 | H13: 0.87478823 | I13: -0.83526296 | J13: 0.3390475 | K13: 0.30213082 | L13: 1.5208156 | M13: 0.90008031 | N13: 0.66362574 | O13: 0.9077212 | P13: -0.21808277 | Q13: 1.9052497 | R13: 1.4366998 | S13: 9.2569805 | T13: 0.15551987 | U13: 9.1014606 | V13: 0.87478823 | W13: 4.6758099 | X13: 0.084774447 | Y13: 4.5910354 | Z13: -0.83526296 | AA13: -0.3390475 | AB13: -0.3610543 | AC13: -0.24320733 | AD13: 1.6019835 | AE13: 0.87764249 | AF13: 1.5274215 | AG13: 1.6323146 | AH13: 1.5546071 | AI13: 1.9309243 | AJ13: 0.41148213 | AK13: 1.5059906 | AL13: 0.78276819 | AM13: -0.66362574 | AN13: 0.9077212 | AO13: -0.21279922 | AP13: -0.22336632 | AQ13: 1.9052497
... A79: 582 | B79: 2025 | C79: Vietnam | D79: 11.666667 | E79: 13.097197 | F79: -1.4305304 | G79: -0.52050785 | H79: 0.71185819 | I79: 0.99098701 | J79: 0.32426127 | K79: 0.30213082 | L79: -0.55113204 | M79: -0.14379026 | N79: 0.72246886 | O79: 0.53892019 | P79: 0.15390513 | Q79: -0.52486557 | R79: -0.52050785 | S79: 9.2569805 | T79: 0.15551987 | U79: 9.1014606 | V79: 0.71185819 | W79: 4.6758099 | X79: 0.084774447 | Y79: 4.5910354 | Z79: 0.99098701 | AA79: -0.32426127 | AB79: -0.3610543 | AC79: -0.24320733 | AD79: -1.5386896 | AE79: -0.072805955 | AF79: -0.12479766 | AG79: -0.7534169 | AH79: -0.26078406 | AI79: -0.55629806 | AJ79: 0.1601046 | AK79: -0.90476843 | AL79: 0.31329305 | AM79: -0.72246886 | AN79: 0.53892019 | AO79: 0.4196259 | AP79: -0.11181563 | AQ79: -0.52486557
A80: 612 | B80: 2025 | C80: Algeria | E80: 10.217685 | G80: -0.32979716 | H80: 0.4401473 | I80: -0.33736546 | J80: -0.087025063 | K80: 0.30213082 | L80: -1.0017507 | M80: -0.60012296 | N80: 0.11117279 | O80: -0.078903292 | P80: 0.72729805 | Q80: -0.52486557 | R80: -0.32979716 | S80: 9.2569805 | T80: 0.15551987 | U80: 9.1014606 | V80: 0.4401473 | W80: 4.6758099 | X80: 0.084774447 | Y80: 4.5910354 | Z80: -0.33736546 | AA80: 0.087025063 | AB80: -0.3610543 | AC80: -0.24320733 | AD80: -1.2465867 | AE80: -0.72039856 | AF80: -1.0171611 | AG80: -1.3956453 | AH80: -0.89785661 | AI80: -0.73285598 | AJ80: -1.7086497 | AK80: -0.4390508 | AL80: 0.34733157 | AM80: -0.11117279 | AN80: -0.078903292 | AO80: 0.5034776 | AP80: 0.9511185 | AQ80: -0.52486557
A81: 614 | B81: 2025 | C81: Angola | D81: 7 | E81: 8.1893718 | F81: -1.1893718 | G81: -0.88732718 | H81: -0.038275151 | I81: -0.50886155 | J81: -2.4888632 | K81: 0.30213082 | L81: -1.0162937 | M81: -0.97235922 | N81: -0.11992118 | O81: 0.61929841 | P81: 0.36650141 | Q81: -0.52486557 | R81: -0.88732718 | S81: 9.2569805 | T81: 0.15551987 | U81: 9.1014606 | V81: -0.038275151 | W81: 4.6758099 | X81: 0.084774447 | Y81: 4.5910354 | Z81: -0.50886155 | AA81: 2.4888632 | AB81: -0.3610543 | AC81: -0.24320733 | AD81: -0.97604617 | AE81: -0.43770824 | AF81: -1.3966611 | AG81: -1.1836067 | AH81: -1.3499081 | AI81: -0.75383199 | AJ81: 0.26911589 | AK81: -1.1419585 | AL81: -2.044235 | AM81: 0.11992118 | AN81: 0.61929841 | AO81: 0.0055940286 | AP81: 0.72740879 | AQ81: -0.52486557
A82: 616 | B82: 2025 | C82: Botswana | D82: 15 | E82: 12.539766 | F82: 2.460234 | G82: -0.23064156 | H82: -0.97369839 | I82: -0.32042542 | J82: -0.096202069 | K82: 0.30213082 | L82: 0.48303371 | M82: -0.43794758 | N82: 0.53485433 | O82: -0.28900388 | P82: 0.36555389 | Q82: -0.52486557 | R82: -0.23064156 | S82: 9.2569805 | T82: 0.15551987 | U82: 9.1014606 | V82: -0.97369839 | W82: 4.6758099 | X82: 0.084774447 | Y82: 4.5910354 | Z82: -0.32042542 | AA82: 0.096202069 | AB82: -0.3610543 | AC82: -0.24320733 | AD82: 0.40804345 | AE82: 1.2125883 | AF82: 0.2161513 | AG82: 0.24606958 | AH82: 0.2505872 | AI82: 0.5647624 | AJ82: -0.99025271 | AK82: -0.4388858 | AL82: 0.11529578 | AM82: -0.53485433 | AN82: -0.28900388 | AO82: 0.40104322 | AP82: 0.33006456 | AQ82: -0.52486557
A83: 622 | B83: 2025 | C83: Cameroon | D83: 7 | E83: 7.8245569 | F83: -0.82455694 | G83: -1.1678745 | H83: -0.37360528 | I83: 0.1380472 | J83: 0.16067779 | K83: 0.30213082 | L83: -1.3809824 | M83: -0.32273956 | N83: 0.55935841 | O83: -0.27167653 | P83: 0.14554339 | Q83: -0.52486557 | R83: -1.1678745 | S83: 9.2569805 | T83: 0.15551987 | U83: 9.1014606 | V83: -0.37360528 | W83: 4.6758099 | X83: 0.084774447 | Y83: 4.5910354 | Z83: 0.1380472 | AA83: -0.16067779 | AB83: -0.3610543 | AC83: -0.24320733 | AD83: -1.3430508 | AE83: -1.7040994 | AF83: -1.2816746 | AG83: -1.3563333 | AH83: -1.2845044 | AI83: -1.3162317 | AJ83: 0.25786392 | AK83: -1.1847765 | AL83: -0.041306083 | AM83: -0.55935841 | AN83: -0.27167653 | AO83: -0.11815968 | AP83: 0.40924646 | AQ83: -0.52486557
A84: 624 | B84: 2025 | C84: Cabo Verde | D84: 8 | E84: 9.6316888 | F84: -1.6316888 | G84: -0.38473336 | H84: -1.9571969 | I84: 0.27382949 | J84: 0.41185303 | K84: 0.30213082 | L84: 0.46685882 | M84: -0.079753926 | N84: -1.3326784 | O84: -0.35696847 | P84: 0.55792718 | Q84: -0.52486557 | R84: -0.38473336 | S84: 9.2569805 | T84: 0.15551987 | U84: 9.1014606 | V84: -1.9571969 | W84: 4.6758099 | X84: 0.084774447 | Y84: 4.5910354 | Z84: 0.27382949 | AA84: -0.41185303 | AB84: -0.3610543 | AC84: -0.24320733 | AD84: 0.91431352 | AE84: 1.0509078 | AF84: -0.25114642 | AG84: -0.043008674 | AH84: 0.26097778 | AI84: 0.86910891 | AJ84: -0.0070961671 | AK84: -0.24055362 | AL84: 0.0083880083 | AM84: 1.3326784 | AN84: -0.35696847 | AO84: 0.62610884 | AP84: 0.48974553 | AQ84: -0.52486557
A85: 634 | B85: 2025 | C85: Republic of Congo | D85: 5.6666667 | E85: 4.0131544 | F85: 1.6535123 | G85: -1.033178 | H85: -1.0785242 | I85: -0.67001024 | J85: 0.26095709 | K85: -2.1230086 | L85: -1.2837854 | M85: 0.20940632 | N85: -0.97503556 | O85: 0.3896205 | P85: -0.45716384 | Q85: -0.52486557 | R85: -1.033178 | S85: 9.2569805 | T85: 0.15551987 | U85: 9.1014606 | V85: -1.0785242 | W85: 4.6758099 | X85: 0.084774447 | Y85: 4.5910354 | Z85: -0.67001024 | AA85: -0.26095709 | AB85: 2.7696665 | AC85: 1.4763507 | AD85: -1.4409165 | AE85: -0.0063812631 | AF85: -1.7611524 | AG85: -1.7265035 | AH85: -1.2655811 | AI85: -1.5021775 | AJ85: 1.5821381 | AK85: -0.35267235 | AL85: -0.6012468 | AM85: 0.97503556 | AN85: 0.3896205 | AO85: -0.5488224 | AP85: -0.36550528 | AQ85: -0.52486557
A86: 636 | B86: 2025 | C86: Democratic Republic of the Congo | D86: 7 | E86: 6.3503053 | F86: 0.6496947 | G86: -1.902952 | H86: -0.21389459 | I86: 0.97216959 | J86: -1.1209741 | K86: 0.30213082 | L86: -1.9438088 | M86: -0.19598085 | N86: 1.0829454 | O86: -0.18889317 | P86: -0.15540116 | Q86: -0.52486557 | R86: -1.902952 | S86: 9.2569805 | T86: 0.15551987 | U86: 9.1014606 | V86: -0.21389459 | W86: 4.6758099 | X86: 0.084774447 | Y86: 4.5910354 | Z86: 0.97216959 | AA86: 1.1209741 | AB86: -0.3610543 | AC86: -0.24320733 | AD86: -1.5068847 | AE86: -2.474778 | AF86: -2.1585802 | AG86: -1.918634 | AH86: -1.9641772 | AI86: -1.6397987 | AJ86: 0.19328413 | AK86: -1.2249545 | AL86: 0.44372777 | AM86: -1.0829454 | AN86: -0.18889317 | AO86: -0.027207915 | AP86: -0.2835944 | AQ86: -0.52486557
A87: 638 | B87: 2025 | C87: Benin | D87: 9.3333333 | E87: 8.0230611 | F87: 1.3102722 | G87: -1.3315409 | H87: -0.84817989 | I87: 1.3850176 | J87: 0.52457185 | K87: 0.30213082 | L87: -0.48408279 | M87: -0.63130676 | N87: 0.20304917 | O87: -0.45300596 | P87: -3.2682022 | Q87: -0.52486557 | R87: -1.3315409 | S87: 9.2569805 | T87: 0.15551987 | U87: 9.1014606 | V87: -0.84817989 | W87: 4.6758099 | X87: 0.084774447 | Y87: 4.5910354 | Z87: 1.3850176 | AA87: -0.52457185 | AB87: -0.3610543 | AC87: -0.24320733 | AD87: -0.39816813 | AE87: -0.44375239 | AF87: -0.51177616 | AG87: -0.6548678 | AH87: -0.71233695 | AI87: -0.18359532 | AJ87: -0.31388151 | AK87: -1.1414635 | AL87: -0.43857523 | AM87: -0.20304917 | AN87: -0.45300596 | AO87: -3.3459959 | AP87: -3.1904086 | AQ87: -0.52486557
A88: 644 | B88: 2025 | C88: Ethiopia | D88: 2 | E88: 7.2499237 | F88: -5.2499237 | G88: -1.7105163 | H88: -0.06464973 | I88: 1.7296252 | J88: -2.4258071 | K88: 0.30213082 | L88: -1.303829 | M88: -0.58681722 | N88: 0.31415098 | O88: -0.19543619 | P88: -0.3702058 | Q88: -0.52486557 | R88: -1.7105163 | S88: 9.2569805 | T88: 0.15551987 | U88: 9.1014606 | V88: -0.06464973 | W88: 4.6758099 | X88: 0.084774447 | Y88: 4.5910354 | Z88: 1.7296252 | AA88: 2.4258071 | AB88: -0.3610543 | AC88: -0.24320733 | AD88: -1.3366617 | AE88: -2.3847328 | AF88: -1.1275323 | AG88: -1.4785441 | AH88: -0.88908748 | AI88: -0.60641579 | AJ88: 0.063197321 | AK88: -1.5629607 | AL88: -0.26068832 | AM88: -0.31415098 | AN88: -0.19543619 | AO88: -0.62156966 | AP88: -0.11884193 | AQ88: -0.52486557
A89: 646 | B89: 2025 | C89: Gabon | D89: 5 | E89: 7.5767095 | F89: -2.5767095 | G89: -0.007880117 | H89: -0.9153575 | I89: -0.46913104 | J89: 0.46363347 | K89: 0.30213082 | L89: -1.0236795 | M89: -0.73077958 | N89: -0.50490185 | O89: 0.47209351 | P89: -0.13987896 | Q89: -0.52486557 | R89: -0.007880117 | S89: 9.2569805 | T89: 0.15551987 | U89: 9.1014606 | V89: -0.9153575 | W89: 4.6758099 | X89: 0.084774447 | Y89: 4.5910354 | Z89: -0.46913104 | AA89: -0.46363347 | AB89: -0.3610543 | AC89: -0.24320733 | AD89: -1.178868 | AE89: -0.43055906 | AF89: -1.1400193 | AG89: -1.119361 | AH89: -1.1066664 | AI89: -1.1666031 | AJ89: -0.52604003 | AK89: -0.74611918 | AL89: -0.92017952 | AM89: 0.50490185 | AN89: 0.47209351 | AO89: -0.24932764 | AP89: -0.030430292 | AQ89: -0.52486557
A90: 652 | B90: 2025 | C90: Ghana | D90: 6.3333333 | E90: 7.5150604 | F90: -1.181727 | G90: -0.82204363 | H90: -0.053001596 | I90: 0.43026291 | J90: -2.3223416 | K90: -3.1881897 | L90: -0.19263825 | M90: -1.2840549 | N90: -0.028656012 | O90: 0.15920553 | P90: 0.23470718 | Q90: -0.52486557 | R90: -0.82204363 | S90: 9.2569805 | T90: 0.15551987 | U90: 9.1014606 | V90: -0.053001596 | W90: 4.6758099 | X90: 0.084774447 | Y90: 4.5910354 | Z90: 0.43026291 | AA90: 2.3223416 | AB90: 2.7696665 | AC90: 3.6067129 | AD90: 0.30356011 | AE90: -0.055154253 | AF90: -0.37026869 | AG90: -0.5240505 | AH90: -0.27600566 | AI90: -0.23391047 | AJ90: -0.93116108 | AK90: -1.094273 | AL90: -1.8267305 | AM90: 0.028656012 | AN90: 0.15920553 | AO90: 0.087505706 | AP90: 0.38190865 | AQ90: -0.52486557
A91: 662 | B91: 2025 | C91: Côte d'Ivoire | D91: 10.666667 | E91: 10.110202 | F91: 0.55646459 | G91: -0.86557048 | H91: -0.11613547 | I91: 1.1956646 | J91: 0.36365943 | K91: 0.30213082 | L91: -0.59893669 | M91: -0.73889194 | N91: 0.06816564 | O91: -0.30139164 | P91: 0.12315108 | Q91: -0.52486557 | R91: -0.86557048 | S91: 9.2569805 | T91: 0.15551987 | U91: 9.1014606 | V91: -0.11613547 | W91: 4.6758099 | X91: 0.084774447 | Y91: 4.5910354 | Z91: 1.1956646 | AA91: -0.36365943 | AB91: -0.3610543 | AC91: -0.24320733 | AD91: -0.57266274 | AE91: -0.78486195 | AF91: -0.66919737 | AG91: -0.45071563 | AH91: -0.66450697 | AI91: -0.45167548 | AJ91: -0.4026192 | AK91: -0.98875435 | AL91: -0.82530225 | AM91: -0.06816564 | AN91: -0.30139164 | AO91: -0.11635765 | AP91: 0.36265981 | AQ91: -0.52486557
A92: 664 | B92: 2025 | C92: Kenya | D92: 7 | E92: 9.0162171 | F92: -2.0162171 | G92: -0.9934789 | H92: 0.048562497 | I92: 0.66436729 | J92: -0.15700689 | K92: 0.30213082 | L92: -0.70827988 | M92: -1.4208303 | N92: -0.27697507 | O92: -0.25956031 | P92: 0.067726998 | Q92: -0.52486557 | R92: -0.9934789 | S92: 9.2569805 | T92: 0.15551987 | U92: 9.1014606 | V92: 0.048562497 | W92: 4.6758099 | X92: 0.084774447 | Y92: 4.5910354 | Z92: 0.66436729 | AA92: 0.15700689 | AB92: -0.3610543 | AC92: -0.24320733 | AD92: -0.292446 | AE92: -1.1507927 | AF92: -0.60656965 | AG92: -0.7627287 | AH92: -0.51947403 | AI92: -0.91766814 | AJ92: -0.85650714 | AK92: -1.004842 | AL92: -2.4011418 | AM92: 0.27697507 | AN92: -0.25956031 | AO92: -0.11300316 | AP92: 0.24845715 | AQ92: -0.52486557
... A139: 968 | B139: 2025 | C139: Romania | D139: 13 | E139: 13.731877 | F139: -0.73187723 | G139: 0.66236237 | H139: 0.64015639 | I139: -0.52117364 | J139: -0.28325273 | K139: 0.30213082 | L139: 0.11779894 | M139: -0.31114476 | N139: -0.087721386 | O139: -0.68979583 | P139: 0.22631071 | Q139: -0.52486557 | R139: 0.66236237 | S139: 9.2569805 | T139: 0.15551987 | U139: 9.1014606 | V139: 0.64015639 | W139: 4.6758099 | X139: 0.084774447 | Y139: 4.5910354 | Z139: -0.52117364 | AA139: 0.28325273 | AB139: -0.3610543 | AC139: -0.24320733 | AD139: 0.40706558 | AE139: 0.41754898 | AF139: -0.37027317 | AG139: 0.043304124 | AH139: 0.30107876 | AI139: -0.091930606 | AJ139: -1.0522263 | AK139: 0.23135157 | AL139: -0.11255961 | AM139: 0.087721386 | AN139: -0.68979583 | AO139: 0.21494209 | AP139: 0.23767934 | AQ139: -0.52486557

Sheet 2025_dec_transform
A1: cc | B1: year | C1: name | D1: rating | E1: predicted_rating | F1: resid | G1: wealth_factor | H1: size_factor | I1: growth_factor | J1: inflation_factor | K1: default_factor | L1: governance_factor | M1: fiscalperf_factor | N1: govdebt_factor | O1: extperf_factor | P1: reservebuffer_factor | Q1: reservestatus_factor | R1: ngdp_pc | S1: median_ngdp_pc | T1: detrend_median_ngdp_pc | U1: trend_median_ngdp_pc | V1: ngdp | W1: median_ngdp | X1: detrend_median_ngdp | Y1: trend_median_ngdp | Z1: growth_avg | AA1: inf_avg | AB1: default_hist | AC1: default_decay | AD1: voice_acct | AE1: pol_stab | AF1: gov_eff | AG1: reg_qual | AH1: rule_law | AI1: cont_corrupt | AJ1: fb_avg | AK1: gov_rev_gdp | AL1: ir_rev | AM1: gov_debt_gdp | AN1: cab_avg | AO1: reserve_gdp | AP1: import_cover | AQ1: reserve_fx
A2: 111 | B2: 2025 | C2: United States | D2: 21 | E2: 18.705977 | F2: 2.294023 | G2: 1.7165951 | H2: 2.87566 | I2: -0.42158541 | J2: 0.256588 | K2: 0.30213082 | L2: 0.82855756 | M2: -0.59856353 | N2: -1.8614329 | O2: -0.26667229 | P2: -2.4190325 | Q2: 1.9052497 | R2: 1.7165951 | S2: 9.2569805 | T2: 0.15551987 | U2: 9.1014606 | V2: 2.87566 | W2: 4.6758099 | X2: 0.084774447 | Y2: 4.5910354 | Z2: -0.42158541 | AA2: -0.256588 | AB2: -0.3610543 | AC2: -0.24320733 | AD2: 0.81618166 | AE2: -0.15540861 | AF2: 1.1963812 | AG2: 1.2381495 | AH2: 0.9108459 | AI2: 0.96519575 | AJ2: -1.4785982 | AK2: 0.083757451 | AL2: -0.4008498 | AM2: 1.8614329 | AN2: -0.26667229 | AO2: -2.7395727 | AP2: -2.0984922 | AQ2: 1.9052497
A3: 112 | B3: 2025 | C3: United Kingdom | D3: 19.333333 | E3: 19.153396 | F3: 0.17993686 | G3: 1.3676964 | H3: 1.8079895 | I3: -0.89625584 | J3: 0.23216686 | K3: 0.30213082 | L3: 1.0991731 | M3: 0.081403246 | N3: -1.2588605 | O3: -0.12581645 | P3: -0.60432103 | Q3: 1.9052497 | R3: 1.3676964 | S3: 9.2569805 | T3: 0.15551987 | U3: 9.1014606 | V3: 1.8079895 | W3: 4.6758099 | X3: 0.084774447 | Y3: 4.5910354 | Z3: -0.89625584 | AA3: -0.23216686 | AB3: -0.3610543 | AC3: -0.24320733 | AD3: 1.2675474 | AE3: 0.26915693 | AF3: 0.99717107 | AG3: 1.4217018 | AH3: 1.2429962 | AI3: 1.3964651 | AJ3: -0.70990574 | AK3: 0.82082056 | AL3: 0.13329492 | AM3: 1.2588605 | AN3: -0.12581645 | AO3: -0.72087482 | AP3: -0.48776724 | AQ3: 1.9052497
A4: 122 | B4: 2025 | C4: Austria | D4: 20.666667 | E4: 18.723972 | F4: 1.9426946 | G4: 1.4324905 | H4: 0.79318469 | I4: -1.110102 | J4: 0.2170372 | K4: 0.30213082 | L4: 1.2334629 | M4: 0.64367319 | N4: -0.66609531 | O4: 0.44703351 | P4: -1.548332 | Q4: 1.9052497 | R4: 1.4324905 | S4: 9.2569805 | T4: 0.15551987 | U4: 9.1014606 | V4: 0.79318469 | W4: 4.6758099 | X4: 0.084774447 | Y4: 4.5910354 | Z4: -1.110102 | AA4: -0.2170372 | AB4: -0.3610543 | AC4: -0.24320733 | AD4: 1.3819502 | AE4: 0.5506054 | AF4: 1.3722223 | AG4: 1.2364995 | AH4: 1.6826228 | AI4: 1.1768774 | AJ4: -0.46005688 | AK4: 1.8538969 | AL4: 0.53717951 | AM4: 0.66609531 | AN4: 0.44703351 | AO4: -1.4399274 | AP4: -1.6567365 | AQ4: 1.9052497
A5: 124 | B5: 2025 | C5: Belgium | D5: 19 | E5: 17.541837 | F5: 1.4581632 | G5: 1.4165765 | H5: 0.91617924 | I5: -0.80622913 | J5: 0.31042898 | K5: 0.30213082 | L5: 1.0532288 | M5: 0.44382636 | N5: -1.3739074 | O5: 0.14883499 | P5: -1.6896021 | Q5: 1.9052497 | R5: 1.4165765 | S5: 9.2569805 | T5: 0.15551987 | U5: 9.1014606 | V5: 0.91617924 | W5: 4.6758099 | X5: 0.084774447 | Y5: 4.5910354 | Z5: -0.80622913 | AA5: -0.31042898 | AB5: -0.3610543 | AC5: -0.24320733 | AD5: 1.482072 | AE5: 0.10519436 | AF5: 1.0083566 | AG5: 1.1121873 | AH5: 1.2568859 | AI5: 1.3546767 | AJ5: -0.75626687 | AK5: 1.676025 | AL5: 0.41172098 | AM5: 1.3739074 | AN5: 0.14883499 | AO5: -1.5146285 | AP5: -1.8645758 | AQ5: 1.9052497
A6: 128 | B6: 2025 | C6: Denmark | D6: 22 | E6: 23.251883 | F6: -1.2518833 | G6: 1.5970641 | H6: 0.68409036 | I6: -0.61622124 | J6: 0.39882206 | K6: 0.30213082 | L6: 1.7928139 | M6: 1.2528402 | N6: 0.78959113 | O6: 1.5943498 | P6: 0.59010082 | Q6: 1.9052497 | R6: 1.5970641 | S6: 9.2569805 | T6: 0.15551987 | U6: 9.1014606 | V6: 0.68409036 | W6: 4.6758099 | X6: 0.084774447 | Y6: 4.5910354 | Z6: -0.61622124 | AA6: -0.39882206 | AB6: -0.3610543 | AC6: -0.24320733 | AD6: 1.9160566 | AE6: 0.88426567 | AF6: 1.825546 | AG6: 1.9067083 | AH6: 2.0346627 | AI6: 2.1896441 | AJ6: 1.0603374 | AK6: 1.7624859 | AL6: 0.93569733 | AM6: -0.78959113 | AN6: 1.5943498 | AO6: 0.61125154 | AP6: 0.5689501 | AQ6: 1.9052497
A7: 132 | B7: 2025 | C7: France | D7: 18.666667 | E7: 17.913243 | F7: 0.75342344 | G7: 1.2568188 | H7: 1.7226357 | I7: -0.96632998 | J7: 0.40021483 | K7: 0.30213082 | L7: 0.80220623 | M7: 0.44103213 | N7: -1.6240323 | O7: 0.13602051 | P7: -1.3696265 | Q7: 1.9052497 | R7: 1.2568188 | S7: 9.2569805 | T7: 0.15551987 | U7: 9.1014606 | V7: 1.7226357 | W7: 4.6758099 | X7: 0.084774447 | Y7: 4.5910354 | Z7: -0.96632998 | AA7: -0.40021483 | AB7: -0.3610543 | AC7: -0.24320733 | AD7: 1.1017518 | AE7: -0.33139979 | AF7: 1.0151396 | AG7: 0.99957514 | AH7: 0.92903136 | AI7: 1.0991393 | AJ7: -0.91194 | AK7: 1.8543919 | AL7: 0.38064446 | AM7: 1.6240323 | AN7: 0.13602051 | AO7: -1.4362936 | AP7: -1.3029594 | AQ7: 1.9052497
A8: 134 | B8: 2025 | C8: Germany | D8: 22 | E8: 21.331576 | F8: 0.6684243 | G8: 1.4103441 | H8: 1.9312788 | I8: -1.183669 | J8: 0.29436445 | K8: 0.30213082 | L8: 1.3012734 | M8: 0.64163853 | N8: -0.17701401 | O8: 0.87610525 | P8: -1.577591 | Q8: 1.9052497 | R8: 1.4103441 | S8: 9.2569805 | T8: 0.15551987 | U8: 9.1014606 | V8: 1.9312788 | W8: 4.6758099 | X8: 0.084774447 | Y8: 4.5910354 | Z8: -1.183669 | AA8: -0.29436445 | AB8: -0.3610543 | AC8: -0.24320733 | AD8: 1.5922117 | AE8: 0.10858056 | AF8: 1.4083937 | AG8: 1.4064671 | AH8: 1.6266154 | AI8: 1.6653721 | AJ8: -0.18840575 | AK8: 1.5277708 | AL8: 0.58555049 | AM8: 0.17701401 | AN8: 0.87610525 | AO8: -1.6273499 | AP8: -1.5278321 | AQ8: 1.9052497
A9: 136 | B9: 2025 | C9: Italy | D9: 14.333333 | E9: 16.575605 | F9: -2.2422721 | G9: 1.1604992 | H9: 1.577122 | I9: -0.98348832 | J9: 0.34765214 | K9: 0.30213082 | L9: 0.54514429 | M9: 0.27018451 | N9: -2.188904 | O9: 0.35605199 | P9: -0.86851649 | Q9: 1.9052497 | R9: 1.1604992 | S9: 9.2569805 | T9: 0.15551987 | U9: 9.1014606 | V9: 1.577122 | W9: 4.6758099 | X9: 0.084774447 | Y9: 4.5910354 | Z9: -0.98348832 | AA9: -0.34765214 | AB9: -0.3610543 | AC9: -0.24320733 | AD9: 1.0130186 | AE9: 0.33052136 | AF9: 0.55040968 | AG9: 0.41451204 | AH9: 0.54154645 | AI9: 0.42085766 | AJ9: -0.63886045 | AK9: 1.4830553 | AL9: -0.033641367 | AM9: 2.188904 | AN9: 0.35605199 | AO9: -0.94360281 | AP9: -0.79343017 | AQ9: 1.9052497
A10: 137 | B10: 2025 | C10: Luxembourg | D10: 22 | E10: 21.06722 | F10: 0.93277977 | G10: 2.0925923 | H10: -0.10863984 | I10: -0.72043742 | J10: 0.37642329 | K10: 0.30213082 | L10: 1.7286095 | M10: 0.89322797 | N10: 0.85926938 | O10: 1.370452 | P10: -1.5490968 | Q10: 1.9052497 | R10: 2.0925923 | S10: 9.2569805 | T10: 0.15551987 | U10: 9.1014606 | V10: -0.10863984 | W10: 4.6758099 | X10: 0.084774447 | Y10: 4.5910354 | Z10: -0.72043742 | AA10: -0.37642329 | AB10: -0.3610543 | AC10: -0.24320733 | AD10: 1.6655116 | AE10: 1.2502946 | AF10: 1.9698481 | AG10: 1.8002716 | AH10: 1.7732029 | AI10: 1.9125281 | AJ10: 0.37624768 | AK10: 1.496338 | AL10: 0.80709825 | AM10: -0.85926938 | AN10: 1.370452 | AO10: -2.4449681 | AP10: -0.65322547 | AQ10: 1.9052497
A11: 138 | B11: 2025 | C11: Netherlands | D11: 22 | E11: 21.4562 | F11: 0.54379968 | G11: 1.5624155 | H11: 1.234991 | I11: -0.7655381 | J11: 0.22810303 | K11: 0.30213082 | L11: 1.4922354 | M11: 0.64221512 | N11: 0.38930236 | O11: 1.3362111 | P11: -1.9971327 | Q11: 1.9052497 | R11: 1.5624155 | S11: 9.2569805 | T11: 0.15551987 | U11: 9.1014606 | V11: 1.234991 | W11: 4.6758099 | X11: 0.084774447 | Y11: 4.5910354 | Z11: -0.7655381 | AA11: -0.22810303 | AB11: -0.3610543 | AC11: -0.24320733 | AD11: 1.6527832 | AE11: 0.47421965 | AF11: 1.6424564 | AG11: 1.6651936 | AH11: 1.7140803 | AI11: 1.8046792 | AJ11: 0.14860203 | AK11: 1.1398516 | AL11: 0.63819176 | AM11: -0.38930236 | AN11: 1.3362111 | AO11: -1.8433318 | AP11: -2.1509336 | AQ11: 1.9052497
A12: 142 | B12: 2025 | C12: Norway | D12: 22 | E12: 23.741085 | F12: -1.7410851 | G12: 1.7357668 | H12: 0.74560497 | I12: -0.74440671 | J12: 0.31888098 | K12: 0.30213082 | L12: 1.6972911 | M12: 2.4858292 | N12: 0.42589178 | O12: 2.1992683 | P12: 0.43941714 | Q12: 1.9052497 | R12: 1.7357668 | S12: 9.2569805 | T12: 0.15551987 | U12: 9.1014606 | V12: 0.74560497 | W12: 4.6758099 | X12: 0.084774447 | Y12: 4.5910354 | Z12: -0.74440671 | AA12: -0.31888098 | AB12: -0.3610543 | AC12: -0.24320733 | AD12: 1.9536842 | AE12: 1.0459816 | AF12: 1.7460731 | AG12: 1.605794 | AH12: 1.975525 | AI12: 1.8566888 | AJ12: 3.5203338 | AK12: 2.6624058 | AL12: 1.274748 | AM12: -0.42589178 | AN12: 2.1992683 | AO12: 0.29566164 | AP12: 0.58317265 | AQ12: 1.9052497
A13: 144 | B13: 2025 | C13: Sweden | D13: 22 | E13: 21.812877 | F13: 0.18712298 | G13: 1.4366998 | H13: 0.87478823 | I13: -0.83526296 | J13: 0.3390475 | K13: 0.30213082 | L13: 1.5488989 | M13: 0.90008008 | N13: 0.66362574 | O13: 0.9077212 | P13: -0.222662 | Q13: 1.9052497 | R13: 1.4366998 | S13: 9.2569805 | T13: 0.15551987 | U13: 9.1014606 | V13: 0.87478823 | W13: 4.6758099 | X13: 0.084774447 | Y13: 4.5910354 | Z13: -0.83526296 | AA13: -0.3390475 | AB13: -0.3610543 | AC13: -0.24320733 | AD13: 1.7336721 | AE13: 0.68527622 | AF13: 1.6682843 | AG13: 1.6073434 | AH13: 1.7354015 | AI13: 1.8634159 | AJ13: 0.41148213 | AK13: 1.5059906 | AL13: 0.78276751 | AM13: -0.66362574 | AN13: 0.9077212 | AO13: -0.22632287 | AP13: -0.21900113 | AQ13: 1.9052497
... A79: 582 | B79: 2025 | C79: Vietnam | D79: 11.666667 | E79: 13.07901 | F79: -1.4123433 | G79: -0.52050785 | H79: 0.71185819 | I79: 0.99098701 | J79: 0.32426127 | K79: 0.30213082 | L79: -0.5564751 | M79: -0.14379061 | N79: 0.72246886 | O79: 0.53892019 | P79: 0.15462753 | Q79: -0.52486557 | R79: -0.52050785 | S79: 9.2569805 | T79: 0.15551987 | U79: 9.1014606 | V79: 0.71185819 | W79: 4.6758099 | X79: 0.084774447 | Y79: 4.5910354 | Z79: 0.99098701 | AA79: -0.32426127 | AB79: -0.3610543 | AC79: -0.24320733 | AD79: -1.350064 | AE79: -0.03412738 | AF79: -0.45615612 | AG79: -0.63414747 | AH79: -0.46435385 | AI79: -0.40000179 | AJ79: 0.1601046 | AK79: -0.90476843 | AL79: 0.31329199 | AM79: -0.72246886 | AN79: 0.53892019 | AO79: 0.4203834 | AP79: -0.11112834 | AQ79: -0.52486557
A80: 612 | B80: 2025 | C80: Algeria | E80: 10.4754 | G80: -0.32979716 | H80: 0.4401473 | I80: -0.33736546 | J80: -0.087025063 | K80: 0.30213082 | L80: -0.93826462 | M80: -0.6001233 | N80: 0.11117279 | O80: -0.078903292 | P80: 0.69343961 | Q80: -0.52486557 | R80: -0.32979716 | S80: 9.2569805 | T80: 0.15551987 | U80: 9.1014606 | V80: 0.4401473 | W80: 4.6758099 | X80: 0.084774447 | Y80: 4.5910354 | Z80: -0.33736546 | AA80: 0.087025063 | AB80: -0.3610543 | AC80: -0.24320733 | AD80: -1.2956118 | AE80: -0.87557874 | AF80: -0.63696077 | AG80: -1.1958973 | AH80: -0.87704938 | AI80: -0.74848978 | AJ80: -1.7086497 | AK80: -0.4390508 | AL80: 0.34733054 | AM80: -0.11117279 | AN80: -0.078903292 | AO80: 0.48203246 | AP80: 0.90484676 | AQ80: -0.52486557
A81: 614 | B81: 2025 | C81: Angola | D81: 7 | E81: 7.9745947 | F81: -0.97459467 | G81: -0.88732718 | H81: -0.038275151 | I81: -0.50886155 | J81: -2.4888632 | K81: 0.30213082 | L81: -1.1112399 | M81: -0.97236019 | N81: -0.11992118 | O81: 0.61929841 | P81: 0.34318514 | Q81: -0.52486557 | R81: -0.88732718 | S81: 9.2569805 | T81: 0.15551987 | U81: 9.1014606 | V81: -0.038275151 | W81: 4.6758099 | X81: 0.084774447 | Y81: 4.5910354 | Z81: -0.50886155 | AA81: 2.4888632 | AB81: -0.3610543 | AC81: -0.24320733 | AD81: -1.3070548 | AE81: -0.73118732 | AF81: -1.2445966 | AG81: -1.2194534 | AH81: -1.3868932 | AI81: -0.77825387 | AJ81: 0.26911589 | AK81: -1.1419585 | AL81: -2.0442379 | AM81: 0.11992118 | AN81: 0.61929841 | AO81: 0.016162669 | AP81: 0.67020761 | AQ81: -0.52486557
A82: 616 | B82: 2025 | C82: Botswana | D82: 15 | E82: 12.282028 | F82: 2.717972 | G82: -0.23064156 | H82: -0.97369839 | I82: -0.32042542 | J82: -0.096202069 | K82: 0.30213082 | L82: 0.39083092 | M82: -0.43794798 | N82: 0.53485433 | O82: -0.28900388 | P82: 0.36627432 | Q82: -0.52486557 | R82: -0.23064156 | S82: 9.2569805 | T82: 0.15551987 | U82: 9.1014606 | V82: -0.97369839 | W82: 4.6758099 | X82: 0.084774447 | Y82: 4.5910354 | Z82: -0.32042542 | AA82: 0.096202069 | AB82: -0.3610543 | AC82: -0.24320733 | AD82: 0.17055094 | AE82: 1.2012476 | AF82: 0.12324398 | AG82: 0.13907784 | AH82: 0.21047848 | AI82: 0.50038667 | AJ82: -0.99025271 | AK82: -0.4388858 | AL82: 0.11529457 | AM82: -0.53485433 | AN82: -0.28900388 | AO82: 0.40179319 | AP82: 0.33075545 | AQ82: -0.52486557
A83: 622 | B83: 2025 | C83: Cameroon | D83: 7 | E83: 7.7166527 | F83: -0.71665266 | G83: -1.1678745 | H83: -0.37360528 | I83: 0.1380472 | J83: 0.16067779 | K83: 0.30213082 | L83: -1.4534646 | M83: -0.32274 | N83: 0.55935841 | O83: -0.27167653 | P83: 0.14859183 | Q83: -0.52486557 | R83: -1.1678745 | S83: 9.2569805 | T83: 0.15551987 | U83: 9.1014606 | V83: -0.37360528 | W83: 4.6758099 | X83: 0.084774447 | Y83: 4.5910354 | Z83: 0.1380472 | AA83: -0.16067779 | AB83: -0.3610543 | AC83: -0.24320733 | AD83: -1.5065999 | AE83: -1.9143228 | AF83: -1.2623455 | AG83: -1.1681764 | AH83: -1.4774227 | AI83: -1.3919202 | AJ83: 0.25786392 | AK83: -1.1847765 | AL83: -0.041307415 | AM83: -0.55935841 | AN83: -0.27167653 | AO83: -0.11685492 | AP83: 0.41403858 | AQ83: -0.52486557
A84: 624 | B84: 2025 | C84: Cabo Verde | D84: 8 | E84: 9.5974388 | F84: -1.5974388 | G84: -0.38473336 | H84: -1.9571969 | I84: 0.27382949 | J84: 0.41185303 | K84: 0.30213082 | L84: 0.43200757 | M84: -0.079754357 | N84: -1.3326784 | O84: -0.35696847 | P84: 0.56383554 | Q84: -0.52486557 | R84: -0.38473336 | S84: 9.2569805 | T84: 0.15551987 | U84: 9.1014606 | V84: -1.9571969 | W84: 4.6758099 | X84: 0.084774447 | Y84: 4.5910354 | Z84: 0.27382949 | AA84: -0.41185303 | AB84: -0.3610543 | AC84: -0.24320733 | AD84: 0.71156542 | AE84: 0.88511643 | AF84: 0.12131638 | AG84: -0.27345892 | AH84: 0.33133791 | AI84: 0.81616822 | AJ84: -0.0070961671 | AK84: -0.24055362 | AL84: 0.0083867153 | AM84: 1.3326784 | AN84: -0.35696847 | AO84: 0.62927404 | AP84: 0.49839704 | AQ84: -0.52486557
A85: 634 | B85: 2025 | C85: Republic of Congo | D85: 5.6666667 | E85: 3.7726127 | F85: 1.894054 | G85: -1.033178 | H85: -1.0785242 | I85: -0.67001024 | J85: 0.26095709 | K85: -2.1230086 | L85: -1.3669688 | M85: 0.20940572 | N85: -0.97503556 | O85: 0.3896205 | P85: -0.45626619 | Q85: -0.52486557 | R85: -1.033178 | S85: 9.2569805 | T85: 0.15551987 | U85: 9.1014606 | V85: -1.0785242 | W85: 4.6758099 | X85: 0.084774447 | Y85: 4.5910354 | Z85: -0.67001024 | AA85: -0.26095709 | AB85: 2.7696665 | AC85: 1.4763507 | AD85: -1.58627 | AE85: -0.35191678 | AF85: -1.614921 | AG85: -1.6571396 | AH85: -1.3963999 | AI85: -1.5951654 | AJ85: 1.5821381 | AK85: -0.35267235 | AL85: -0.60124857 | AM85: 0.97503556 | AN85: 0.3896205 | AO85: -0.54771231 | AP85: -0.36482006 | AQ85: -0.52486557
A86: 636 | B86: 2025 | C86: Democratic Republic of the Congo | D86: 7 | E86: 6.3491191 | F86: 0.65088086 | G86: -1.902952 | H86: -0.21389459 | I86: 0.97216959 | J86: -1.1209741 | K86: 0.30213082 | L86: -1.9540687 | M86: -0.19598117 | N86: 1.0829454 | O86: -0.18889317 | P86: -0.18666537 | Q86: -0.52486557 | R86: -1.902952 | S86: 9.2569805 | T86: 0.15551987 | U86: 9.1014606 | V86: -0.21389459 | W86: 4.6758099 | X86: 0.084774447 | Y86: 4.5910354 | Z86: 0.97216959 | AA86: 1.1209741 | AB86: -0.3610543 | AC86: -0.24320733 | AD86: -1.4758794 | AE86: -2.5910487 | AF86: -2.2780941 | AG86: -1.8112481 | AH86: -1.8793816 | AI86: -1.6887605 | AJ86: 0.19328413 | AK86: -1.2249545 | AL86: 0.44372682 | AM86: -1.0829454 | AN86: -0.18889317 | AO86: -0.090422228 | AP86: -0.28290851 | AQ86: -0.52486557
A87: 638 | B87: 2025 | C87: Benin | D87: 9.3333333 | E87: 7.9366786 | F87: 1.3966548 | G87: -1.3315409 | H87: -0.84817989 | I87: 1.3850176 | J87: 0.52457185 | K87: 0.30213082 | L87: -0.54340765 | M87: -0.6313073 | N87: 0.20304917 | O87: -0.45300596 | P87: -3.2734305 | Q87: -0.52486557 | R87: -1.3315409 | S87: 9.2569805 | T87: 0.15551987 | U87: 9.1014606 | V87: -0.84817989 | W87: 4.6758099 | X87: 0.084774447 | Y87: 4.5910354 | Z87: 1.3850176 | AA87: -0.52457185 | AB87: -0.3610543 | AC87: -0.24320733 | AD87: -0.56679085 | AE87: -0.52591402 | AF87: -0.56212143 | AG87: -0.64623713 | AH87: -0.57058298 | AI87: -0.38879946 | AJ87: -0.31388151 | AK87: -1.1414635 | AL87: -0.43857687 | AM87: -0.20304917 | AN87: -0.45300596 | AO87: -3.3458466 | AP87: -3.2010143 | AQ87: -0.52486557
A88: 644 | B88: 2025 | C88: Ethiopia | D88: 2 | E88: 7.2218771 | F88: -5.2218771 | G88: -1.7105163 | H88: -0.06464973 | I88: 1.7296252 | J88: -2.4258071 | K88: 0.30213082 | L88: -1.339719 | M88: -0.58681773 | N88: 0.31415098 | O88: -0.19543619 | P88: -0.13027835 | Q88: -0.52486557 | R88: -1.7105163 | S88: 9.2569805 | T88: 0.15551987 | U88: 9.1014606 | V88: -0.06464973 | W88: 4.6758099 | X88: 0.084774447 | Y88: 4.5910354 | Z88: 1.7296252 | AA88: 2.4258071 | AB88: -0.3610543 | AC88: -0.24320733 | AD88: -1.5072874 | AE88: -2.3092236 | AF88: -1.0862016 | AG88: -1.28908 | AH88: -1.2566554 | AI88: -0.58986622 | AJ88: 0.063197321 | AK88: -1.5629607 | AL88: -0.26068983 | AM88: -0.31415098 | AN88: -0.19543619 | AO88: -0.34478373 | AP88: 0.084227022 | AQ88: -0.52486557
A89: 646 | B89: 2025 | C89: Gabon | D89: 5 | E89: 7.6194959 | F89: -2.6194959 | G89: -0.007880117 | H89: -0.9153575 | I89: -0.46913104 | J89: 0.46363347 | K89: 0.30213082 | L89: -1.0447961 | M89: -0.73078025 | N89: -0.50490185 | O89: 0.47209351 | P89: -0.41346503 | Q89: -0.52486557 | R89: -0.007880117 | S89: 9.2569805 | T89: 0.15551987 | U89: 9.1014606 | V89: -0.9153575 | W89: 4.6758099 | X89: 0.084774447 | Y89: 4.5910354 | Z89: -0.46913104 | AA89: -0.46363347 | AB89: -0.3610543 | AC89: -0.24320733 | AD89: -1.2655295 | AE89: -0.37414491 | AF89: -0.99649456 | AG89: -1.1621477 | AH89: -1.3717627 | AI89: -1.0986973 | AJ89: -0.52604003 | AK89: -0.74611918 | AL89: -0.92018155 | AM89: 0.50490185 | AN89: 0.47209351 | AO89: -0.52215575 | AP89: -0.30477431 | AQ89: -0.52486557
A90: 652 | B90: 2025 | C90: Ghana | D90: 6.3333333 | E90: 7.3490591 | F90: -1.0157258 | G90: -0.82204363 | H90: -0.053001596 | I90: 0.43026291 | J90: -2.3223416 | K90: -3.1881897 | L90: -0.17952081 | M90: -1.2840558 | N90: -0.028656012 | O90: 0.15920553 | P90: 0.23536424 | Q90: -0.52486557 | R90: -0.82204363 | S90: 9.2569805 | T90: 0.15551987 | U90: 9.1014606 | V90: -0.053001596 | W90: 4.6758099 | X90: 0.084774447 | Y90: 4.5910354 | Z90: 0.43026291 | AA90: 2.3223416 | AB90: 2.7696665 | AC90: 3.6067129 | AD90: 0.071310851 | AE90: -0.02716364 | AF90: -0.28333607 | AG90: -0.42954928 | AH90: -0.067762194 | AI90: -0.34062453 | AJ90: -0.93116108 | AK90: -1.094273 | AL90: -1.8267333 | AM90: 0.028656012 | AN90: 0.15920553 | AO90: 0.088128524 | AP90: 0.38259996 | AQ90: -0.52486557
A91: 662 | B91: 2025 | C91: Côte d'Ivoire | D91: 10.666667 | E91: 9.8343364 | F91: 0.83233031 | G91: -0.86557048 | H91: -0.11613547 | I91: 1.1956646 | J91: 0.36365943 | K91: 0.30213082 | L91: -0.71552671 | M91: -0.73889259 | N91: 0.06816564 | O91: -0.30139164 | P91: 0.065414525 | Q91: -0.52486557 | R91: -0.86557048 | S91: 9.2569805 | T91: 0.15551987 | U91: 9.1014606 | V91: -0.11613547 | W91: 4.6758099 | X91: 0.084774447 | Y91: 4.5910354 | Z91: 1.1956646 | AA91: -0.36365943 | AB91: -0.3610543 | AC91: -0.24320733 | AD91: -0.82452331 | AE91: -1.0563749 | AF91: -0.71038571 | AG91: -0.51869785 | AH91: -0.74916586 | AI91: -0.43401265 | AJ91: -0.4026192 | AK91: -0.98875435 | AL91: -0.8253042 | AM91: -0.06816564 | AN91: -0.30139164 | AO91: -0.15674275 | AP91: 0.2875718 | AQ91: -0.52486557
A92: 664 | B92: 2025 | C92: Kenya | D92: 7 | E92: 8.6955272 | F92: -1.6955272 | G92: -0.9934789 | H92: 0.048562497 | I92: 0.66436729 | J92: -0.15700689 | K92: 0.30213082 | L92: -0.86660985 | M92: -1.4208314 | N92: -0.27697507 | O92: -0.25956031 | P92: 0.068342862 | Q92: -0.52486557 | R92: -0.9934789 | S92: 9.2569805 | T92: 0.15551987 | U92: 9.1014606 | V92: 0.048562497 | W92: 4.6758099 | X92: 0.084774447 | Y92: 4.5910354 | Z92: 0.66436729 | AA92: 0.15700689 | AB92: -0.3610543 | AC92: -0.24320733 | AD92: -0.53815222 | AE92: -1.6723043 | AF92: -0.69009932 | AG92: -0.7113405 | AH92: -0.62669486 | AI92: -0.9610679 | AJ92: -0.85650714 | AK92: -1.004842 | AL92: -2.401145 | AM92: 0.27697507 | AN92: -0.25956031 | AO92: -0.11246165 | AP92: 0.24914738 | AQ92: -0.52486557
... A139: 968 | B139: 2025 | C139: Romania | D139: 13 | E139: 13.805774 | F139: -0.80577398 | G139: 0.66236237 | H139: 0.64015639 | I139: -0.52117364 | J139: -0.28325273 | K139: 0.30213082 | L139: 0.13682122 | M139: -0.31114523 | N139: -0.087721386 | O139: -0.68979583 | P139: 0.27671154 | Q139: -0.52486557 | R139: 0.66236237 | S139: 9.2569805 | T139: 0.15551987 | U139: 9.1014606 | V139: 0.64015639 | W139: 4.6758099 | X139: 0.084774447 | Y139: 4.5910354 | Z139: -0.52117364 | AA139: 0.28325273 | AB139: -0.3610543 | AC139: -0.24320733 | AD139: 0.2710415 | AE139: 0.15023786 | AF139: 0.12465041 | AG139: 0.11771164 | AH139: 0.27409631 | AI139: -0.11681042 | AJ139: -1.0522263 | AK139: 0.23135157 | AL139: -0.112561 | AM139: 0.087721386 | AN139: -0.68979583 | AO139: 0.26830423 | AP139: 0.28511884 | AQ139: -0.52486557

Sheet 2025_oct_raw
A1: cc | B1: year | C1: name | D1: rating | E1: ngdp_pc | F1: pppgdp_pc | G1: ngdp | H1: pppgdp | I1: rgdp_g | J1: inf | K1: fb | L1: gov_rev_gdp | M1: gov_debt_gdp | N1: cab | O1: pb | P1: ir_gdp | Q1: ir_rev | R1: gov_debt_rev | S1: growth_avg | T1: inf_avg | U1: fb_avg | V1: cab_avg | W1: import_cover | X1: extdebt_to_reserve | Y1: extdebt_gdp | Z1: reserve_gdp | AA1: voice_acct | AB1: pol_stab | AC1: gov_eff | AD1: reg_qual | AE1: rule_law | AF1: cont_corrupt | AG1: reserve_fx | AH1: non_reserve_fx | AI1: default_hist | AJ1: default_last | AK1: default_decay
A2: 111 | B2: 2025 | C2: United States | D2: 21 | E2: 89598.86 | F2: 89598.86 | G2: 30615.74 | H2: 30615.74 | I2: 2.017 | J2: 2.648 | K2: -7.365 | L2: 30.42 | M2: 125.05 | N2: -3.988 | O2: -3.8 | P2: 3.565 | Q2: 11.719264 | R2: 4.1107824 | S2: 2.2471 | T2: 3.3069 | U2: -8.4116 | V2: -3.6001 | W2: 0.13997025 | X2: 769.9124 | Y2: 100.06956 | Z2: 0.12997526 | AA2: 0.877519 | AB2: 0.029425 | AC2: 1.217201 | AD2: 1.393733 | AE2: 1.327678 | AF2: 1.123433 | AG2: 1 | AH2: 0 | AI2: 0 | AJ2: 0 | AK2: 0
A3: 112 | B3: 2025 | C3: United Kingdom | D3: 19.333333 | E3: 56660.87 | F3: 63759.05 | G3: 3958.78 | H3: 4454.716 | I3: 1.308 | J3: 3.35 | K3: -4.336 | L3: 39.354 | M3: 103.361 | N3: -3.091 | O3: -1.815 | P3: 2.521 | Q3: 6.4059562 | R3: 2.626442 | S3: 1.1599 | T3: 3.4349 | U3: -5.3442 | V3: -2.5108 | W3: 1.71602 | X3: 87.590579 | Y3: 272.38362 | Z3: 3.1097365 | AA3: 1.261624 | AB3: 0.514936 | AC3: 1.161143 | AD3: 1.536567 | AE3: 1.398366 | AF3: 1.480914 | AG3: 1 | AH3: 0 | AI3: 0 | AJ3: 0 | AK3: 0
A4: 122 | B4: 2025 | C4: Austria | D4: 20.666667 | E4: 61694.03 | F4: 74852.29 | G4: 566.456 | H4: 687.271 | I4: 0.27 | J4: 3.626 | K4: -4.248 | L4: 51.876 | M4: 82.025 | N4: 1.793 | O4: -3.009 | P4: 1.239 | Q4: 2.3883877 | R4: 1.5811743 | S4: 0.6701 | T4: 3.5142 | U4: -4.3472 | V4: 1.9193 | W4: 0.287666 | X4: 167.90897 | Y4: 167.33073 | Z4: 0.99655622 | AA4: 1.411248 | AB4: 0.727989 | AC4: 1.326681 | AD4: 1.36137 | AE4: 1.746565 | AF4: 1.133653 | AG4: 1 | AH4: 0 | AI4: 0 | AJ4: 0 | AK4: 0
A5: 124 | B5: 2025 | C5: Belgium | D5: 19 | E5: 60417.88 | F5: 75882.37 | G5: 716.98 | H5: 900.497 | I5: 1.065 | J5: 0.29 | K5: -5.528 | L5: 49.72 | M5: 107.502 | N5: -0.909 | O5: -3.72 | P5: 1.808 | Q5: 3.6363636 | R5: 2.162148 | S5: 1.3661 | T5: 3.0247 | U5: -5.5292 | V5: -0.3868 | W5: 0.2 | X5: 254.35168 | Y5: 244.21014 | Z5: 0.96012788 | AA5: 1.325729 | AB5: 0.403853 | AC5: 1.037022 | AD5: 1.168225 | AE5: 1.295375 | AF5: 1.336844 | AG5: 1 | AH5: 0 | AI5: 0 | AJ5: 0 | AK5: 0
A6: 128 | B6: 2025 | C6: Denmark | D6: 22 | E6: 76580.72 | F6: 84762.88 | G6: 459.612 | H6: 508.718 | I6: 1.84 | J6: 1.797 | K6: 1.8 | L6: 50.768 | M6: 29.629 | N6: 12.235 | O6: 1 | P6: -0.8 | Q6: -1.5757958 | R6: 0.58361566 | S6: 1.8013 | T6: 2.5614 | U6: 1.7198 | V6: 10.792 | W6: 9.1 | X6: 5.6749907 | Y6: 152.46042 | Z6: 26.865316 | AA6: 1.664699 | AB6: 0.850848 | AC6: 2.015649 | AD6: 1.83952 | AE6: 1.908936 | AF6: 2.376053 | AG6: 1 | AH6: 0 | AI6: 0 | AJ6: 0 | AK6: 0
A7: 132 | B7: 2025 | C7: France | D7: 18.666667 | E7: 48981.97 | F7: 66060.53 | G7: 3361.557 | H7: 4533.633 | I7: 0.671 | J7: 1.461 | K7: -5.441 | L7: 51.882 | M7: 116.505 | N7: -0.076 | O7: -3.394 | P7: 2.047 | Q7: 3.9454917 | R7: 2.2455765 | S7: 0.9994 | T7: 2.5541 | U7: -6.1504 | V7: -0.4859 | W7: 0.641487 | X7: 150.1646 | Y7: 261.99893 | Z7: 1.744745 | AA7: 1.154601 | AB7: 0.343698 | AC7: 1.144626 | AD7: 1.153505 | AE7: 1.180571 | AF7: 1.184822 | AG7: 1 | AH7: 0 | AI7: 0 | AJ7: 0 | AK7: 0
A8: 134 | B8: 2025 | C8: Germany | D8: 22 | E8: 59925.32 | F8: 73553.3 | G8: 5013.574 | H8: 6153.741 | I8: 0.191 | J8: 1.749 | K8: -2.523 | L8: 47.923 | M8: 64.421 | N8: 5.419 | O8: -1.609 | P8: 0.914 | Q8: 1.9072262 | R8: 1.3442606 | S8: 0.5016 | T8: 3.1089 | U8: -3.2632 | V8: 5.2375 | W8: 0.3399455 | X8: 211.72603 | Y8: 156.58172 | Z8: 0.73954873 | AA8: 1.461386 | AB8: 0.586989 | AC8: 1.185417 | AD8: 1.456975 | AE8: 1.551208 | AF8: 1.664166 | AG8: 1 | AH8: 0 | AI8: 0 | AJ8: 0 | AK8: 0
A9: 136 | B9: 2025 | C9: Italy | D9: 14.333333 | E9: 43161.2 | F9: 63125.68 | G9: 2543.677 | H9: 3720.271 | I9: 0.546 | J9: 1.531 | K9: -3.302 | L9: 47.381 | M9: 136.837 | N9: 0.97 | O9: 0.52 | P9: 3.822 | Q9: 8.0665246 | R9: 2.8880142 | S9: 0.9601 | T9: 2.8296 | U9: -5.0607 | V9: 1.2157 | W9: 1.0765297 | X9: 57.603884 | Y9: 125.50182 | Z9: 2.1787042 | AA9: 1.115531 | AB9: 0.583321 | AC9: 0.611037 | AD9: 0.644032 | AE9: 0.390359 | AF9: 0.550129 | AG9: 1 | AH9: 0 | AI9: 0 | AJ9: 0 | AK9: 0
A10: 137 | B10: 2025 | C10: Luxembourg | D10: 22 | E10: 146818.03 | F10: 152394.65 | G10: 100.642 | H10: 104.465 | I10: 1.177 | J10: 1.208 | K10: -1.056 | L10: 47.542 | M10: 27.121 | N10: 12.163 | O10: -1.197 | P10: -0.141 | Q10: -0.29657987 | R10: 0.57046401 | S10: 1.5626 | T10: 2.6788 | U10: -1.01 | V10: 9.0605 | W10: 1.3685067 | X10: 25405.689 | Y10: 5191.9166 | Z10: 0.20436039 | AA10: 1.632663 | AB10: 1.054002 | AC10: 1.914213 | AD10: 1.929063 | AE10: 1.752435 | AF10: 1.926659 | AG10: 1 | AH10: 0 | AI10: 0 | AJ10: 0 | AK10: 0
A11: 138 | B11: 2025 | C11: Netherlands | D11: 22 | E11: 73173.72 | F11: 84035.22 | G11: 1320.635 | H11: 1516.663 | I11: 1.433 | J11: 2.465 | K11: -2.111 | L11: 43.221 | M11: 44.037 | N11: 9.531 | O11: -1.513 | P11: 0.598 | Q11: 1.3835867 | R11: 1.0188797 | S11: 1.4593 | T11: 3.4562 | U11: -1.9184 | V11: 8.7957 | W11: 0.12186675 | X11: 705.54015 | Y11: 361.6077 | Z11: 0.51252604 | AA11: 1.556264 | AB11: 0.658282 | AC11: 1.625532 | AD11: 1.790966 | AE11: 1.642504 | AF11: 1.8671 | AG11: 1 | AH11: 0 | AI11: 0 | AJ11: 0 | AK11: 0
A12: 142 | B12: 2025 | C12: Norway | D12: 22 | E12: 91883.69 | F12: 106694.12 | G12: 517.102 | H12: 600.452 | I12: 1.181 | J12: 2.2 | K12: 12.736 | L12: 61.676 | M12: 42.72 | N12: 16.189 | O12: 9.684 | P12: -3.052 | Q12: -4.9484402 | R12: 0.69265192 | S12: 1.5077 | T12: 2.9804 | U12: 11.5362 | V12: 15.4701 | W12: 9.3574198 | X12: 9.5447215 | Y12: 165.83773 | Z12: 17.374811 | AA12: 1.777254 | AB12: 0.892857 | AC12: 1.799935 | AD12: 1.597523 | AE12: 1.833982 | AF12: 2.113522 | AG12: 1 | AH12: 0 | AI12: 0 | AJ12: 0 | AK12: 0
A13: 144 | B13: 2025 | C13: Sweden | D13: 22 | E13: 62036.06 | F13: 73069.51 | G13: 662.318 | H13: 780.115 | I13: 0.75 | J13: 1.6 | K13: -1.372 | L13: 47.659 | M13: 34.163 | N13: 5.838 | O13: -1.398 | P13: -0.026 | Q13: -0.054554229 | R13: 0.71682159 | S13: 1.2996 | T13: 2.8747 | U13: -0.8694 | V13: 5.482 | W13: 2.603962 | X13: 26.516697 | Y13: 181.36888 | Z13: 6.8397991 | AA13: 1.574832 | AB13: 0.758365 | AC13: 1.601383 | AD13: 1.718017 | AE13: 1.604023 | AF13: 2.028246 | AG13: 1 | AH13: 0 | AI13: 0 | AJ13: 0 | AK13: 0
... A79: 582 | B79: 2025 | C79: Vietnam | D79: 11.666667 | E79: 4744.725 | F79: 17688.249 | G79: 484.726 | H79: 1807.05 | I79: 6.457 | J79: 3.39 | K79: -3.259 | L79: 18.438 | M79: 32.045 | N79: 4.047 | O79: -2.408 | P79: 0.851 | Q79: 4.6154681 | R79: 1.7379868 | S79: 5.4825 | T79: 2.9522 | U79: -1.8725 | V79: 2.6299 | W79: 3.1 | X79: 1.5445797 | Y79: 28.569297 | Z79: 18.496486 | AA79: -1.241854 | AB79: -0.036381 | AC79: 0.126467 | AD79: -0.382608 | AE79: -0.085472 | AF79: -0.415814 | AG79: 0 | AH79: 1 | AI79: 0 | AJ79: 0 | AK79: 0
A80: 612 | B80: 2025 | C80: Algeria | E80: 6095.32 | F80: 18509.45 | G80: 288.013 | H80: 874.599 | I80: 3.357 | J80: 4.608 | K80: -11.543 | L80: 24.083 | M80: 54.048 | N80: -3.679 | O80: -10.513 | P80: 1.03 | Q80: 4.2768758 | R80: 2.2442387 | S80: 2.44 | T80: 5.1079 | U80: -9.3296 | V80: -2.148 | W80: 16.328367 | X80: 0.1311137 | Y80: 2.7670768 | Z80: 21.104406 | AA80: -0.979884 | AB80: -0.577885 | AC80: -0.670135 | AD80: -0.948087 | AE80: -0.678364 | AF80: -0.589308 | AG80: 0 | AH80: 1 | AI80: 0 | AJ80: 0 | AK80: 0
A81: 614 | B81: 2025 | C81: Angola | D81: 7 | E81: 2930.687 | F81: 10216.56 | G81: 115.167 | H81: 401.48 | I81: 2.09 | J81: 20.01 | K81: -2.759 | L81: 15.563 | M81: 62.366 | N81: 0.94 | O81: 1.609 | P81: 4.368 | Q81: 28.066568 | R81: 4.0073251 | S81: 2.0472 | T81: 17.6968 | U81: -1.4375 | V81: 3.2515 | W81: 11.51001 | X81: 4.9078467 | Y81: 47.329432 | Z81: 9.6436247 | AA81: -0.737252 | AB81: -0.341505 | AC81: -1.00891 | AD81: -0.761388 | AE81: -1.099066 | AF81: -0.60992 | AG81: 0 | AH81: 1 | AI81: 0 | AJ81: 0 | AK81: 0
A82: 616 | B82: 2025 | C82: Botswana | D82: 15 | E82: 6943.157 | F82: 19053.1 | G82: 19.186 | H82: 52.65 | I82: -0.877 | J82: 5 | K82: -10.148 | L82: 24.085 | M82: 38.798 | N82: -7.6 | O82: -8.562 | P82: 1.586 | Q82: 6.5850114 | R82: 1.6108781 | S82: 2.4788 | T82: 5.156 | U82: -6.4629 | V82: -3.7728 | W82: 6.18494 | X82: 1.6189004 | Y82: 29.081344 | Z82: 17.963639 | AA82: 0.504057 | AB82: 1.03844 | AC82: 0.430828 | AD82: 0.497435 | AE82: 0.390436 | AF82: 0.685792 | AG82: 0 | AH82: 1 | AI82: 0 | AJ82: 0 | AK82: 0
A83: 622 | B83: 2025 | C83: Cameroon | D83: 7 | E83: 2027.399 | F83: 5791.09 | G83: 60.577 | H83: 173.034 | I83: 3.796 | J83: 3.6 | K83: -0.839 | L83: 15.044 | M83: 37.916 | N83: -3.361 | O83: 0.386 | P83: 1.225 | Q83: 8.1427812 | R83: 2.5203403 | S83: 3.5289 | T83: 3.8096 | U83: -1.4824 | V83: -3.6388 | W83: 6.99985 | X83: 4.0494162 | Y83: 32.143226 | Z83: 7.9377432 | AA83: -1.066397 | AB83: -1.400436 | AC83: -0.906263 | AD83: -0.913473 | AE83: -1.038198 | AF83: -1.16256 | AG83: 0 | AH83: 1 | AI83: 0 | AJ83: 0 | AK83: 0
A84: 624 | B84: 2025 | C84: Cabo Verde | D84: 8 | E84: 5671.001 | F84: 12335.268 | G84: 2.915 | H84: 6.34 | I84: 5.186 | J84: 2 | K84: -1.584 | L84: 26.489 | M84: 106.018 | N84: -0.872 | O84: 0.442 | P84: 2.026 | Q84: 7.6484579 | R84: 4.0023406 | S84: 3.8399 | T84: 2.4931 | U84: -2.5397 | V84: -4.2984 | W84: 7.938458 | X84: 3.0036258 | Y84: 76.876816 | Z84: 25.594672 | AA84: 0.958101 | AB84: 0.903246 | AC84: 0.013677 | AD84: 0.242903 | AE84: 0.400106 | AF84: 0.984857 | AG84: 0 | AH84: 1 | AI84: 0 | AJ84: 0 | AK84: 0
A85: 634 | B85: 2025 | C85: Republic of Congo | D85: 5.6666667 | E85: 2419.764 | F85: 6515.358 | G85: 15.695 | H85: 42.259 | I85: 2.654 | J85: 3.4 | K85: 3.231 | L85: 25.13 | M85: 93.145 | N85: -5.865 | O85: 6.677 | P85: 3.446 | Q85: 13.712694 | R85: 3.7065261 | S85: 1.6781 | T85: 3.284 | U85: 3.802 | V85: 1.4753 | W85: 2.085175 | X85: 13.710896 | Y85: 55.278018 | Z85: 4.0316854 | AA85: -1.154167 | AB85: 0.019162 | AC85: -1.334287 | AD85: -1.239406 | AE85: -1.020587 | AF85: -1.345279 | AG85: 0 | AH85: 1 | AI85: 1 | AJ85: 1 | AK85: 0.27538748
A86: 636 | B86: 2025 | C86: Democratic Republic of the Congo | D86: 7 | E86: 772.032 | F86: 1974.505 | G86: 82.262 | H86: 210.388 | I86: 5.28 | J86: 7.855 | K86: -2.21 | L86: 14.557 | M86: 19.07 | N86: -3.261 | O86: -1.727 | P86: 0.483 | Q86: 3.3179913 | R86: 1.3100227 | S86: 5.4394 | T86: 10.5272 | U86: -1.7401 | V86: -2.9986 | W86: 2.37 | X86: 1.8533318 | Y86: 16.974016 | Z86: 9.1586489 | AA86: -1.21333 | AB86: -2.044862 | AC86: -1.689066 | AD86: -1.408576 | AE86: -1.670736 | AF86: -1.480512 | AG86: 0 | AH86: 1 | AI86: 0 | AJ86: 0 | AK86: 0
A87: 638 | B87: 2025 | C87: Benin | D87: 9.3333333 | E87: 1635.236 | F87: 4719.244 | G87: 24.402 | H87: 70.423 | I87: 7.041 | J87: 2.1 | K87: -2.9 | L87: 15.569 | M87: 50.741 | N87: -5.546 | O87: -1.017 | P87: 1.883 | Q87: 12.094547 | R87: 3.2591046 | S87: 6.385 | T87: 1.9023 | U87: -3.7639 | V87: -5.0411 | W87: 0.025202 | X87: 1274.405 | Y87: 63.078947 | Z87: 0.049496783 | AA87: -0.218987 | AB87: -0.346559 | AC87: -0.218984 | AD87: -0.295836 | AE87: -0.50571 | AF87: -0.049579 | AG87: 0 | AH87: 1 | AI87: 0 | AJ87: 0 | AK87: 0
A88: 644 | B88: 2025 | C88: Ethiopia | D88: 2 | E88: 994.042 | F88: 4419.777 | G88: 109.492 | H88: 486.83 | I88: 7.224 | J88: 9.803 | K88: -1.547 | L88: 10.46 | M88: 46.742 | N88: -2.878 | O88: -0.467 | P88: 1.08 | Q88: 10.325048 | R88: 4.4686424 | S88: 7.1743 | T88: 17.3663 | U88: -2.2592 | V88: -3.0492 | W88: 3.066139 | X88: 8.9491835 | Y88: 32.178976 | Z88: 3.5957443 | AA88: -1.060667 | AB88: -1.969568 | AC88: -0.768662 | AD88: -1.021079 | AE88: -0.670203 | AF88: -0.465062 | AG88: 0 | AH88: 1 | AI88: 0 | AJ88: 0 | AK88: 0
A89: 646 | B89: 2025 | C89: Gabon | D89: 5 | E89: 9303.04 | F89: 24738.8 | G89: 21.455 | H89: 57.054 | I89: 1.874 | J89: 1.95 | K89: -5.406 | L89: 20.361 | M89: 76.223 | N89: 1.775 | O89: -1.968 | P89: 3.438 | Q89: 16.885222 | R89: 3.7435784 | S89: 2.1382 | T89: 2.2217 | U89: -4.6105 | V89: 2.1131 | W89: 3.520552 | X89: 7.4240673 | Y89: 47.943594 | Z89: 6.4578609 | AA89: -0.919151 | AB89: -0.335527 | AC89: -0.779809 | AD89: -0.70482 | AE89: -0.872693 | AF89: -1.015528 | AG89: 0 | AH89: 1 | AI89: 0 | AJ89: 0 | AK89: 0
A90: 652 | B90: 2025 | C90: Ghana | D90: 6.3333333 | E90: 3193.071 | F90: 8410.294 | G90: 111.963 | H90: 294.901 | I90: 4.026 | J90: 11.978 | K90: -2.728 | L90: 16.141 | M90: 59.081 | N90: 1.808 | O90: 1.453 | P90: 4.181 | Q90: 25.90298 | R90: 3.6603061 | S90: 4.1982 | T90: 16.824 | U90: -6.2271 | V90: -0.3066 | W90: 6.70703 | X90: 4.9372148 | Y90: 54.160278 | Z90: 10.969804 | AA90: 0.410352 | AB90: -0.021621 | AC90: -0.092662 | AD90: -0.180652 | AE90: -0.099638 | AF90: -0.099021 | AG90: 0 | AH90: 1 | AI90: 1 | AJ90: 1 | AK90: 0.61656529
A91: 662 | B91: 2025 | C91: Côte d'Ivoire | D91: 10.666667 | E91: 3015.643 | F91: 8112.67 | G91: 99.207 | H91: 266.886 | I91: 6.4 | J91: 1 | K91: -3.012 | L91: 17.42 | M91: 55.596 | N91: -2.148 | O91: -0.235 | P91: 2.777 | Q91: 15.941447 | R91: 3.191504 | S91: 5.9513 | T91: 2.7457 | U91: -4.118 | V91: -3.8686 | W91: 6.508232 | X91: 5.4236561 | Y91: 43.173798 | Z91: 7.9602758 | AA91: -0.375481 | AB91: -0.631788 | AC91: -0.359512 | AD91: -0.116081 | AE91: -0.461197 | AF91: -0.313007 | AG91: 0 | AH91: 1 | AI91: 0 | AJ91: 0 | AK91: 0
A92: 664 | B92: 2025 | C92: Kenya | D92: 7 | E92: 2549.284 | F92: 7556.076 | G92: 136.014 | H92: 403.146 | I92: 4.815 | J92: 4.421 | K92: -5.964 | L92: 17.225 | M92: 68.019 | N92: -2.813 | O92: -0.518 | P92: 5.446 | Q92: 31.616836 | R92: 3.9488534 | S92: 4.7344 | T92: 5.4747 | U92: -5.9292 | V92: -3.5451 | W92: 5.44422 | X92: 6.4230284 | Y92: 51.399584 | Z92: 8.0023909 | AA92: -0.124171 | AB92: -0.937772 | AC92: -0.303605 | AD92: -0.390807 | AE92: -0.326222 | AF92: -0.770913 | AG92: 0 | AH92: 1 | AI92: 0 | AJ92: 0 | AK92: 0
... A139: 968 | B139: 2025 | C139: Romania | D139: 13 | E139: 22436.007 | F139: 48847.46 | G139: 422.508 | H139: 919.881 | I139: 0.96 | J139: 8.538 | K139: -8.156 | L139: 32.209 | M139: 61.207 | N139: -7.97 | O139: -5.305 | P139: 2.851 | Q139: 8.8515632 | R139: 1.9003074 | S139: 2.019 | T139: 6.1364 | U139: -6.7102 | V139: -6.8723 | W139: 5.353269 | X139: 3.102519 | Y139: 41.58842 | Z139: 13.404727 | AA139: 0.50318 | AB139: 0.373644 | AC139: -0.092666 | AD139: 0.318901 | AE139: 0.437426 | AF139: 0.040495 | AG139: 0 | AH139: 1 | AI139: 0 | AJ139: 0 | AK139: 0

Sheet 2025_dec_raw
A1: cc | B1: year | C1: name | D1: rating | E1: ngdp_pc | F1: pppgdp_pc | G1: ngdp | H1: pppgdp | I1: rgdp_g | J1: inf | K1: fb | L1: gov_rev_gdp | M1: gov_debt_gdp | N1: cab | O1: pb | P1: ir_gdp | Q1: ir_rev | R1: gov_debt_rev | S1: growth_avg | T1: inf_avg | U1: fb_avg | V1: cab_avg | W1: import_cover | X1: extdebt_to_reserve | Y1: extdebt_gdp | Z1: reserve_gdp | AA1: voice_acct | AB1: pol_stab | AC1: gov_eff | AD1: reg_qual | AE1: rule_law | AF1: cont_corrupt | AG1: reserve_fx | AH1: non_reserve_fx | AI1: default_hist | AJ1: default_last | AK1: default_decay
A2: 111 | B2: 2025 | C2: United States | D2: 21 | E2: 89598.86 | F2: 89598.86 | G2: 30615.74 | H2: 30615.74 | I2: 2.017 | J2: 2.648 | K2: -7.365 | L2: 30.42 | M2: 125.05 | N2: -3.988 | O2: -3.8 | P2: 3.565 | Q2: 11.719264 | R2: 4.1107824 | S2: 2.2471 | T2: 3.3069 | U2: -8.4116 | V2: -3.6001 | W2: 0.13875075 | X2: 767.31128 | Y2: 98.670782 | Z2: 0.1285929 | AA2: 0.886956 | AB2: -0.095113 | AC2: 1.359979 | AD2: 1.352489 | AE2: 0.96179 | AF2: 1.086891 | AG2: 1 | AH2: 0 | AI2: 0 | AJ2: 0 | AK2: 0
A3: 112 | B3: 2025 | C3: United Kingdom | D3: 19.333333 | E3: 56660.87 | F3: 63759.05 | G3: 3958.78 | H3: 4454.716 | I3: 1.308 | J3: 3.35 | K3: -4.336 | L3: 39.354 | M3: 103.361 | N3: -3.091 | O3: -1.815 | P3: 2.521 | Q3: 6.4059562 | R3: 2.626442 | S3: 1.1599 | T3: 3.4349 | U3: -5.3442 | V3: -2.5108 | W3: 1.7205985 | X3: 88.240217 | Y3: 271.27694 | Z3: 3.0743004 | AA3: 1.300612 | AB3: 0.257709 | AC3: 1.18491 | AD3: 1.511238 | AE3: 1.269914 | AF3: 1.509755 | AG3: 1 | AH3: 0 | AI3: 0 | AJ3: 0 | AK3: 0
A4: 122 | B4: 2025 | C4: Austria | D4: 20.666667 | E4: 61694.03 | F4: 74852.29 | G4: 566.456 | H4: 687.271 | I4: 0.27 | J4: 3.626 | K4: -4.248 | L4: 51.876 | M4: 82.025 | N4: 1.793 | O4: -3.009 | P4: 1.239 | Q4: 2.3883877 | R4: 1.5811743 | S4: 0.6701 | T4: 3.5142 | U4: -4.3472 | V4: 1.9193 | W4: 0.276772 | X4: 166.89763 | Y4: 165.64164 | Z4: 0.99247454 | AA4: 1.405457 | AB4: 0.491598 | AC4: 1.514511 | AD4: 1.351062 | AE4: 1.67774 | AF4: 1.294447 | AG4: 1 | AH4: 0 | AI4: 0 | AJ4: 0 | AK4: 0
A5: 124 | B5: 2025 | C5: Belgium | D5: 19 | E5: 60417.88 | F5: 75882.37 | G5: 716.98 | H5: 900.497 | I5: 1.065 | J5: 0.29 | K5: -5.528 | L5: 49.72 | M5: 107.502 | N5: -0.909 | O5: -3.72 | P5: 1.808 | Q5: 3.6363636 | R5: 2.162148 | S5: 1.3661 | T5: 3.0247 | U5: -5.5292 | V5: -0.3868 | W5: 0.2 | X5: 272.6101 | Y5: 240.5744 | Z5: 0.88248526 | AA5: 1.497214 | AB5: 0.121453 | AC5: 1.19474 | AD5: 1.243548 | AE5: 1.282799 | AF5: 1.468781 | AG5: 1 | AH5: 0 | AI5: 0 | AJ5: 0 | AK5: 0
A6: 128 | B6: 2025 | C6: Denmark | D6: 22 | E6: 76580.72 | F6: 84762.88 | G6: 459.612 | H6: 508.718 | I6: 1.84 | J6: 1.797 | K6: 1.8 | L6: 50.768 | M6: 29.629 | N6: 12.235 | O6: 1 | P6: -0.8 | Q6: -1.5757958 | R6: 0.58361566 | S6: 1.8013 | T6: 2.5614 | U6: 1.7198 | V6: 10.792 | W6: 8.975 | X6: 5.5956086 | Y6: 139.72582 | Z6: 24.970621 | AA6: 1.894941 | AB6: 0.768876 | AC6: 1.912899 | AD6: 1.930706 | AE6: 2.004315 | AF6: 2.287475 | AG6: 1 | AH6: 0 | AI6: 0 | AJ6: 0 | AK6: 0
A7: 132 | B7: 2025 | C7: France | D7: 18.666667 | E7: 48981.97 | F7: 66060.53 | G7: 3361.557 | H7: 4533.633 | I7: 0.671 | J7: 1.461 | K7: -5.441 | L7: 51.882 | M7: 116.505 | N7: -0.076 | O7: -3.394 | P7: 2.047 | Q7: 3.9454917 | R7: 2.2455765 | S7: 0.9994 | T7: 2.5541 | U7: -6.1504 | V7: -0.4859 | W7: 0.4811545 | X7: 262.22262 | Y7: 261.74052 | Z7: 0.99816149 | AA7: 1.148668 | AB7: -0.241365 | AC7: 1.200701 | AD7: 1.146153 | AE7: 0.97866 | AF7: 1.218224 | AG7: 1 | AH7: 0 | AI7: 0 | AJ7: 0 | AK7: 0
A8: 134 | B8: 2025 | C8: Germany | D8: 22 | E8: 59925.32 | F8: 73553.3 | G8: 5013.574 | H8: 6153.741 | I8: 0.191 | J8: 1.749 | K8: -2.523 | L8: 47.923 | M8: 64.421 | N8: 5.419 | O8: -1.609 | P8: 0.914 | Q8: 1.9072262 | R8: 1.3442606 | S8: 0.5016 | T8: 3.1089 | U8: -3.2632 | V8: 5.2375 | W8: 0.338555 | X8: 210.83354 | Y8: 155.83747 | Z8: 0.7391493 | AA8: 1.598152 | AB8: 0.124267 | AC8: 1.546299 | AD8: 1.498062 | AE8: 1.625784 | AF8: 1.773421 | AG8: 1 | AH8: 0 | AI8: 0 | AJ8: 0 | AK8: 0
A9: 136 | B9: 2025 | C9: Italy | D9: 14.333333 | E9: 43161.2 | F9: 63125.68 | G9: 2543.677 | H9: 3720.271 | I9: 0.546 | J9: 1.531 | K9: -3.302 | L9: 47.381 | M9: 136.837 | N9: 0.97 | O9: 0.52 | P9: 3.822 | Q9: 8.0665246 | R9: 2.8880142 | S9: 0.9601 | T9: 2.8296 | U9: -5.0607 | V9: 1.2157 | W9: 1.0670373 | X9: 57.735417 | Y9: 125.0524 | Z9: 2.1659565 | AA9: 1.067348 | AB9: 0.308704 | AC9: 0.792289 | AD9: 0.640149 | AE9: 0.619204 | AF9: 0.553162 | AG9: 1 | AH9: 0 | AI9: 0 | AJ9: 0 | AK9: 0
A10: 137 | B10: 2025 | C10: Luxembourg | D10: 22 | E10: 146818.03 | F10: 152394.65 | G10: 100.642 | H10: 104.465 | I10: 1.177 | J10: 1.208 | K10: -1.056 | L10: 47.542 | M10: 27.121 | N10: 12.163 | O10: -1.197 | P10: -0.141 | Q10: -0.29657987 | R10: 0.57046401 | S10: 1.5626 | T10: 2.6788 | U10: -1.01 | V10: 9.0605 | W10: 1.3284887 | X10: 25405.689 | Y10: 5191.9166 | Z10: 0.20436039 | AA10: 1.665328 | AB10: 1.073053 | AC10: 2.039714 | AD10: 1.838652 | AE10: 1.761768 | AF10: 2.01576 | AG10: 1 | AH10: 0 | AI10: 0 | AJ10: 0 | AK10: 0
A11: 138 | B11: 2025 | C11: Netherlands | D11: 22 | E11: 73173.72 | F11: 84035.22 | G11: 1320.635 | H11: 1516.663 | I11: 1.433 | J11: 2.465 | K11: -2.111 | L11: 43.221 | M11: 44.037 | N11: 9.531 | O11: -1.513 | P11: 0.598 | Q11: 1.3835867 | R11: 1.0188797 | S11: 1.4593 | T11: 3.4562 | U11: -1.9184 | V11: 8.7957 | W11: 0.12783075 | X11: 686.09398 | Y11: 361.09878 | Z11: 0.52631096 | AA11: 1.653663 | AB11: 0.42812 | AC11: 1.751997 | AD11: 1.721827 | AE11: 1.706922 | AF11: 1.910013 | AG11: 1 | AH11: 0 | AI11: 0 | AJ11: 0 | AK11: 0
A12: 142 | B12: 2025 | C12: Norway | D12: 22 | E12: 91883.69 | F12: 106694.12 | G12: 517.102 | H12: 600.452 | I12: 1.181 | J12: 2.2 | K12: 12.736 | L12: 61.676 | M12: 42.72 | N12: 16.189 | O12: 9.684 | P12: -3.052 | Q12: -4.9484402 | R12: 0.69265192 | S12: 1.5077 | T12: 2.9804 | U12: 11.5362 | V12: 15.4701 | W12: 9.176762 | X12: 9.665457 | Y12: 146.94052 | Z12: 15.202646 | AA12: 1.929425 | AB12: 0.903265 | AC12: 1.843057 | AD12: 1.670454 | AE12: 1.949455 | AF12: 1.961009 | AG12: 1 | AH12: 0 | AI12: 0 | AJ12: 0 | AK12: 0
A13: 144 | B13: 2025 | C13: Sweden | D13: 22 | E13: 62036.06 | F13: 73069.51 | G13: 662.318 | H13: 780.115 | I13: 0.75 | J13: 1.6 | K13: -1.372 | L13: 47.659 | M13: 34.163 | N13: 5.838 | O13: -1.398 | P13: -0.026 | Q13: -0.054554229 | R13: 0.71682159 | S13: 1.2996 | T13: 2.8747 | U13: -0.8694 | V13: 5.482 | W13: 2.618979 | X13: 27.076694 | Y13: 181.15979 | Z13: 6.6906169 | AA13: 1.727794 | AB13: 0.603512 | AC13: 1.774695 | AD13: 1.671794 | AE13: 1.726701 | AF13: 1.967605 | AG13: 1 | AH13: 0 | AI13: 0 | AJ13: 0 | AK13: 0
... A79: 582 | B79: 2025 | C79: Vietnam | D79: 11.666667 | E79: 4744.725 | F79: 17688.249 | G79: 484.726 | H79: 1807.05 | I79: 6.457 | J79: 3.39 | K79: -3.259 | L79: 18.438 | M79: 32.045 | N79: 4.047 | O79: -2.408 | P79: 0.851 | Q79: 4.6154681 | R79: 1.7379868 | S79: 5.4825 | T79: 2.9522 | U79: -1.8725 | V79: 2.6299 | W79: 3.1 | X79: 1.5445797 | Y79: 28.569297 | Z79: 18.496486 | AA79: -1.098309 | AB79: 0.005674 | AC79: -0.092297 | AD79: -0.266806 | AE79: -0.313934 | AF79: -0.251699 | AG79: 0 | AH79: 1 | AI79: 0 | AJ79: 0 | AK79: 0
A80: 612 | B80: 2025 | C80: Algeria | E80: 6095.32 | F80: 18509.45 | G80: 288.013 | H80: 874.599 | I80: 3.357 | J80: 4.608 | K80: -11.543 | L80: 24.083 | M80: 54.048 | N80: -3.679 | O80: -10.513 | P80: 1.03 | Q80: 4.2768758 | R80: 2.2442387 | S80: 2.44 | T80: 5.1079 | U80: -9.3296 | V80: -2.148 | W80: 15.172553 | X80: 0.13929751 | Y80: 2.8387785 | Z80: 20.379248 | AA80: -1.048406 | AB80: -0.693588 | AC80: -0.251191 | AD80: -0.752647 | AE80: -0.696777 | AF80: -0.593395 | AG80: 0 | AH80: 1 | AI80: 0 | AJ80: 0 | AK80: 0
A81: 614 | B81: 2025 | C81: Angola | D81: 7 | E81: 2930.687 | F81: 10216.56 | G81: 115.167 | H81: 401.48 | I81: 2.09 | J81: 20.01 | K81: -2.759 | L81: 15.563 | M81: 62.366 | N81: 0.94 | O81: 1.609 | P81: 4.368 | Q81: 28.066568 | R81: 4.0073251 | S81: 2.0472 | T81: 17.6968 | U81: -1.4375 | V81: 3.2515 | W81: 10.51413 | X81: 4.7885308 | Y81: 46.909098 | Z81: 9.7961357 | AA81: -1.058893 | AB81: -0.573596 | AC81: -0.785191 | AD81: -0.77302 | AE81: -1.169741 | AF81: -0.622579 | AG81: 0 | AH81: 1 | AI81: 0 | AJ81: 0 | AK81: 0
A82: 616 | B82: 2025 | C82: Botswana | D82: 15 | E82: 6943.157 | F82: 19053.1 | G82: 19.186 | H82: 52.65 | I82: -0.877 | J82: 5 | K82: -10.148 | L82: 24.085 | M82: 38.798 | N82: -7.6 | O82: -8.562 | P82: 1.586 | Q82: 6.5850114 | R82: 1.6108781 | S82: 2.4788 | T82: 5.156 | U82: -6.4629 | V82: -3.7728 | W82: 6.18494 | X82: 1.6189004 | Y82: 29.081344 | Z82: 17.963639 | AA82: 0.295265 | AB82: 1.032294 | AC82: 0.416889 | AD82: 0.401934 | AE82: 0.312084 | AF82: 0.631141 | AG82: 0 | AH82: 1 | AI82: 0 | AJ82: 0 | AK82: 0
A83: 622 | B83: 2025 | C83: Cameroon | D83: 7 | E83: 2027.399 | F83: 5791.09 | G83: 60.577 | H83: 173.034 | I83: 3.796 | J83: 3.6 | K83: -0.839 | L83: 15.044 | M83: 37.916 | N83: -3.361 | O83: 0.386 | P83: 1.225 | Q83: 8.1427812 | R83: 2.5203403 | S83: 3.5289 | T83: 3.8096 | U83: -1.4824 | V83: -3.6388 | W83: 7.044861 | X83: 4.0494162 | Y83: 32.181931 | Z83: 7.9473013 | AA83: -1.241767 | AB83: -1.556804 | AC83: -0.800789 | AD83: -0.728672 | AE83: -1.253722 | AF83: -1.224285 | AG83: 0 | AH83: 1 | AI83: 0 | AJ83: 0 | AK83: 0
A84: 624 | B84: 2025 | C84: Cabo Verde | D84: 8 | E84: 5671.001 | F84: 12335.268 | G84: 2.915 | H84: 6.34 | I84: 5.186 | J84: 2 | K84: -1.584 | L84: 26.489 | M84: 106.018 | N84: -0.872 | O84: 0.442 | P84: 2.026 | Q84: 7.6484579 | R84: 4.0023406 | S84: 3.8399 | T84: 2.4931 | U84: -2.5397 | V84: -4.2984 | W84: 8.03784 | X84: 3.0566532 | Y84: 78.520441 | Z84: 25.688371 | AA84: 0.79108 | AB84: 0.769583 | AC84: 0.415195 | AD84: 0.045143 | AE84: 0.424201 | AF84: 0.940768 | AG84: 0 | AH84: 1 | AI84: 0 | AJ84: 0 | AK84: 0
A85: 634 | B85: 2025 | C85: Republic of Congo | D85: 5.6666667 | E85: 2419.764 | F85: 6515.358 | G85: 15.695 | H85: 42.259 | I85: 2.654 | J85: 3.4 | K85: 3.231 | L85: 25.13 | M85: 93.145 | N85: -5.865 | O85: 6.677 | P85: 3.446 | Q85: 13.712694 | R85: 3.7065261 | S85: 1.6781 | T85: 3.284 | U85: 3.802 | V85: 1.4753 | W85: 2.085175 | X85: 13.710896 | Y85: 55.342838 | Z85: 4.036413 | AA85: -1.314781 | AB85: -0.258415 | AC85: -1.110638 | AD85: -1.151562 | AE85: -1.17856 | AF85: -1.423569 | AG85: 0 | AH85: 1 | AI85: 1 | AJ85: 1 | AK85: 0.27538748
A86: 636 | B86: 2025 | C86: Democratic Republic of the Congo | D86: 7 | E86: 772.032 | F86: 1974.505 | G86: 82.262 | H86: 210.388 | I86: 5.28 | J86: 7.855 | K86: -2.21 | L86: 14.557 | M86: 19.07 | N86: -3.261 | O86: -1.727 | P86: 0.483 | Q86: 3.3179913 | R86: 1.3100227 | S86: 5.4394 | T86: 10.5272 | U86: -1.7401 | V86: -2.9986 | W86: 2.37 | X86: 1.8533318 | Y86: 15.35406 | Z86: 8.2845715 | AA86: -1.213613 | AB86: -2.119176 | AC86: -1.693445 | AD86: -1.284846 | AE86: -1.626605 | AF86: -1.51534 | AG86: 0 | AH86: 1 | AI86: 0 | AJ86: 0 | AK86: 0
A87: 638 | B87: 2025 | C87: Benin | D87: 9.3333333 | E87: 1635.236 | F87: 4719.244 | G87: 24.402 | H87: 70.423 | I87: 7.041 | J87: 2.1 | K87: -2.9 | L87: 15.569 | M87: 50.741 | N87: -5.546 | O87: -1.017 | P87: 1.883 | Q87: 12.094547 | R87: 3.2591046 | S87: 6.385 | T87: 1.9023 | U87: -3.7639 | V87: -5.0411 | W87: 0.024762 | X87: 1274.405 | Y87: 63.170143 | Z87: 0.049568342 | AA87: -0.380475 | AB87: -0.40301 | AC87: -0.185421 | AD87: -0.277262 | AE87: -0.412479 | AF87: -0.240715 | AG87: 0 | AH87: 1 | AI87: 0 | AJ87: 0 | AK87: 0
A88: 644 | B88: 2025 | C88: Ethiopia | D88: 2 | E88: 994.042 | F88: 4419.777 | G88: 109.492 | H88: 486.83 | I88: 7.224 | J88: 9.803 | K88: -1.547 | L88: 10.46 | M88: 46.742 | N88: -2.878 | O88: -0.467 | P88: 1.08 | Q88: 10.325048 | R88: 4.4686424 | S88: 7.1743 | T88: 17.3663 | U88: -2.2592 | V88: -3.0492 | W88: 4.207064 | X88: 5.7836049 | Y88: 32.119604 | Z88: 5.5535611 | AA88: -1.242397 | AB88: -1.884974 | AC88: -0.645991 | AD88: -0.833238 | AE88: -1.048924 | AF88: -0.437863 | AG88: 0 | AH88: 1 | AI88: 0 | AJ88: 0 | AK88: 0
A89: 646 | B89: 2025 | C89: Gabon | D89: 5 | E89: 9303.04 | F89: 24738.8 | G89: 21.455 | H89: 57.054 | I89: 1.874 | J89: 1.95 | K89: -5.406 | L89: 20.361 | M89: 76.223 | N89: 1.775 | O89: -1.968 | P89: 3.438 | Q89: 16.885222 | R89: 3.7435784 | S89: 2.1382 | T89: 2.2217 | U89: -4.6105 | V89: 2.1131 | W89: 2.290365 | X89: 10.216659 | Y89: 42.929574 | Z89: 4.201919 | AA89: -1.020837 | AB89: -0.276887 | AC89: -0.567155 | AD89: -0.723458 | AE89: -1.155705 | AF89: -0.936777 | AG89: 0 | AH89: 1 | AI89: 0 | AJ89: 0 | AK89: 0
A90: 652 | B90: 2025 | C90: Ghana | D90: 6.3333333 | E90: 3193.071 | F90: 8410.294 | G90: 111.963 | H90: 294.901 | I90: 4.026 | J90: 11.978 | K90: -2.728 | L90: 16.141 | M90: 59.081 | N90: 1.808 | O90: 1.453 | P90: 4.181 | Q90: 25.90298 | R90: 3.6603061 | S90: 4.1982 | T90: 16.824 | U90: -6.2271 | V90: -0.3066 | W90: 6.70703 | X90: 4.9372148 | Y90: 54.160278 | Z90: 10.969804 | AA90: 0.204316 | AB90: 0.011461 | AC90: 0.05958 | AD90: -0.089855 | AE90: 0.05397 | AF90: -0.193479 | AG90: 0 | AH90: 1 | AI90: 1 | AJ90: 1 | AK90: 0.61656529
A91: 662 | B91: 2025 | C91: Côte d'Ivoire | D91: 10.666667 | E91: 3015.643 | F91: 8112.67 | G91: 99.207 | H91: 266.886 | I91: 6.4 | J91: 1 | K91: -3.012 | L91: 17.42 | M91: 55.596 | N91: -2.148 | O91: -0.235 | P91: 2.777 | Q91: 15.941447 | R91: 3.191504 | S91: 5.9513 | T91: 2.7457 | U91: -4.118 | V91: -3.8686 | W91: 5.781229 | X91: 5.7880767 | Y91: 43.203143 | Z91: 7.4641621 | AA91: -0.616675 | AB91: -0.843833 | AC91: -0.315718 | AD91: -0.166957 | AE91: -0.578144 | AF91: -0.285047 | AG91: 0 | AH91: 1 | AI91: 0 | AJ91: 0 | AK91: 0
A92: 664 | B92: 2025 | C92: Kenya | D92: 7 | E92: 2549.284 | F92: 7556.076 | G92: 136.014 | H92: 403.146 | I92: 4.815 | J92: 4.421 | K92: -5.964 | L92: 17.225 | M92: 68.019 | N92: -2.813 | O92: -0.518 | P92: 5.446 | Q92: 31.616836 | R92: 3.9488534 | S92: 4.7344 | T92: 5.4747 | U92: -5.9292 | V92: -3.5451 | W92: 5.44422 | X92: 6.4230284 | Y92: 51.399584 | Z92: 8.0023909 | AA92: -0.354229 | AB92: -1.355682 | AC92: -0.29789 | AD92: -0.333568 | AE92: -0.464532 | AF92: -0.80183 | AG92: 0 | AH92: 1 | AI92: 0 | AJ92: 0 | AK92: 0
... A139: 968 | B139: 2025 | C139: Romania | D139: 13 | E139: 22436.007 | F139: 48847.46 | G139: 422.508 | H139: 919.881 | I139: 0.96 | J139: 8.538 | K139: -8.156 | L139: 32.209 | M139: 61.207 | N139: -7.97 | O139: -5.305 | P139: 2.851 | Q139: 8.8515632 | R139: 1.9003074 | S139: 2.019 | T139: 6.1364 | U139: -6.7102 | V139: -6.8723 | W139: 5.7591047 | X139: 2.842721 | Y139: 41.397257 | Z139: 14.562547 | AA139: 0.38736 | AB139: 0.158885 | AC139: 0.418125 | AD139: 0.383455 | AE139: 0.3711 | AF139: 0.025973 | AG139: 0 | AH139: 1 | AI139: 0 | AJ139: 0 | AK139: 0

Sheet coefficients
B1: old | C1: new
A2: const | B2: 12.695933 | C2: 12.691923
A3: wealth_factor | B3: 0.50759205 | C3: 0.53027255
A4: size_factor | B4: 1.6047043 | C4: 1.5749904
A5: growth_factor | B5: 0.14465344 | C5: 0.13008491
A6: inflation_factor | B6: 0.27236765 | C6: 0.30518536
A7: default_factor | B7: 0.81804555 | C7: 0.87885606
A8: governance_factor | B8: 2.8789941 | C8: 2.8044707
A9: fiscalperf_factor | B9: 0.65335151 | C9: 0.5796163
A10: govdebt_factor | B10: 0.91025734 | C10: 0.88139076
A11: extperf_factor | B11: 0.46481235 | C11: 0.47302681
A12: reservebuffer_factor | B12: 0.35395378 | C12: 0.3484954
A13: reservestatus_factor | B13: 0.45274543 | C13: 0.48221815

Sheet country_list
A1: Albania
A2: Algeria
A3: Angola
A4: Argentina
A5: Armenia
A6: Australia
A7: Austria
A8: Azerbaijan
A9: Bahrain
A10: Bangladesh
A11: Barbados
A12: Belarus
... A138: Zambia
